Workbook

Sheet Budget
A1: Totale kosten | D1: Kosten van thuis | G1: Kosten vooraf | J1: Kosten op reis | O1: Inkomsten
E2: Per maand | H2: Eenmalig | P2: Per maand
A3: Kosten van thuis | B3: =E27 -> 10455.75 | D3: Zorgverzekering | E3: =Verzekeringen!B4 -> 352 | G3: Uitrusting | H3: 0 | J3: Maaltijden en boodschappen | K3: Aantal dagen | L3: Dagbudget | M3: Totaal per land | O3: Salaris
A4: Kosten vooraf | B4: =H27 -> 21551.2 | D4: Woonhuis / reis verzekering | E4: =SUM(Verzekeringen!B5:B15) -> 344.15 | G4: Vaccinaties | H4: 500 | J4: Australië | K4: =COUNTA('Planning simpel'!D39:D86) -> 48 | L4: 75 | M4: =K4*L4 -> 3600 | O4: Salaris Maartje | P4: 4200
A5: Kosten op reis | B5: =M27 -> 60048.913 | D5: Pensioenpremie Bas | E5: 0 | G5: Visa | H5: 400 | J5: Nieuw-Zeeland | K5: =COUNTA('Planning simpel'!D87:D125) -> 39 | L5: 75 | M5: =K5*L5 -> 2925 | O5: Salaris Bas | P5: 3200
A6: Onvoorzien | B6: 5000 | D6: Pensioenpremie Maartje | E6: 0 | G6: Annulerings verzekering (extra) | H6: 400 | J6: Fiji | K6: =COUNTA('Planning simpel'!D31:D38) -> 8 | L6: 175 | M6: =K6*L6 -> 1400
A7: Totaal benodigd | B7: =SUM(B3:B6) -> 97055.863 | D7: Hypotheek | E7: 480 | J7: Thailand & SIN & Doha | K7: 23 | L7: 100 | M7: =K7*L7 -> 2300 | O7: Totaal | P7: =SUM(P4:P6) -> 7400
D8: BGHU | E8: 180 | J8: USA | K8: =COUNTA('Planning simpel'!D2:D29) -> 28 | L8: 150 | M8: =K8*L8 -> 4200 | O8: Overige
A9: Totaal al betaald | B9: =SUM(B10:B12) -> 43527.913 | D9: Nuts | E9: 100 | J9: Tanzania (inclucsief) | K9: =COUNTA('Planning simpel'!D148:D157) -> 10 | L9: 0 | M9: 0 | O9: Hypotheek teruggave | P9: 239
A10: Vluchten | B10: =H12 -> 12749 | D10: tv/internet/telefoon | E10: 120 | O10: Belasting
A11: Accomodatie | B11: =SUMIF('Planning simpel'!L2:L158, "Ja", 'Planning simpel'!I2:I159) -> 29533.913 | D11: levens verzekering | E11: 15 | G11: Vervoer | O11: Kinderbijslag
A12: Excursies | B12: =SUMIF('Excursies en activiteien'!C2:C91, "Ja", 'Excursies en activiteien'!B2:B91) -> 1245 | D12: diverse | E12: 100 | G12: Vliegtickets | H12: ='Vluchten en vervoer'!G29 -> 12749
A13: Bekostiging reis | D13: Auto | E13: 400 | G13: Auto huur | H13: ='Vluchten en vervoer'!G51 -> 4522.2
A14: Salaris | B14: =P7*P26 -> 37000 | D14: Opslagbox voor spullen | E14: 0 | G14: Overig vervoer | H14: ='Vluchten en vervoer'!G96 -> 480 | J14: Uit eten extra | K14: 15 | L14: 150 | M14: =K14*L14 -> 2250
A15: Spaarrekening Wereldreis | B15: 62000 | J15: Totaal en gemiddelde | K15: =SUM(K4:K13) -> 156 | M15: =SUM(M4:M14) -> 16675
A16: Huurinkomsten | B16: =P22 -> 11200 | J16: Accomodatie | O16: Totaal | P16: =SUM(P9:P15) -> 239
A17: Vakantie spraarrekening | B17: 6000 | G17: Benzine (10.000 km) | H17: 2500 | J17: kosten cabin/hotel | K17: ='Planning simpel'!A158 -> 157 | M17: =SUM('Planning simpel'!I4:I159) -> 36952.913 | O17: Huur inkomsten totaal | P17: 11200
A18: Totaal | B18: =SUM(B14:B17) -> 116200
J19: Excursies
A20: Totaal benodigd | B20: =B7 -> 97055.863 | J20: Excursies (gepland) | M20: ='Excursies en activiteien'!B92 -> 5421
A21: Verschil | B21: =B18-B20 -> 19144.137 | J21: Excursies (niet gepland) | M21: 1000
J22: Totaal excursies | M22: =SUM(M20:M21) -> 6421 | O22: Totaal | P22: =SUM(P17:P21) -> 11200
A23: Spaarrekening Wereldreis = huidig bedrag + maandelijkse inleg van €500 | J23: Overige
D24: Totaal per maand | E24: =SUM(E3:E23) -> 2091.15 | M24: =K24*L24 -> 0 | O24: Totaal per maand | P24: =SUM(P7+P16) -> 7639
A25: Vakantie spraarrekening = 16 maanden inleg (€500) vakantie spaarrekening | M25: =K25*L25 -> 0
D26: Aantal maanden op reis | E26: 5 | O26: Aantal maanden op reis | P26: 5
A27: kosten per dag | B27: =B20/K15 -> 622.15297 | D27: Totale kosten van thuis | E27: =E24*E26 -> 10455.75 | G27: Totale kosten vooraf | H27: =SUM(H3:H25) -> 21551.2 | J27: Totale kosten op reis | M27: =M15+M17+M25+M22+M24 -> 60048.913 | O27: Totale kosten van thuis | P27: =((P24*P26)+P17) -> 49395

Sheet Planning simpel
B1: Datum | D1: aantal dagen | E1: Locatie | F1: Vervoer | G1: KM | H1: duur | I1: Kosten | J1: Geboekt | K1: Annuleren | L1: Betaald | M1: Geboekt bij | N1: Ontbijt | O1: Keuken | P1: Zwembad | Q1: Naam
A2: 1 | B2: 46284 | C2: Zaterdag | D2: 1 | E2: ✈️ Aankomst San Francisco 14:00 | I2: 193 | J2: Ja | K2: Ja | L2: Ja | M2: Booking | N2: ja | O2: Nee | P2: ja | Q2: Holliday inn golden gateway
A3: 2 | B3: 46285 | C3: Zondag | D3: 2 | E3: San Francisco | I3: 193 | J3: Ja | K3: Ja | L3: Ja | M3: Booking | N3: ja | O3: Nee | P3: ja | Q3: Holliday inn golden gateway
A4: 3 | B4: 46286 | C4: Maandag | D4: 3 | E4: San Francisco | I4: 193 | J4: Ja | K4: Ja | L4: Ja | M4: Booking | N4: ja | O4: Nee | P4: ja | Q4: Holliday inn golden gateway
A5: 4 | B5: 46287 | C5: dinsdag | D5: 4 | E5: San Francisco → Monterey / Carmel | F5: Auto | G5: 200 | H5: 2.3 | I5: 155 | J5: Ja | K5: Nee | L5: Ja | M5: Direct | N5: Ja | O5: Nee | P5: Nee | Q5: https://www.coltoninn.com/
A6: 5 | B6: 46288 | C6: woensdag | D6: 5 | E6: Monterey → San Simeon (Big Sur route) | F6: Auto | G6: 360 | H6: 6 | I6: 91 | J6: Ja | K6: Nee | L6: Ja | M6: Direct | N6: Ja | O6: Nee | P6: Ja | Q6: https://www.choicehotels.com/en-uk/california/san-simeon/quality-inn-hotels
A7: 6 | B7: 46289 | C7: donderdag | D7: 6 | E7: San Simeon → Santa Barbara | F7: Auto | G7: 150 | H7: 2.15 | I7: 160 | J7: Ja | K7: Ja | L7: Nee | M7: Booking | N7: Nee | O7: Ja | P7: Ja | Q7: Flying Flags RV Resort & Campground
A8: 7 | B8: 46290 | C8: vrijdag | D8: 7 | E8: Santa Barbara → Los Angeles | F8: Auto | G8: 165 | H8: 3 | I8: 285 | J8: Ja | K8: Ja | L8: Ja | M8: VRBO | N8: Nee | O8: Ja | P8: Ja | Q8: Marina del Rey, 13950 Panay Way, Marina del Rey, CA, 90292 Verenigde Staten
A9: 8 | B9: 46291 | C9: zaterdag | D9: 8 | E9: Los Angeles - Venice beach - Venice beach | F9: Auto | G9: 30 | H9: 0.3 | I9: 285 | J9: Ja | K9: Ja | L9: Ja | M9: VRBO | N9: Nee | O9: Ja | P9: Ja | Q9: Marina del Rey, 13950 Panay Way, Marina del Rey, CA, 90292 Verenigde Staten
A10: 9 | B10: 46292 | C10: zondag | D10: 9 | E10: Los Angeles - Venice beach | F10: Auto | I10: 285 | J10: Ja | K10: Ja | L10: Ja | M10: VRBO | N10: Nee | O10: Ja | P10: Ja | Q10: Marina del Rey, 13950 Panay Way, Marina del Rey, CA, 90292 Verenigde Staten
A11: 10 | B11: 46293 | C11: maandag | D11: 10 | E11: Los Angeles - Anaheim | F11: Auto | G11: 30 | H11: 1 | I11: 146 | J11: Ja | K11: Nee | L11: Ja | M11: Booking | N11: Ja | O11: Nee | P11: Ja | Q11: Embassy Suites by Hilton Anaheim South
A12: 11 | B12: 46294 | C12: dinsdag | D12: 11 | E12: Los Angeles - Anaheim | F12: Auto | I12: 146 | J12: Ja | K12: Nee | L12: Ja | M12: Booking | N12: Ja | O12: Nee | P12: Ja | Q12: Embassy Suites by Hilton Anaheim South
A13: 12 | B13: 46295 | C13: woensdag | D13: 12 | E13: Los Angeles → Joshua Tree → Kingman | F13: Auto | G13: 470 | H13: 5.3 | I13: 134 | J13: Ja | K13: Nee | L13: Ja | M13: Booking | N13: Ja | O13: Nee | P13: Ja | Q13: Best Western Plus A Wayfarer's Inn & Suites
A14: 13 | B14: 46296 | C14: donderdag | D14: 13 | E14: Kingman → Grand Canyon | F14: Auto | G14: 230 | H14: 3.3 | I14: 196 | J14: Ja | K14: Ja | L14: Ja | M14: Booking | N14: Nee | O14: Nee | P14: Ja | Q14: Grand Canyon Hotel & Suites
A15: 14 | B15: 46297 | C15: vrijdag | D15: 14 | E15: Grand Canyon → Kayenta | F15: Auto | G15: 200 | H15: 2.3 | I15: 194 | J15: Ja | K15: Nee | L15: Ja | M15: Booking | N15: Ja | O15: Nee | P15: Ja | Q15: Hampton Inn Kayenta Monument Valley
A16: 15 | B16: 46298 | C16: zaterdag | D16: 15 | E16: Bluff (Monument Valley) | F16: Auto | G16: 100 | H16: 1.3 | I16: 300 | J16: Ja | K16: Nee | L16: Ja | M16: Direct | N16: Nee | O16: Nee | P16: Nee | Q16: The View Hotel
A17: 16 | B17: 46299 | C17: zondag | D17: 16 | E17: Bluff (Monument Valley) → Page → Kanab | F17: Auto | G17: 200 | H17: 3 | I17: 180 | J17: Ja | K17: Ja | L17: Nee | M17: Direct | N17: Ja | O17: Nee | P17: Ja | Q17: Holiday Inn Express & Suites Kanab
A18: 17 | B18: 46300 | C18: maandag | D18: 17 | E18: Kanab → Bryce Canyon NP | F18: Auto | I18: 260 | J18: Ja | K18: Nee | L18: Nee | M18: Direct | N18: Nee | O18: Ja | P18: Nee | Q18: https://brycevistas.com/
A19: 18 | B19: 46301 | C19: dinsdag | D19: 18 | E19: Bryce Canyon → Zion NP | F19: Auto | G19: 140 | H19: 2 | I19: 270 | J19: Ja | K19: Ja | L19: Ja | M19: Direct | N19: Nee | O19: Ja | P19: Ja | Q19: https://therivatzion.com/
A20: 19 | B20: 46302 | C20: woensdag | D20: 19 | E20: Zion NP | F20: Auto | I20: 270 | J20: Ja | K20: Ja | L20: Ja | M20: Direct | N20: Nee | O20: Ja | P20: Ja | Q20: https://therivatzion.com/
A21: 20 | B21: 46303 | C21: donderdag | D21: 20 | E21: Zion NP | F21: Auto | I21: 270 | J21: Ja | K21: Ja | L21: Ja | M21: Direct | N21: Nee | O21: Ja | P21: Ja | Q21: https://therivatzion.com/
A22: 21 | B22: 46304 | C22: vrijdag | D22: 21 | E22: Zion NP → Las Vegas | F22: Auto | G22: 310 | H22: 4 | I22: 205 | J22: Ja | K22: Ja | L22: Ja | M22: Airbnb | N22: Nee | O22: Ja | P22: Ja | Q22: MGM Grand Tower C
A23: 22 | B23: 46305 | C23: zaterdag | D23: 22 | E23: Las Vegas | F23: Auto | I23: 205 | J23: Ja | K23: Ja | L23: Ja | M23: Airbnb | N23: Nee | O23: Ja | P23: Ja | Q23: MGM Grand Tower C
A24: 23 | B24: 46306 | C24: zondag | D24: 23 | E24: Las Vegas → Mammoth Lakes | F24: Auto | G24: 530 | H24: 6 | I24: 204 | J24: Ja | K24: Ja | L24: Ja | M24: Expedia | N24: Nee | O24: Ja | P24: Ja | Q24: Juniper springs
A25: 24 | B25: 46307 | C25: maandag | D25: 24 | E25: Mammoth Lakes | F25: Auto | I25: 204 | J25: Ja | K25: Ja | L25: Ja | M25: Expedia | N25: Nee | O25: Ja | P25: Ja | Q25: Juniper springs
A26: 25 | B26: 46308 | C26: dinsdag | D26: 25 | E26: Mammoth Lakes → Yosemite NP | F26: Auto | G26: 170 | H26: 3.3 | I26: 271 | J26: Ja | K26: Nee | L26: Ja | M26: Booking | N26: Nee | O26: Ja | P26: Ja | Q26: Yosemite View Lodge
A27: 26 | B27: 46309 | C27: woensdag | D27: 26 | E27: Yosemite NP | F27: Auto | I27: 271 | J27: Ja | K27: Nee | L27: Ja | M27: Booking | N27: Nee | O27: Ja | P27: Ja | Q27: Yosemite View Lodge
A28: 27 | B28: 46310 | C28: donderdag | D28: 27 | E28: Yosemite NP → San Francisco | F28: Auto | G28: 310 | H28: 4.15 | I28: 133 | J28: Ja | K28: Nee | L28: Ja | M28: Booking | N28: Nee | O28: Nee | P28: Nee | Q28: Nob Hill Motor Inn
A29: 28 | B29: 46311 | C29: vrijdag | D29: 28 | E29: San Francisco ✈️ Vertrek 22:55 | I29: 133 | J29: Ja | K29: Nee | L29: Ja | M29: Booking | N29: Nee | O29: Nee | P29: Nee | Q29: Nob Hill Motor Inn
A30: 29 | B30: 46312 | C30: zaterdag | D30: 0 | E30: Volgende dag aankomst + 1 dag tijdverschil
A31: 30 | B31: 46313 | C31: zondag | D31: 1 | E31: Nadi aankomst 05:00 (ochtend) Plantation | I31: 240 | J31: Ja | K31: Ja | L31: Nee | M31: Direct | N31: Nee | O31: Nee | P31: Ja | Q31: Plantation resort
A32: 31 | B32: 46314 | C32: maandag | D32: 2 | E32: Plantation | F32: x | H32: 1u45 | I32: 240 | J32: Ja | K32: Ja | L32: Nee | M32: Direct | N32: Nee | O32: Nee | P32: Ja | Q32: Plantation resort
A33: 32 | B33: 46315 | C33: dinsdag | D33: 3 | E33: Plantation / Port Denarau | F33: x | I33: 250 | J33: Ja | K33: Nee | L33: Ja | M33: Booking | N33: Nee | O33: Ja | P33: Ja | Q33: The Palms Denarau Fiji
A34: 33 | B34: 46316 | C34: woensdag | D34: 4 | E34: Port Denarau | F34: x | I34: 250 | J34: Ja | K34: Nee | L34: Ja | M34: Booking | N34: Nee | O34: Ja | P34: Ja | Q34: The Palms Denarau Fiji
A35: 34 | B35: 46317 | C35: donderdag | D35: 5 | E35: Kuata (1/3) | F35: x | H35: 2u15 | I35: 291 | J35: Ja | K35: Ja | L35: Ja | M35: Direct | N35: Ja | O35: Nee | P35: Ja | Q35: https://www.barefootkuatafiji.com/
A36: 35 | B36: 46318 | C36: vrijdag | D36: 6 | E36: Kuata (2/3) | F36: x | I36: 291 | J36: Ja | K36: Ja | L36: Ja | M36: Direct | N36: Ja | O36: Nee | P36: Ja | Q36: https://www.barefootkuatafiji.com/
A37: 36 | B37: 46319 | C37: zaterdag | D37: 7 | E37: Kuata (3/3) | F37: x | I37: 291 | J37: Ja | K37: Ja | L37: Ja | M37: Direct | N37: Ja | O37: Nee | P37: Ja | Q37: https://www.barefootkuatafiji.com/
A38: 37 | B38: 46320 | C38: zondag | D38: 8 | E38: Einde middag Terug naar Denarau | F38: x | H38: 2u45 | I38: 150 | J38: Ja | K38: Ja | L38: Ja | M38: Booking | N38: Ja | O38: Nee | P38: Ja | Q38: Tokatoka
A39: 38 | B39: 46321 | C39: maandag | D39: 1 | E39: Fiji➔ Brisbane | I39: 180 | J39: Ja | K39: Nee | L39: Ja | M39: Booking | N39: Nee | O39: Ja | P39: Ja | Q39: https://www.booking.com/hotel/au/brisbane-1.nl.html?label=gen173nr-10CAso6AFCEWVpbGVlbnMtdHJlZXMtaW5uSBxYBGipAYgBAZgBM7gBF8gBDNgBA-gBAfgBAYgCAagCAbgCw6uNzAbAAgHSAiQ0MWI3MmEyMS04MDI1LTRhYTUtYjVlZi1iOTc1Y2ViNWQ5ZDDYAgHgAgE&sid=58385233827b3dc4126ecb2cfd20fd81&aid=304142
A40: 39 | B40: 46322 | C40: dinsdag | D40: 2 | E40: Brisbane | F40: x | G40: - | H40: - | I40: 180 | J40: Ja | K40: Nee | L40: Ja | M40: Booking | N40: Nee | O40: Ja | P40: Ja | Q40: https://www.booking.com/hotel/au/brisbane-1.nl.html?label=gen173nr-10CAso6AFCEWVpbGVlbnMtdHJlZXMtaW5uSBxYBGipAYgBAZgBM7gBF8gBDNgBA-gBAfgBAYgCAagCAbgCw6uNzAbAAgHSAiQ0MWI3MmEyMS04MDI1LTRhYTUtYjVlZi1iOTc1Y2ViNWQ5ZDDYAgHgAgE&sid=58385233827b3dc4126ecb2cfd20fd81&aid=304142
A41: 40 | B41: 46323 | C41: woensdag | D41: 3 | E41: Brisbane | F41: x | I41: 180 | J41: Ja | K41: Nee | L41: Ja | M41: Booking | N41: Nee | O41: Ja | P41: Ja | Q41: https://www.booking.com/hotel/au/brisbane-1.nl.html?label=gen173nr-10CAso6AFCEWVpbGVlbnMtdHJlZXMtaW5uSBxYBGipAYgBAZgBM7gBF8gBDNgBA-gBAfgBAYgCAagCAbgCw6uNzAbAAgHSAiQ0MWI3MmEyMS04MDI1LTRhYTUtYjVlZi1iOTc1Y2ViNWQ5ZDDYAgHgAgE&sid=58385233827b3dc4126ecb2cfd20fd81&aid=304142
A42: 41 | B42: 46324 | C42: donderdag | D42: 4 | E42: Byron bay | F42: Auto | G42: 165 | H42: 2 | I42: 180 | J42: Ja | K42: Ja | L42: Ja | M42: Airbnb | N42: Nee | O42: Ja | P42: Ja | Q42: https://www.airbnb.nl/rooms/54331136?photo_id=2420221961&source_impression_id=p3_1769886957_P3qy0z1aoSnqd-qr&previous_page_section_name=1000
A43: 42 | B43: 46325 | C43: vrijdag | D43: 5 | E43: Byron bay | F43: Auto | I43: 180 | J43: Ja | K43: Ja | L43: Ja | M43: Airbnb | N43: Nee | O43: Ja | P43: Ja | Q43: https://www.airbnb.nl/rooms/54331136?photo_id=2420221961&source_impression_id=p3_1769886957_P3qy0z1aoSnqd-qr&previous_page_section_name=1000
A44: 43 | B44: 46326 | C44: zaterdag | D44: 6 | E44: Byron bay | F44: Auto | I44: 180 | J44: Ja | K44: Ja | L44: Ja | M44: Airbnb | N44: Nee | O44: Ja | P44: Ja | Q44: https://www.airbnb.nl/rooms/54331136?photo_id=2420221961&source_impression_id=p3_1769886957_P3qy0z1aoSnqd-qr&previous_page_section_name=1000
A45: 44 | B45: 46327 | C45: zondag | D45: 7 | E45: Lamington | F45: Auto | G45: 120 | H45: 2 | I45: 170 | J45: Ja | K45: Ja | L45: Nee | M45: Booking | N45: Nee | O45: Ja | P45: Nee | Q45: https://www.booking.com/hotel/au/rosellas-on-springbrook.nl.html?label=gen173nr-10CAso6AFCEWVpbGVlbnMtdHJlZXMtaW5uSBxYBGipAYgBAZgBM7gBF8gBDNgBA-gBAfgBAYgCAagCAbgCw6uNzAbAAgHSAiQ0MWI3MmEyMS04MDI1LTRhYTUtYjVlZi1iOTc1Y2ViNWQ5ZDDYAgHgAgE&sid=58385233827b3dc4126ecb2cfd20fd81&aid=304142
A46: 45 | B46: 46328 | C46: maandag | D46: 8 | E46: Rainbow beach | F46: Auto | G46: 300 | H46: 4 | I46: 180 | J46: Ja | K46: Ja | L46: Nee | M46: Airbnb | N46: Nee | O46: Ja | P46: Ja | Q46: Airbnb
A47: 46 | B47: 46329 | C47: dinsdag | D47: 9 | E47: Rainbow beach | F47: Auto | I47: 180 | J47: Ja | K47: Ja | L47: Nee | M47: Airbnb | N47: Nee | O47: Ja | P47: Ja | Q47: Airbnb
A48: 47 | B48: 46330 | C48: woensdag | D48: 10 | E48: Noosa | F48: Auto | G48: 120 | H48: 1.4 | I48: 180 | J48: Ja | K48: Ja | L48: Nee | M48: Booking | N48: Nee | O48: Ja | P48: Ja | Q48: https://www.booking.com/hotel/au/myuna-holiday-apartments.nl.html?label=gen173nr-10CAso6AFCEWVpbGVlbnMtdHJlZXMtaW5uSBxYBGipAYgBAZgBM7gBF8gBDNgBA-gBAfgBAYgCAagCAbgCw6uNzAbAAgHSAiQ0MWI3MmEyMS04MDI1LTRhYTUtYjVlZi1iOTc1Y2ViNWQ5ZDDYAgHgAgE&sid=58385233827b3dc4126ecb2cfd20fd81&aid=304142
A49: 48 | B49: 46331 | C49: donderdag | D49: 11 | E49: Noosa | F49: Auto | I49: 180 | J49: Ja | K49: Ja | L49: Nee | M49: Booking | N49: Nee | O49: Ja | P49: Ja | Q49: https://www.booking.com/hotel/au/myuna-holiday-apartments.nl.html?label=gen173nr-10CAso6AFCEWVpbGVlbnMtdHJlZXMtaW5uSBxYBGipAYgBAZgBM7gBF8gBDNgBA-gBAfgBAYgCAagCAbgCw6uNzAbAAgHSAiQ0MWI3MmEyMS04MDI1LTRhYTUtYjVlZi1iOTc1Y2ViNWQ5ZDDYAgHgAgE&sid=58385233827b3dc4126ecb2cfd20fd81&aid=304142
A50: 49 | B50: 46332 | C50: vrijdag | D50: 12 | E50: Glass house mountains | F50: Auto | I50: 180 | J50: Ja | K50: Ja | L50: Ja | M50: Direct | N50: Ja | O50: Ja | P50: Nee | Q50: https://www.blackwattlefarm.com.au/rooms
A51: 50 | B51: 46333 | C51: zaterdag | D51: 13 | E51: Glass house mountains | F51: Auto | G51: 80 | H51: 1 | I51: 180 | J51: Ja | K51: Ja | L51: Ja | M51: Direct | N51: Ja | O51: Ja | P51: Nee | Q51: https://www.blackwattlefarm.com.au/rooms
A52: 51 | B52: 46334 | C52: zondag | D52: 1 | E52: Brisbane naar Cairns | I52: 128 | J52: Ja | K52: Nee | L52: Ja | M52: Airbnb | N52: Nee | O52: Ja | P52: Ja | Q52: https://www.airbnb.nl/rooms/21600843?viralityEntryPoint=1&s=76
A53: 52 | B53: 46335 | C53: maandag | D53: 2 | E53: Port Douglas | F53: Auto | I53: 128 | J53: Ja | K53: Nee | L53: Ja | M53: Airbnb | N53: Nee | O53: Ja | P53: Ja | Q53: https://www.airbnb.nl/rooms/21600843?viralityEntryPoint=1&s=76
A54: 53 | B54: 46336 | C54: dinsdag | D54: 3 | E54: Port Douglas | F54: Auto | I54: 128 | J54: Ja | K54: Nee | L54: Ja | M54: Airbnb | N54: Nee | O54: Ja | P54: Ja | Q54: https://www.airbnb.nl/rooms/21600843?viralityEntryPoint=1&s=76
A55: 54 | B55: 46337 | C55: woensdag | D55: 4 | E55: Port Douglas | F55: Auto | I55: 128 | J55: Ja | K55: Nee | L55: Ja | M55: Airbnb | N55: Nee | O55: Ja | P55: Ja | Q55: https://www.airbnb.nl/rooms/21600843?viralityEntryPoint=1&s=76
A56: 55 | B56: 46338 | C56: donderdag | D56: 5 | E56: Port Douglas | F56: Auto | I56: 128 | J56: Ja | K56: Nee | L56: Ja | M56: Airbnb | N56: Nee | O56: Ja | P56: Ja | Q56: https://www.airbnb.nl/rooms/21600843?viralityEntryPoint=1&s=76
A57: 56 | B57: 46339 | C57: vrijdag | D57: 6 | E57: Port Douglas | F57: Auto | I57: 128 | J57: Ja | K57: Nee | L57: Ja | M57: Airbnb | N57: Nee | O57: Ja | P57: Ja | Q57: https://www.airbnb.nl/rooms/21600843?viralityEntryPoint=1&s=76
A58: 57 | B58: 46340 | C58: zaterdag | D58: 7 | E58: Port Douglas | F58: Auto | I58: 128 | J58: Ja | K58: Nee | L58: Ja | M58: Airbnb | N58: Nee | O58: Ja | P58: Ja | Q58: https://www.airbnb.nl/rooms/21600843?viralityEntryPoint=1&s=76
A59: 58 | B59: 46341 | C59: zondag | D59: 8 | E59: Cape trip | F59: Auto | G59: 120 | H59: 2 | I59: 135 | J59: Ja | K59: Ja | L59: Nee | M59: Booking | N59: Nee | O59: nee | P59: Ja | Q59: https://secure.booking.com/confirmation.nl.html?label=lgnl_crEUR_sf_fn_piPRkLMeRuNjOx_oiOF06AY3UAJRx_sctpa_pl_ta_neg_fi_tikwd-2471616913092_lp1010754_li_dec_dm_ag196401585027_ci23568827516&sid=58385233827b3dc4126ecb2cfd20fd81&aid=2421090&auth_key=X7EBOVauwp1Qiynh&source=mytrips
A60: 59 | B60: 46342 | C60: maandag | D60: 9 | E60: Cape trip -> tablelands | F60: Auto | G60: 50 | H60: 3 | I60: 126 | J60: Ja | K60: Ja | L60: Nee | M60: Booking | N60: Nee | O60: nee | P60: Ja | Q60: https://chamberslodges.com.au/
A61: 60 | B61: 46343 | C61: dinsdag | D61: 10 | E61: Cairns | F61: Auto | G61: 100 | H61: 2 | I61: 114 | J61: Ja | K61: Ja | L61: Nee | M61: Booking | N61: Nee | O61: nee | P61: Ja | Q61: https://www.booking.com/hotel/au/cairns-colonial-club-resort.nl.html?label=lgnl_crEUR_sf_fn_piPRkLMeRuNjOx_oiOF06AY3UAJRx_sctpa_pl_ta_neg_fi_tikwd-2471616913092_lp1010754_li_dec_dm_ag196401585027_ci23568827516&sid=58385233827b3dc4126ecb2cfd20fd81&aid=2421090&ucfs=1&checkin=2026-11-17&checkout=2026-11-18&dest_id=-1612224&dest_type=city&group_adults=2&no_rooms=1&group_children=2&age=7&req_age=7&age=9&req_age=9&nflt=price%3DEUR-min-130-1&srpvid=202f59219a0a0a2a&srepoch=1771764690&matching_block_id=17948805_222659274_2_2_0_1152507&atlas_src=sr_iw_title#_
A62: 61 | B62: 46344 | C62: woensdag | D62: 1 | E62: Cairns ➔ Sydney | I62: 244 | J62: Ja | K62: Nee | L62: Ja | M62: Airbnb | N62: Nee | O62: Ja | P62: Nee | Q62: https://www.airbnb.nl/trips/v1/reservation-details/ro/RESERVATION2_CHECKIN/HMPQJZ93WF
A63: 62 | B63: 46345 | C63: donderdag | D63: 2 | E63: Sydney | F63: x | I63: 244 | J63: Ja | K63: Nee | L63: Ja | M63: Airbnb | N63: Nee | O63: Ja | P63: Nee | Q63: https://www.airbnb.nl/trips/v1/reservation-details/ro/RESERVATION2_CHECKIN/HMPQJZ93WF
A64: 63 | B64: 46346 | C64: vrijdag | D64: 3 | E64: Sydney | F64: x | I64: 244 | J64: Ja | K64: Nee | L64: Ja | M64: Airbnb | N64: Nee | O64: Ja | P64: Nee | Q64: https://www.airbnb.nl/trips/v1/reservation-details/ro/RESERVATION2_CHECKIN/HMPQJZ93WF
A65: 64 | B65: 46347 | C65: zaterdag | D65: 4 | E65: Sydney | F65: x | I65: 244 | J65: Ja | K65: Nee | L65: Ja | M65: Airbnb | N65: Nee | O65: Ja | P65: Nee | Q65: https://www.airbnb.nl/trips/v1/reservation-details/ro/RESERVATION2_CHECKIN/HMPQJZ93WF
A66: 65 | B66: 46348 | C66: zondag | D66: 5 | E66: Sydney → Bendalong | F66: Auto | G66: 230 | H66: 3 | I66: 145 | J66: Ja | K66: Ja | L66: Ja | M66: Direct | N66: Nee | O66: Ja | P66: Ja | Q66: https://holidayhaven.com.au/bendalong/
A67: 66 | B67: 46349 | C67: maandag | D67: 6 | E67: Bendalong | F67: Auto | I67: 145 | J67: Ja | K67: Ja | L67: Ja | M67: Direct | N67: Nee | O67: Ja | P67: Ja | Q67: https://holidayhaven.com.au/bendalong/
A68: 67 | B68: 46350 | C68: dinsdag | D68: 7 | E68: Bendalong | F68: Auto | I68: 145 | J68: Ja | K68: Ja | L68: Ja | M68: Direct | N68: Nee | O68: Ja | P68: Ja | Q68: https://holidayhaven.com.au/bendalong/
A69: 68 | B69: 46351 | C69: woensdag | D69: 8 | E69: Bendalong → Tuross Head | F69: Auto | G69: 150 | H69: 2.15 | I69: 115 | J69: Ja | K69: Ja | L69: Ja | M69: Direct | N69: Nee | O69: Ja | P69: Ja | Q69: https://www.discoveryholidayparks.com.au/caravan-parks/new-south-wales/south-coast/narooma-beach?accommodationCode=NNRM-118-2384-RT&propertyCode=NNRM&arrive=2026-11-25&depart=2026-11-27&adults=2&kids=2&infants=0&index=9&sort=price-desc&maxSearchResults=30
A70: 69 | B70: 46352 | C70: donderdag | D70: 9 | E70: Tuross Head | F70: Auto | I70: 115 | J70: Ja | K70: Ja | L70: Ja | M70: Direct | N70: Nee | O70: Ja | P70: Ja | Q70: https://www.discoveryholidayparks.com.au/caravan-parks/new-south-wales/south-coast/narooma-beach?accommodationCode=NNRM-118-2384-RT&propertyCode=NNRM&arrive=2026-11-25&depart=2026-11-27&adults=2&kids=2&infants=0&index=9&sort=price-desc&maxSearchResults=30
A71: 70 | B71: 46353 | C71: vrijdag | D71: 10 | E71: Tuross Head → Eden | F71: Auto | G71: 140 | H71: 1.4 | I71: 135 | J71: Ja | K71: Ja | L71: Ja | M71: Direct | N71: Nee | O71: Ja | P71: Ja | Q71: https://www.discoveryholidayparks.com.au/caravan-parks/new-south-wales/south-coast/eden/superior-2-bedroom-cabin-sleeps-6?accommodationCode=NEDN-94-1574-RT&propertyCode=NEDN&arrive=2026-11-27&depart=2026-11-28&adults=2&kids=2&infants=0&index=5
A72: 71 | B72: 46354 | C72: zaterdag | D72: 11 | E72: Eden→ Traralgon | F72: Auto | G72: 416 | H72: 5 | I72: 140 | J72: Ja | K72: Nee | L72: Ja | M72: Booking | N72: Nee | O72: Ja | P72: Ja | Q72: https://www.booking.com/hotel/au/traralgon-park-lane-holiday-park.nl.html?label=gen173nr-10CAEoggI46AdIM1gEaKkBiAEBmAEzuAEHyAEM2AED6AEB-AEBiAIBqAIBuAKAsaPLBsACAdICJGExZTJmMzM5LTFmNWMtNDVkNy05YmVhLWU5NzZkZWFmMTdjY9gCAeACAQ&aid=304142&ucfs=1&checkin=2026-11-28&checkout=2026-11-29&dest_id=-1587163&dest_type=city&group_adults=2&no_rooms=1&group_children=2&age=7&req_age=7&age=9&req_age=9&srpvid=2b22592dcb840154&srepoch=1769949687&matching_block_id=113618714_370496383_4_0_0&atlas_src=sr_iw_title#_
A73: 72 | B73: 46355 | C73: zondag | D73: 12 | E73: Traralgon → Wilsons Promontory | F73: Auto | G73: 150 | H73: 2 | I73: 200 | J73: Ja | K73: Ja | L73: Ja | M73: Direct | N73: Nee | O73: Ja | P73: Nee | Q73: https://www.parks.vic.gov.au/places-to-see/parks/wilsons-promontory-national-park/where-to-stay/tidal-river-accommodation/tidal-river-huts
A74: 73 | B74: 46356 | C74: maandag | D74: 13 | E74: Wilsons Promontory | F74: Auto | I74: 200 | J74: Ja | K74: Ja | L74: Ja | M74: Direct | N74: Nee | O74: Ja | P74: Nee | Q74: https://www.parks.vic.gov.au/places-to-see/parks/wilsons-promontory-national-park/where-to-stay/tidal-river-accommodation/tidal-river-huts
A75: 74 | B75: 46357 | C75: dinsdag | D75: 14 | E75: Wilsons Promontory → Yarra Ranges | F75: Auto | G75: 250 | H75: 3.3 | I75: 110 | J75: Ja | K75: Ja | L75: Ja | M75: Direct | N75: Nee | O75: Ja | P75: Ja | Q75: https://hampshireholidays.com.au/parks/vic/warburton-holiday-park
A76: 75 | B76: 46358 | C76: woensdag | D76: 15 | E76: Yarra Ranges | F76: Auto | I76: 110 | J76: Ja | K76: Ja | L76: Ja | M76: Direct | N76: Nee | O76: Ja | P76: Ja | Q76: https://hampshireholidays.com.au/parks/vic/warburton-holiday-park
A77: 76 | B77: 46359 | C77: donderdag | D77: 16 | E77: Yarra Ranges | F77: Auto | G77: 300 | H77: 3.2 | I77: 110 | J77: Ja | K77: Ja | L77: Ja | M77: Direct | N77: Nee | O77: Ja | P77: Ja | Q77: https://hampshireholidays.com.au/parks/vic/warburton-holiday-park
A78: 77 | B78: 46360 | C78: vrijdag | D78: 17 | E78: Yarra Ranges → Bimbi Park | F78: Auto | G78: 75 | H78: 1.2 | I78: 150 | J78: Ja | K78: Ja | L78: Ja | M78: Direct | N78: Nee | O78: Ja | P78: Nee | Q78: https://bimbipark.com.au/
A79: 78 | B79: 46361 | C79: zaterdag | D79: 18 | E79: Bimbi Park | F79: Auto | I79: 150 | J79: Ja | K79: Ja | L79: Ja | M79: Direct | N79: Nee | O79: Ja | P79: Nee | Q79: https://bimbipark.com.au/
A80: 79 | B80: 46362 | C80: zondag | D80: 19 | E80: Bimbi Park → Mount Macedon | F80: Auto | G80: 250 | H80: 3.3 | I80: 0 | J80: Ja | K80: Ja | L80: Ja | M80: Direct | N80: Ja | O80: Ja | P80: Nee | Q80: Andrew
A81: 80 | B81: 46363 | C81: maandag | D81: 20 | E81: Mount Macedon | F81: Auto | I81: 0 | J81: Ja | K81: Ja | L81: Ja | M81: Direct | N81: Ja | O81: Ja | P81: Nee | Q81: Andrew
A82: 81 | B82: 46364 | C82: dinsdag | D82: 21 | E82: Mount Macedon | F82: Auto | I82: 0 | J82: Ja | K82: Ja | L82: Ja | M82: Direct | N82: Ja | O82: Ja | P82: Nee | Q82: Andrew
A83: 82 | B83: 46365 | C83: woensdag | D83: 22 | E83: Mount Macedon | F83: Auto | I83: 0 | J83: Ja | K83: Ja | L83: Ja | M83: Direct | N83: Ja | O83: Ja | P83: Nee | Q83: Andrew
A84: 83 | B84: 46366 | C84: donderdag | D84: 23 | E84: Mount Macedon → Melbourne | F84: Auto | G84: 60 | H84: 1 | I84: 171 | J84: Ja | K84: Ja | L84: Nee | M84: Airbnb | N84: Nee | O84: Ja | P84: Ja | Q84: https://www.airbnb.nl/rooms/1576585362074394024?photo_id=2441452811&source_impression_id=p3_1773059472_P3xjRZH-UHXNI_VK&previous_page_section_name=1000
A85: 84 | B85: 46367 | C85: vrijdag | D85: 24 | E85: Melbourne | F85: Auto | I85: 171 | J85: Ja | K85: Ja | L85: Nee | M85: Airbnb | N85: Nee | O85: Ja | P85: Ja | Q85: https://www.airbnb.nl/rooms/1576585362074394024?photo_id=2441452811&source_impression_id=p3_1773059472_P3xjRZH-UHXNI_VK&previous_page_section_name=1001
A86: 85 | B86: 46368 | C86: zaterdag | D86: 25 | E86: Melbourne | F86: Auto | I86: 171 | J86: Ja | K86: Ja | L86: Nee | M86: Airbnb | N86: Nee | O86: Ja | P86: Ja | Q86: https://www.airbnb.nl/rooms/1576585362074394024?photo_id=2441452811&source_impression_id=p3_1773059472_P3xjRZH-UHXNI_VK&previous_page_section_name=1002
A87: 86 | B87: 46369 | C87: zondag | D87: 1 | E87: Melbourne - Christchurch | I87: 112 | J87: Ja | K87: Nee | L87: Ja | M87: Booking | N87: Nee | O87: Ja | P87: Nee | Q87: https://www.booking.com/hotel/nz/inner-city-haven-location-location-location.nl.html?label=gen173nr-10CAEoggI46AdIM1gEaKkBiAEBmAEzuAEHyAEM2AED6AEB-AEBiAIBqAIBuAKAsaPLBsACAdICJGExZTJmMzM5LTFmNWMtNDVkNy05YmVhLWU5NzZkZWFmMTdjY9gCAeACAQ&sid=e52a85b3cbf592e6f63f2c39287a1c6a&aid=304142
A88: 87 | B88: 46370 | C88: maandag | D88: 2 | E88: Christchurch | F88: x | I88: 112 | J88: Ja | K88: Nee | L88: Ja | M88: Booking | N88: Nee | O88: Ja | P88: Nee | Q88: https://www.booking.com/hotel/nz/inner-city-haven-location-location-location.nl.html?label=gen173nr-10CAEoggI46AdIM1gEaKkBiAEBmAEzuAEHyAEM2AED6AEB-AEBiAIBqAIBuAKAsaPLBsACAdICJGExZTJmMzM5LTFmNWMtNDVkNy05YmVhLWU5NzZkZWFmMTdjY9gCAeACAQ&sid=e52a85b3cbf592e6f63f2c39287a1c6a&aid=304142
A89: 88 | B89: 46371 | C89: dinsdag | D89: 3 | E89: Christchurch | F89: x | I89: 112 | J89: Ja | K89: Nee | L89: Ja | M89: Booking | N89: Nee | O89: Ja | P89: Nee | Q89: https://www.booking.com/hotel/nz/inner-city-haven-location-location-location.nl.html?label=gen173nr-10CAEoggI46AdIM1gEaKkBiAEBmAEzuAEHyAEM2AED6AEB-AEBiAIBqAIBuAKAsaPLBsACAdICJGExZTJmMzM5LTFmNWMtNDVkNy05YmVhLWU5NzZkZWFmMTdjY9gCAeACAQ&sid=e52a85b3cbf592e6f63f2c39287a1c6a&aid=304142
A90: 89 | B90: 46372 | C90: woensdag | D90: 4 | E90: Christchurch → Lake Tekapo | F90: Auto | G90: 230 | H90: 3 | I90: 200 | J90: Ja | K90: Nee | L90: Ja | M90: Booking | N90: Nee | O90: Ja | P90: Nee | Q90: https://www.booking.com/hotel/nz/the-shearers-quarters.nl.html?label=askray-apartment-cSIo6DzYweefYjEQIpj9fQS714023430663%3Apl%3Ata%3Ap1%3Ap2%3Aac%3Aap%3Aneg%3Afi%3Atikwd-2392211680204%3Alp1010427%3Ali%3Adec%3Adm%3Appccp%3DUmFuZG9tSVYkc2RlIyh9YbSsBl3MCvHsD8UKUHIRFxY&sid=ebe3ad77cd4029892a5e367c699c80e5&aid=311984&ucfs=1&checkin=2026-12-16&checkout=2026-12-17&dest_id=-1512185&dest_type=city&group_adults=2&no_rooms=1&group_children=2&age=7&req_age=7&age=9&req_age=9&sr_order=price&srpvid=de3d3cb2e2470055&srepoch=1772529681&matching_block_id=1255877701_398126718_4_0_0&atlas_src=sr_iw_title
A91: 90 | B91: 46373 | C91: donderdag | D91: 5 | E91: Lake Tekapo → Mount Cook | F91: Auto | G91: 100 | H91: 1.1 | I91: 250 | J91: Ja | K91: Ja | L91: Ja | M91: Direct | N91: Ja | O91: Ja | P91: Nee | Q91: https://www.hermitage.co.nz/
A92: 91 | B92: 46374 | C92: vrijdag | D92: 6 | E92: Mount Cook → Moeraki | F92: Auto | G92: 250 | H92: 3 | I92: 120 | J92: Ja | K92: Ja | L92: Nee | M92: Booking | N92: Ja | O92: Ja | P92: Nee | Q92: century house b&b flatlette
A93: 92 | B93: 46375 | C93: zaterdag | D93: 7 | E93: Moeraki → Te Anau | F93: Auto | G93: 360 | H93: 4.2 | I93: 142 | J93: Ja | K93: Ja | L93: Nee | M93: Booking | N93: Nee | O93: Ja | P93: Nee | Q93: https://www.booking.com/hotel/nz/te-anau-lakeview.nl.html?label=gen173nr-10CAEoggI46AdIM1gEaKkBiAEBmAEzuAEHyAEM2AED6AEB-AEBiAIBqAIBuAKAsaPLBsACAdICJGExZTJmMzM5LTFmNWMtNDVkNy05YmVhLWU5NzZkZWFmMTdjY9gCAeACAQ&aid=304142&ucfs=1&checkin=2026-12-19&checkout=2026-12-21&dest_id=-1519212&dest_type=city&group_adults=2&no_rooms=1&group_children=2&age=7&req_age=7&age=9&req_age=9&nflt=price%3DEUR-min-210-1&srpvid=35e783f36aea1070&srepoch=1770922107&matching_block_id=33314831_402800212_4_0_0&atlas_src=sr_iw_title#_
A94: 93 | B94: 46376 | C94: zondag | D94: 8 | E94: Te Anau | F94: Auto | G94: 120 | H94: 1.3 | I94: 142 | J94: Ja | K94: Ja | L94: Nee | M94: Booking | N94: Nee | O94: Ja | P94: Nee | Q94: https://www.booking.com/hotel/nz/te-anau-lakeview.nl.html?label=gen173nr-10CAEoggI46AdIM1gEaKkBiAEBmAEzuAEHyAEM2AED6AEB-AEBiAIBqAIBuAKAsaPLBsACAdICJGExZTJmMzM5LTFmNWMtNDVkNy05YmVhLWU5NzZkZWFmMTdjY9gCAeACAQ&aid=304142&ucfs=1&checkin=2026-12-19&checkout=2026-12-21&dest_id=-1519212&dest_type=city&group_adults=2&no_rooms=1&group_children=2&age=7&req_age=7&age=9&req_age=9&nflt=price%3DEUR-min-210-1&srpvid=35e783f36aea1070&srepoch=1770922107&matching_block_id=33314831_402800212_4_0_0&atlas_src=sr_iw_title#_
A95: 94 | B95: 46377 | C95: maandag | D95: 9 | E95: Te Anau → Queenstown | F95: Auto | G95: 175 | H95: 2.3 | I95: 163 | J95: Ja | K95: Ja | L95: Nee | M95: Direct | N95: Nee | O95: Ja | P95: Nee | Q95: https://hampshireholidayparks.co.nz/queenstown
A96: 95 | B96: 46378 | C96: dinsdag | D96: 10 | E96: Queenstown | F96: Auto | I96: 163 | J96: Ja | K96: Ja | L96: Nee | M96: Direct | N96: Nee | O96: Ja | P96: Nee | Q96: https://hampshireholidayparks.co.nz/queenstown
A97: 96 | B97: 46379 | C97: woensdag | D97: 11 | E97: Queenstown → Wanaka | F97: Auto | G97: 70 | H97: 1.15 | I97: 160 | J97: Ja | K97: Ja | L97: Nee | M97: Booking | N97: Nee | O97: Ja | P97: Nee | Q97: https://www.booking.com/hotel/nz/toi-toi-holiday-home.nl.html?label=gen173nr-10CAEoggI46AdIM1gEaKkBiAEBmAEzuAEHyAEM2AED6AEB-AEBiAIBqAIBuAKAsaPLBsACAdICJGExZTJmMzM5LTFmNWMtNDVkNy05YmVhLWU5NzZkZWFmMTdjY9gCAeACAQ&aid=304142&ucfs=1&checkin=2026-12-23&checkout=2026-12-25&dest_id=-1516080&dest_type=city&group_adults=2&no_rooms=1&group_children=2&age=7&req_age=7&age=9&req_age=9&nflt=price%3DEUR-min-200-1&srpvid=5dde618ea09b01c4&srepoch=1770386517&matching_block_id=1042234601_376644161_4_0_0_530773&atlas_src=sr_iw_title
A98: 97 | B98: 46380 | C98: donderdag | D98: 12 | E98: Wanaka | F98: Auto | I98: 160 | J98: Ja | K98: Ja | L98: Nee | M98: Booking | N98: Nee | O98: Ja | P98: Nee | Q98: https://www.booking.com/hotel/nz/toi-toi-holiday-home.nl.html?label=gen173nr-10CAEoggI46AdIM1gEaKkBiAEBmAEzuAEHyAEM2AED6AEB-AEBiAIBqAIBuAKAsaPLBsACAdICJGExZTJmMzM5LTFmNWMtNDVkNy05YmVhLWU5NzZkZWFmMTdjY9gCAeACAQ&aid=304142&ucfs=1&checkin=2026-12-23&checkout=2026-12-25&dest_id=-1516080&dest_type=city&group_adults=2&no_rooms=1&group_children=2&age=7&req_age=7&age=9&req_age=9&nflt=price%3DEUR-min-200-1&srpvid=5dde618ea09b01c4&srepoch=1770386517&matching_block_id=1042234601_376644161_4_0_0_530773&atlas_src=sr_iw_title
A99: 98 | B99: 46381 | C99: vrijdag | D99: 13 | E99: Wanaka → Franz Josef | F99: Auto | G99: 285 | H99: 4.15 | I99: 100 | J99: Ja | K99: Ja | L99: Ja | M99: Direct | N99: Nee | O99: Ja | P99: Nee | Q99: https://rainforest.nz/holiday-park/
A100: 99 | B100: 46382 | C100: zaterdag | D100: 14 | E100: Franz Josef | F100: Auto | I100: 100 | J100: Ja | K100: Ja | L100: Ja | M100: Direct | N100: Nee | O100: Ja | P100: Nee | Q100: https://rainforest.nz/holiday-park/
...

Sheet Accomodatie
A1: Accomodatie
A2: Aankomst datum | B2: Vertrek datum | C2: Naam Accomodatie | D2: Reserveringsnummer | E2: Kosten | F2: inchecken (tijd) | G2: uitchecken (tijd) | H2: Ontbijt | I2: Telefoonnummer | J2: Adres
A3: 46284 | B3: 46287 | C3: Holliday inn golden gateway | D3: 6004927844 | E3: 584.06 | F3: 0.66666667 | G3: 0.45833333 | H3: Ja | I3: +1 415 441 4000 | J3: 1500 Van Ness Ave, San Francisco, CA 94109, Verenigde Staten
A4: 46287 | B4: 46288 | C4: Colton Inn | D4: CICA05091266 | E4: 155.98 | F4: 0.625 | G4: 0.45833333 | H4: Ja | I4: +1 831 649 6500 | J4: 707 Pacific Street | Monterey, CA 93940
A5: 46288 | B5: 46289 | C5: Quality Inn near Hearst Castle (San Simeon) | D5: 12693981 | E5: 91.3 | F5: 0.625 | G5: 0.45833333 | H5: Nee | I5: +1 805 927 3998 | J5: 9260 Castillo Drive, San Simeon, CA 93452, US
A6: 46289 | B6: 46290 | C6: Flying Flags RV Resort & Campground | D6: 5411636117 | E6: 161 | F6: 0.66666667 | G6: 0.45833333 | H6: Nee | I6: +1 805 688 3716 | J6: 180 Avenue of Flags, Buellton, 93427, Verenigde Staten
A7: 46290 | B7: 46293 | C7: Airbnb Marina del Rey | D7: HM23KJD38X | E7: 641 | F7: 0.66666667 | G7: 0.41666667 | H7: Nee | I7: Niet openbaar | J7: 14000 Palawan Way, Marina del Rey, CA 90292, United States
A8: 46293 | B8: 46295 | C8: Embassy Suites by Hilton Anaheim South | D8: 6248261201 | E8: 292 | F8: 0.66666667 | G8: 0.45833333 | H8: Ja | I8: +1 714 539 3300 | J8: 11767 Harbor Boulevard, Garden Grove, Anaheim, CA 92840, Verenigde Staten
A9: 46295 | B9: 46296 | C9: Best Western Plus A Wayfarer's Inn & Suites (Kingman) | D9: 5722837090 | E9: 134 | F9: 0.625 | G9: 0.45833333 | H9: Ja | I9: +1 928 753 6271 | J9: 2815 East Andy Devine Avenue, Kingman, AZ 86401, Verenigde Staten
A10: 46296 | B10: 46297 | C10: Grand Canyon Hotel & Suites | D10: 6821604479 | E10: 197.88 | F10: 0.66666667 | G10: 0.45833333 | H10: Nee | I10: +1 928 638 3000 | J10: 226 Highway 64, Tusayan, AZ 86023, Verenigde Staten
A11: 46297 | B11: 46298 | C11: Hampton Inn Kayenta Monument Valley | D11: 6984657657 | E11: 194 | F11: 0.66666667 | G11: 0.41666667 | H11: Ja | I11: +1 928 697 3170 | J11: US Highway 160, Kayenta, AZ 86033, Verenigde Staten
A12: 46298 | B12: 46299 | C12: The View Campground/Hotel (Monument Valley) | D12: 128167 (online: TVCUT05056231) | E12: 333.49 | F12: 0.66666667 | G12: 0.45833333 | H12: Nee | I12: +1 435 727 5555 | J12: PO Box 360457, Monument Valley, UT 84536 (geen straatadres vermeld)
A13: 46299 | B13: 46300 | C13: Holiday Inn Express & Suites Kanab | D13: 29639006 | E13: 138.92 | F13: 0.66666667 | G13: 0.45833333 | H13: Ja | I13: +1 435 644 3100 | J13: 217 South 100 East, Kanab, UT 84741, United States
A14: 46300 | B14: 46301 | C14: Bryce Vistas (Claron Suite) | D14: 80799875 | E14: 265.55 | F14: 0.66666667 | G14: 0.45833333 | H14: Nee | I14: +1 435 383 2900 | J14: Niet vermeld in e-mail (Bryce Vistas, Zuid-Utah)
A15: 46301 | B15: 46304 | C15: Zion Park Motel | D15: 5594993241 | E15: 744.44 | F15: 0.625 | G15: 0.4375 | H15: Nee | I15: +1 435 772 3251 | J15: 865 Zion Park Blvd, Springdale, 84767, Verenigde Staten
A16: 46304 | B16: 46306 | C16: The Signature at MGM Grand (Las Vegas, Airbnb) | D16: HM4F4WTDMK | E16: 409 | F16: 0.625 | G16: 0.45833333 | H16: Nee | I16: +1 702 797 6000 | J16: Tower C, 125 East Harmon Avenue 17-818, Las Vegas, NV 89109, United States
A17: 46306 | B17: 46308 | C17: Juniper Springs Resort (Mammoth Lakes) | D17: 72070151578100 | E17: 407.41 | F17: 0.66666667 | G17: 0.45833333 | H17: Nee | I17: +1 760 934 1102 | J17: 4000 Meridian Blvd, Mammoth Lakes, CA 93546, Verenigde Staten
A18: 46308 | B18: 46310 | C18: Yosemite View Lodge | D18: 5638749450 | E18: 544.56 | F18: 0.66666667 | G18: 0.45833333 | H18: Nee | I18: +1 209 379 2681 | J18: 11136 Highway 140, El Portal, CA 95318, Verenigde Staten
A19: 46310 | B19: 46312 | C19: Nob Hill Motor Inn (San Francisco) | D19: 5638746431 | E19: 266.43 | F19: 0.625 | G19: 0.45833333 | H19: Nee | I19: +1 415 775 8160 | J19: 1630 Pacific Avenue, Russian Hill, San Francisco, CA 94109, Verenigde Staten
A20: 46313 | B20: 46315 | C20: Plantation resort Fiji | D20: 70810566 | E20: 504.7 | F20: 0.625 | G20: 0.45833333 | H20: Nee | I20: +679 673 4777 | J20: Malolo Lailai, Nadi, Fiji
A21: 46315 | B21: 46317 | C21: The Palms Denarau | D21: 5361293748 | E21: 521.84 | F21: 0.625 | G21: 0.45833333 | H21: Nee | I21: +679 675 0104 | J21: P O Box PD120, Port Denarau, Nadi, Denarau, Fiji
A22: 46317 | B22: 46320 | C22: Kuata Island | D22: 37620 | E22: 1263.34 | F22: 0.625 | G22: 0.45833333 | H22: Ja | I22: +679 895 2090 | J22: Kuata island
A23: 46320 | B23: 46321 | C23: Tokatoka Resort Hotel | D23: 5317923311 | E23: 150 | F23: 0.625 | G23: 0.45833333 | H23: Nee | I23: +679 672 0222 | J23: Nadi Airport, 9305 Nadi, Fiji
A24: 46321 | B24: 46324 | C24: Brisbane One Apartments by CLLIX | D24: 6755476861 | E24: 477.01 | F24: 0.58333333 | G24: 0.41666667 | H24: Nee | I24: +61 7 3255 0889 | J24: 1 Cordelia Street, South Brisbane, 4101 Brisbane, Australië
A25: 46324 | B25: 46327 | C25: Broken Head Nature Cabins | D25: HMRBDPZKYE | E25: 530 | F25: 0.625 | G25: 0.41666667 | H25: Nee | I25: Niet openbaar | J25: 1 Bundaleer Road, Broken Head, NSW 2481
A26: 46327 | B26: 46328 | C26: Rosella's On Springbrook | D26: 6766283993 | E26: 175.69 | F26: 0.58333333 | G26: 0.41666667 | H26: Nee | I26: +61 427 682 856 | J26: 8 Canyon Parade, 4213 Springbrook, Australië
A27: 46328 | B27: 46330 | C27: Woning in Rainbow Beach | D27: HMD4TRTHAY | E27: 247.65 | F27: 0.625 | G27: 0.41666667 | H27: Nee | I27: Niet openbaar | J27: Rainbow Shores Drive 48/5, Rainbow Beach, Queensland 4581, Australië
A28: 46330 | B28: 46332 | C28: Myuna Holiday Apartments | D28: 5045905618 | E28: 383.45 | F28: 0.625 | G28: 0.41666667 | H28: Nee | I28: +61 7 5447 5588 | J28: 19 Katharina Street, 4567 Noosa Heads, Australië
A29: 46332 | B29: 46334 | C29: Blackwattle Farm (Tall Gum Tiny House, Glass House Mountains) | D29: 562738 | E29: 379.53 | F29: 0.58333333 | G29: 0.41666667 | H29: Ja | I29: +61 408 536 815 | J29: 123 Old Peachester Road, Beerwah, Queensland, Australia
A30: 46334 | B30: 46341 | C30: Airbnb Port Douglas - Reef Nest | D30: HMB3YMXBCS | E30: 898.39 | F30: 0.58333333 | G30: 0.41666667 | H30: Nee | I30: Niet openbaar | J30: 19-37 Saint Crispins Avenue Unit 28, Port Douglas, QLD 4877, Australia
A31: 46341 | B31: 46342 | C31: Cape Trib Beach House | D31: 5293053886 | E31: 137.73 | F31: 0.58333333 | G31: 0.41666667 | H31: Nee | I31: +61 7 4098 0030 | J31: 7 Rykers Road, 4873 Cape Tribulation, Australië
A32: 46342 | B32: 46343 | C32: Chambers Wildlife Rainforest Lodges (Tablelands) | D32: 6645797482 | E32: 128.55 | F32: 0.58333333 | G32: 0.41666667 | H32: Nee | I32: +61 7 4095 3754 | J32: Eacham Close, 4884 Lake Eacham, Australië
A33: 46343 | B33: 46344 | C33: Cairns Colonial Club Resort | D33: 6817625650 | E33: 114 | F33: 0.58333333 | G33: 0.41666667 | H33: Nee | I33: +61 7 4053 8800 | J33: 18-26 Cannon St, Manunda QLD 4870, Australië
A34: 46344 | B34: 46348 | C34: Airbnb Sydney - Cremorne Point | D34: HMPQJZ93WF | E34: 984 | F34: 0.625 | G34: 0.41666667 | H34: Nee | I34: Niet openbaar | J34: 5 Milson Rd, Cremorne Point NSW 2090, Australia
A35: 46348 | B35: 46351 | C35: Holiday Haven Bendalong (Bayview) | D35: 409217 | E35: 446.87 | F35: 0.58333333 | G35: 0.41666667 | H35: Nee | I35: +61 2 4444 8860 | J35: 1 Waratah Street, Bendalong, New South Wales 2539, Australia
A36: 46351 | B36: 46353 | C36: Discovery Parks - Narooma Beach | D36: #J-5894241 | E36: 230.14 | F36: 0.58333333 | G36: 0.41666667 | H36: Nee | I36: +61 2 4402 3247 | J36: Niet vermeld in e-mail (park: Narooma, NSW)
A37: 46353 | B37: 46354 | C37: Discovery Parks - Eden | D37: #J-5894300 | E37: 137.86 | F37: 0.58333333 | G37: 0.41666667 | H37: Nee | I37: +61 2 6496 1572 | J37: 731 Princes Hwy, Boydtown NSW 2551, Australië
A38: 46354 | B38: 46355 | C38: BIG4 Traralgon Park Lane Holiday Park | D38: 6218660708 | E38: 145.17 | F38: 0.58333333 | G38: 0.41666667 | H38: Nee | I38: +61 3 5174 6749 | J38: 5353 Princes Highway, 3844 Traralgon, Australië
A39: 46355 | B39: 46357 | C39: Wilsons Prom Accommodation - Tidal River Cabins | D39: 16014854 | E39: 438.14 | F39: 0.58333333 | G39: 0.41666667 | H39: Nee | I39: +61 3 8427 2122 | J39: Tidal River, Wilsons Promontory National Park, VIC (exact adres niet vermeld)
A40: 46357 | B40: 46360 | C40: Warburton Holiday Park (Riverside Two Bedroom Ensuite Cabin) | D40: 3218364 | E40: 332.21 | F40: 0.58333333 | G40: 0.41666667 | H40: Nee | I40: +61 3 5966 2277 | J40: 30 Woods Point Rd, Warburton VIC 3799, Australia
A41: 46360 | B41: 46362 | C41: Bimbi Park | D41: 74285295 | E41: 312.67 | F41: 0.625 | G41: 0.41666667 | H41: Nee | I41: +61 3 5237 9246 | J41: 90 Manna Gum Drive, VIC 3233, Australia
A42: 46362 | B42: 46366 | C42: Breaside | D42: 0 | E42: 0 | F42: 0.41666667 | G42: 0.45833333 | H42: Ja | I42: +61 3 5426 1762 | J42: 47 Taylors Rd, Mount Macedon VIC 3441, Australië
A43: 46366 | B43: 46369 | C43: Airbnb Melbourne (Lonsdale St) | D43: HMSQN94X8J | E43: 513.59 | F43: 0.625 | G43: 0.45833333 | H43: Nee | I43: Niet openbaar | J43: 639 Lonsdale St, Melbourne VIC 3000, Australia
A44: 46369 | B44: 46372 | C44: Renatal in Christchurch | D44: 5217361899 | E44: 337.47 | F44: 0.58333333 | G44: 0.41666667 | H44: Nee | I44: Niet openbaar | J44: 176 manchecter street 107,8011 Christchurch
A45: 46372 | B45: 46373 | C45: The Shearer's Quarters (Lake Tekapo) | D45: 5698108945 | E45: 205.97 | F45: 0.58333333 | G45: 0.41666667 | H45: Nee | I45: +64 21 273 3576 | J45: Irishman Creek Station, 7999 Lake Tekapo, Nieuw-Zeeland
A46: 46373 | B46: 46374 | C46: Mt Cook Motels (B&B pakket, Aoraki/Mount Cook) | D46: R184C2 | E46: 256.8 | F46: 0.625 | G46: 0.41666667 | H46: Ja | I46: +64 3 435 1809 | J46: Mt Cook Lodge, Aoraki/Mount Cook Village, New Zealand
A47: 46374 | B47: 46375 | C47: Century House B&B flatlette (Moeraki/Oamaru) | E47: 131 | F47: 0.625 | G47: 0.41666667 | H47: Ja | I47: +64 3 434 1514 | J47: 114 Wansbeck Street, 9401 Oamaru, Nieuw-Zeeland
A48: 46375 | B48: 46377 | C48: Te Anau Lakeview Holiday Park & Motels (Familiestudio) | D48: 6302493913 | E48: 283.79 | F48: 0.58333333 | G48: 0.41666667 | H48: Nee | I48: +64 3 249 7457 | J48: 77 Te Anau - Manapouri Highway, 9640 Te Anau, Nieuw-Zeeland
A49: 46377 | B49: 46379 | C49: Hampshire Holiday Parks - Queenstown Lakeview (2 Bedroom Cabin) | D49: 3103778 | E49: 326.1 | F49: 0.625 | G49: 0.41666667 | H49: Nee | I49: +64 3 442 7252 | J49: 4 Cemetery Road, Queenstown, Otago 9300
A50: 46379 | B50: 46381 | C50: Albert Town, Wānaka Townhouse - Toi Toi | D50: 5500411767 | E50: 324.06 | F50: 0.625 | G50: 0.41666667 | H50: Nee | I50: Niet openbaar | J50: 19A Kidds Way, 9305 Albert Town, Nieuw-Zeeland
A51: 46381 | B51: 46383 | C51: Rainforest Retreat - Tuatara Cottages (Franz Josef) | D51: marTend97s69NzRa | E51: 203.81 | F51: 0.625 | G51: 0.41666667 | H51: Nee | I51: +64 3 752 0220 | J51: 46 Cron St, 7886 Franz Josef, New Zealand
A52: 46383 | B52: 46384 | C52: Punakaiki Beachfront Motels (Superior Studio) | D52: 6245102037 | E52: 155.41 | F52: 0.625 | G52: 0.41666667 | H52: Nee | I52: +64 3 731 1188 | J52: Mabel Street, 7873 Punakaiki, Nieuw-Zeeland
A53: 46384 | B53: 46387 | C53: The Barn Cabins & Camp (Abel Tasman) | D53: 177090555186659 | E53: 502.9 | F53: 0.625 | G53: 0.41666667 | H53: Nee | I53: +64 3 527 8043 | J53: 14 Harvey Road, Marahau, Abel Tasman, Motueka, Tasman, New Zealand 7197
A54: 46387 | B54: 46389 | C54: Collingwood Cottage (Collingwood/Pohara) | D54: 6258080939 | E54: 278.2 | F54: 0.625 | G54: 0.41666667 | H54: Nee | I54: Niet openbaar | J54: 40 Ruataniwha Drive, 7073 Collingwood, Nieuw-Zeeland
A55: 46389 | B55: 46390 | C55: Broadway Motel Picton (Family Apartment) | D55: 12036833 | E55: 147.25 | F55: 0.625 | G55: 0.41666667 | H55: Nee | I55: +64 3 573 6563 | J55: 113 High Street, Picton 7220, New Zealand
A56: 46390 | B56: 46392 | C56: Wellington - Self-contained garden apartment (Airbnb) | D56: HMC2EDRC5F | E56: 237.55 | F56: 0.625 | G56: 0.41666667 | H56: Nee | I56: Niet openbaar | J56: Wellington, Nieuw-Zeeland (geen straatadres vermeld)
A57: 46392 | B57: 46394 | C57: Mangorei Heights - New Plymouth | D57: 6659372320 | E57: 365.03 | F57: 0.58333333 | G57: 0.41666667 | H57: Ja | I57: +64 21 334 012 | J57: 1801 Mangorei Road, 4371 New Plymouth, Nieuw-Zeeland
A58: 46394 | B58: 46395 | C58: Top 10 Waitomo | D58: 5099658178 | E58: 139.45 | F58: 0.58333333 | G58: 0.41666667 | H58: Nee | I58: +64 7 878 7639 | J58: 12 Waitomo Village Rd
A59: 46395 | B59: 46399 | C59: Taupo Debretts Spa Resort (Villa) | D59: 6354656702 | E59: 794.86 | F59: 0.58333333 | G59: 0.41666667 | H59: Nee | I59: +64 7 378 8559 | J59: 76 Napier-Taupo Road, 3330 Taupo, Nieuw-Zeeland
A60: 46399 | B60: 46401 | C60: Hideaway of Rotorua (Deluxe Familiekamer met Spabad) | D60: 6199742293 | E60: 310.05 | F60: 0.58333333 | G60: 0.41666667 | H60: Nee | I60: +64 7 357 4717 | J60: 436 Ngongotaha Road, 3015 Rotorua, Nieuw-Zeeland
A61: 46401 | B61: 46406 | C61: Hot Water Beach TOP 10 Holiday Park (Deluxe Family Villa) | D61: 3122788 | E61: 1031.79 | F61: 0.625 | G61: 0.41666667 | H61: Nee | I61: +64 7 866 3116 | J61: 790 Hot Water Beach Road, Whitianga 3591, NZ
A62: 46406 | B62: 46408 | C62: Grand Millennium Auckland | D62: 5516542081 | E62: 216.26 | F62: 0.625 | G62: 0.41666667 | H62: Nee | I62: +64 9 366 3000 | J62: 71 Mayoral Dr, Cnr Vincent St, 1010 Auckland, Nieuw-Zeeland
A63: 46408 | B63: 46412 | C63: Grand Copthorne Waterfront Hotel | D63: 6968451239 | E63: 897.64 | F63: 0.625 | G63: 0.41666667 | H63: Ja | I63: +65 6733 0880 | J63: 392 Havelock Road Singapore, 169663
A64: 46412 | B64: 46416 | C64: The Sands Khao Lak | D64: SKL-HP20462 | E64: 870.3 | F64: 0.625 | G64: 0.41666667 | H64: Ja | I64: +66 76 428 800 | J64: 10/18 Petchakasem Rd. Moo 7 Kukkak ,Takuapa ,Phang Nga 82190
A65: 46416 | B65: 46419 | C65: Magical Mountain View Resort | D65: MMV-TH953 | E65: 447.61 | F65: 0.625 | G65: 0.41666667 | H65: Ja | I65: +66 64 017 2362 | J65: 292/1 Moo 7, T. Khlongsong, A.Panom Surat Thani,
A66: 46419 | B66: 46424 | C66: Sai Naam Lanta Residence | D66: 1007 | E66: 688.43 | F66: 0.625 | G66: 0.41666667 | H66: Nee | I66: +66 75 684 188 | J66: 541/2 Moo 2, Saladan, Koh Lanta Krabi 81150
A67: 46424 | B67: 46426 | C67: Poonsiri Resort Aonang | D67: 5275629477 | E67: 292.65 | F67: 0.625 | G67: 0.41666667 | H67: Ja | I67: +66 75 656 260 | J67: 211 Moo 4 T.Aonang, Muang, Krabi, 81000 Ao Nang Beach
A68: 46426 | B68: 46429 | C68: Baan Karon Resort | D68: 5808883659 | E68: 491.15 | F68: 0.625 | G68: 0.41666667 | H68: Ja | I68: +66 76 396 573 | J68: 213 Patak, Phuket, 83100 Karon Beach, Thailand
A69: 46429 | B69: 46431
A70: 46431 | B70: 46432 | C70: Ilboru Safari Lodge | E70: 12000 | H70: Ja
A71: 46432 | B71: 46434 | C71: Tarangire Safari Lodge | H71: Ja
A72: 46434 | B72: 46436 | C72: Kon Tiki Migration Tented Camp Ndutu | H72: Ja
A73: 46436 | B73: 46438 | C73: Kubu Kubu Tented Lodge by Tanganyika Wilderness Camps | H73: Ja
A74: 46438 | B74: 46439 | C74: Ang'ata Ngorongoro Camp | H74: Ja
A75: 46439 | B75: 46440 | C75: Manyara Best View Lodge and Spa
D150: Totaal | E150: =SUM(E3:E149) -> 36949.08

Sheet Verzekeringen
A2: Kosten verzekeringen
A3: Type verzekering | B3: Kosten per maand | C3: verzekeraar | D3: Polis nummer
A4: CZ basis + aanvullend: alle medische zorg | B4: 352 | C4: CZ | D4: Bas 484990306 Maartje 484990276 Liz 484990284 Isa 484990292
A5: Special ISIS Super + Basis: de volwaardige reisverzekering | B5: 168 | C5: Special isis
A6: OOM annuleringsverzekering: annulering vóór vertrek | B6: 44.15 | C6: OOM | D6: TIB7122782
A7: OOM Achtergebleven Woonhuis: opstal en inboedel | B7: 132 | C7: OOM
A11: afzonderlijke huurauto-/camperverzekeringen | C11: meerdere
A16: totaal | B16: =SUM(B3:B15) -> 696.15

Sheet Excursies en activiteien
A1: Kosten excursies en activiteiten | C1: Betaald | D1: Geboekt | E1: Datum | F1: Adres | G1: Website
A2: Amerika
A3: America the Beautiful pas | B3: 80 | C3: Ja | D3: Ja | G3: https://www.nps.gov/planyourvisit/passes.htm
A4: Fietshuur San fransisco | B4: 160 | E4: 46286 | F4: 2715 Hyde Street, San Francisco, CA 94109, Verenigde Staten | G4: https://www.blazingsaddles.com/san-francisco/locations
A5: Bodie Ghost Town | B5: 26 | E5: 46307 | F5: Highway 270, Bridgeport, CA 93517, Verenigde Staten | G5: https://www.parks.ca.gov/bodie
A6: The Sphere Experience Las Vegas | B6: 450 | E6: 46305 | F6: 255 Sands Avenue, Las Vegas, NV 89169, Verenigde Staten | G6: https://www.thesphere.com/shows/the-sphere-experience
A7: Antelope Canyon X general tour | B7: 210 | C7: Ja | D7: Ja | E7: 46299 | F7: Milepost 308, Highway AZ-98, Page, AZ 86040, Verenigde Staten | G7: https://www.antelopecanyon-x.com/canyon-tours/antelope-canyon-x-hiking-tour/
A8: Monument Valley | B8: 30 | E8: 46298 | F8: Indian Route 42, Oljato-Monument Valley, AZ 84536, Verenigde Staten | G8: https://navajonationparks.org/navajo-tribal-parks/monument-valley/
A9: Disney anaheim | B9: 405 | C9: Ja | D9: Ja | E9: 46294 | F9: 1313 Disneyland Drive, Anaheim, CA 92802, Verenigde Staten | G9: https://disneyland.disney.go.com/
A10: Santa Monica Pier | B10: 100 | E10: 46292 | F10: 200 Santa Monica Pier, Santa Monica, CA 90401, Verenigde Staten | G10: https://www.santamonicapier.org/
B11: 0
A13: Fiji
A14: ecotrax | B14: 250 | C14: Ja | D14: Ja | E14: 46316 | F14: Cuvu Back Road, Cuvu, Fiji | G14: https://www.ecotrax.com.fj/location
A15: Shark dive kuata island | B15: 100 | E15: 46318 | G15: https://www.barefootsharkencounters.com/the-awakening-shark-dive-fiji
A17: Australie
A18: Australian Zoo | B18: 125 | E18: 46333 | F18: 1638 Steve Irwin Way, Beerwah QLD 4519, Australië | G18: https://australiazoo.com.au/
A19: Noosa Everglades SELF GUIDED Kayak | B19: 165 | E19: 46331 | F19: 204 Lake Flat Road, Elanda Point National Park Canoe Launch Area, Boreen Point QLD 4565, Australië | G19: https://www.kanukapersaustralia.com/contact/meeting-place/
A20: Noosa Dolphin Kayak Tour | B20: 410 | E20: 46332 | F20: 60 Noosa Drive, Noosa Heads QLD 4567, Australië | G20: https://www.epicoceanadventures.com.au/dolphin-view-sea-kayak-tour/
A23: Waterfall route | B23: 0 | E23: 46342 | G23: https://tropicalnorthqueensland.org.au/listing/itinerary/waterfall-circuit/
A24: Crater lakes | B24: 0 | E24: 46342 | F24: Lake Eacham Road, Lake Eacham QLD 4884 | G24: https://parks.qld.gov.au/parks/crater-lakes
A25: Baramundi fishing | B25: 115 | E25: 46340 | F25: Lot 3, Vixies Road, Wonga Beach QLD 4873, Australië | G25: https://www.hookabarra.com/
A26: Low iles snorkeling | B26: 330 | E26: 46337 | F26: Crystalbrook Marina, 44 Wharf Street, Port Douglas QLD 4877, Australië | G26: https://wavedancerlowisles.com/
A27: Wildlife habitat | B27: 75 | E27: 46338 | F27: 1 Port Douglas Road, Port Douglas QLD 4877, Australië | G27: https://www.wildlifehabitat.com.au/
A28: Beach horseback riding | B28: 120 | E28: 46336 | F28: 3812 Cape Tribulation Road, Cape Tribulation QLD 4873, Australië | G28: https://www.capetribhorserides.com.au/
A29: Daintree Discovery Centre | B29: 60 | E29: 46336 | F29: 24 Tulip Oak Road, Cow Bay QLD 4873, Australië | G29: https://www.discoverthedaintree.com/
A30: Mossman Gorge | B30: 20 | E30: 46335 | F30: 212R Mossman Gorge Road, Mossman Gorge QLD 4873, Australië | G30: https://www.mossmangorge.com.au/
A31: kuranda butterfly sanctuary | B31: 35 | E31: 46343 | F31: 8 Rob Veivers Drive, Kuranda QLD 4881, Australië | G31: https://australianbutterflies.com/
A32: WAGS boottocht | B32: 0 | E32: 46337 | F32: 1 Spinnaker Close, Port Douglas QLD 4877, Australië | G32: https://www.portdouglasyachtclub.com.au/
A34: Australian Museum | B34: 0 | E34: 46347 | F34: 1 William Street, Sydney NSW 2010, Australië | G34: https://australian.museum/
A35: Pylon Lookout & Museum (harbour bridge) | B35: 50 | E35: 46345 | F35: South-East Pylon, Sydney Harbour Bridge, Sydney NSW 2000, Australië | G35: https://www.bridgemuseum.com.au/
A36: Macquarie’s Chair & Royal Botanic Gardens | B36: 0 | E36: 46347 | F36: Mrs Macquaries Road, Sydney NSW 2000, Australië | G36: https://www.botanicgardens.org.au/royal-botanic-garden-sydney
A37: Sydney Harbour ferry dagtocht | B37: 30 | E37: 46345 | G37: https://transportnsw.info/travel-info/ways-to-get-around/ferry
B38: 0
A39: Pebbly beach | B39: 0 | E39: 46351 | F39: Pebbly Beach Road, Pebbly Beach NSW 2536, Australië | G39: https://www.nationalparks.nsw.gov.au/things-to-do/picnic-areas/pebbly-beach-picnic-area
A40: Durras North Beach | B40: 0 | E40: 46351 | F40: North Durras Road, Durras North NSW 2536, Australië | G40: https://www.nsw.gov.au/visiting-and-exploring-nsw/locations-and-attractions/north-durras-beach
B41: 0
A42: Warburton River Tubing | B42: 135 | E42: 46357 | F42: Warburton Cricket Club, 3455–3457 Warburton Highway, Warburton VIC 3799, Australië | G42: https://www.warburtonadventure.com.au/adventures/self-guided-river-tubing-adventure/
A43: Nationaal park Great Otway | B43: 0 | E43: 46361 | F43: Great Ocean Road, Lorne VIC 3232, Australië | G43: https://www.parks.vic.gov.au/places-to-see/parks/great-otway-national-park
A44: Hanging Rock | B44: 0 | E44: 46364 | F44: 139 South Rock Road, Woodend VIC 3442, Australië | G44: https://www.mrsc.vic.gov.au/See-Do/Our-Region/Natural-Attractions/Hanging-Rock/Plan-Your-Visit
A45: Yarra ranges NT | B45: 0 | E45: 46358 | G45: https://www.parks.vic.gov.au/places-to-see/parks/yarra-ranges-national-park
B46: 0
A47: ACMI | B47: 0 | E47: 46368 | F47: Federation Square, Flinders Street, Melbourne VIC 3000, Australië | G47: https://www.acmi.net.au/
A48: Queen Victoria Market | B48: 0 | E48: 46367 | F48: Queen Street, Melbourne VIC 3000, Australië | G48: https://qvm.com.au/visit-us/
A49: City Circle Tram | B49: 0 | E49: 46367 | G49: https://transport.vic.gov.au/route/15834/35-city-circle-free-tourist-tram
A50: Luna Park St Kilda | B50: 60 | E50: 46368 | F50: 18 Lower Esplanade, St Kilda VIC 3182, Australië | G50: https://lunapark.com.au/
A51: De laneways & straatkunst | B51: 0 | E51: 46367 | F51: 20 Duckboard Pl, Melbourne VIC 3000, Australië | G51: https://www.komoot.com/nl-nl/tour/3192928549?share_token=aXxsZ4xh4f2cbHJ5mcjwqgwY9RyNIfZJCbUx8xh56YyKQ6AGd2&ref=wtd&t_s=referral&t_cid=route_share&t_ref_username=5138285305045
A52: Penguins at St Kilda Pier | B52: 0 | E52: 46368 | F52: Pier Road, St Kilda VIC 3182, Australië | G52: https://www.penguins.org.au/attractions/st-kilda/
B53: 0
B54: 0
B55: 0
A57: Nieuw Zeeland
A58: The Mount John Observatory (Tekapo) | B58: 50 | E58: 46372 | F58: 422 Godley Peaks Road, Lake Tekapo 7945, Nieuw-Zeeland | G58: https://www.darkskyproject.co.nz/experiences/the-summit-experience/
A59: Milford Sound tours | B59: 300 | C59: Ja | D59: Ja | E59: 46376 | F59: Milford Sound Visitor Terminal, Milford Sound 9679, Nieuw-Zeeland | G59: https://www.realnz.com/en/experiences/day-cruises/milford-sound-signature-cruise/
A60: Abel Tasman boten (3x) | B60: 300 | E60: 46385 | F60: 2 Kaiteriteri-Sandy Bay Road, Kaiteriteri, Nieuw-Zeeland | G60: https://www.abeltasmanseashuttles.co.nz/
A61: Te Papa Museum | B61: 0 | E61: 46391 | F61: 55 Cable Street, Wellington 6011, Nieuw-Zeeland | G61: https://tepapa.govt.nz/
A62: Geothermisch Rotorua | B62: 80 | E62: 46399 | F62: 201 Waiotapu Loop Road, RD 3, Rotorua 3073, Nieuw-Zeeland | G62: https://www.waiotapu.co.nz/
A63: Cathedral Cove Kayak Tour | B63: 360 | E63: 46404 | F63: Hahei Beach car park, einde Hahei Beach Road, Hahei, Nieuw-Zeeland | G63: https://kayaktours.co.nz/
A64: Mitai Maori Villag | B64: 280 | E64: 46399 | F64: 196 Fairy Springs Road, Rotorua 3015, Nieuw-Zeeland | G64: https://www.mitai.co.nz/
A65: Golden bay kayaks | B65: 200 | E65: 46388 | F65: 29 Cornwall Place, Tākaka, Nieuw-Zeeland | G65: https://www.goldenbaykayaks.co.nz/
A66: Te Waikoropupu Springs | B66: 0 | E66: 46387 | F66: Pupu Springs Road, Tākaka 7183, Nieuw-Zeeland | G66: https://www.doc.govt.nz/parks-and-recreation/places-to-go/nelson-tasman/places/takaka-area/te-waikoropupu-springs/
A67: Hokitika Gorge | B67: 0 | E67: 46383 | F67: Whitcombe Valley Road, Hokitika 7881, Nieuw-Zeeland | G67: https://www.doc.govt.nz/parks-and-recreation/places-to-go/west-coast/places/hokitika-gorge-scenic-reserve/
A68: PUNAKAIKI CAVERN | B68: 0 | E68: 46383 | F68: State Highway 6, Punakaiki, Nieuw-Zeeland | G68: https://www.doc.govt.nz/parks-and-recreation/places-to-go/west-coast/places/paparoa-national-park/things-to-do/tracks/punakaiki-cavern/
A69: Lake Mangamaho | B69: 0 | E69: 46393 | F69: Lake Mangamahoe Road, New Plymouth, Nieuw-Zeeland | G69: https://www.npdc.govt.nz/leisure-and-culture/riding-and-walking/lake-mangamahoe/
A70: Blue Pools, Haast Pass, Wānaka | B70: 0 | E70: 46381 | F70: Blue Pools car park, Haast Highway (SH6), Makarora, Nieuw-Zeeland | G70: https://www.doc.govt.nz/parks-and-recreation/places-to-go/otago/places/mount-aspiring-national-park/things-to-do/tracks/blue-pools-track/
A71: Tekapo springs | B71: 70 | E71: 46372 | F71: 300 Lakeside Drive, Lake Tekapo 7945, Nieuw-Zeeland | G71: https://tekaposprings.co.nz/
A72: key summit track | B72: 0 | E72: 46376 | F72: The Divide, Milford Road (SH94), Fiordland, Nieuw-Zeeland | G72: https://www.doc.govt.nz/parks-and-recreation/places-to-go/fiordland/places/fiordland-national-park/things-to-do/tracks/routeburn-track-key-summit-track/
B73: 0
A75: Thailand
A76: Railay Beach & Phra Nang cave beach | B76: 20 | E76: 46425 | F76: 2R4Q+944, Stadt, Ao Nang, Mueang Krabi District, Krabi, Thailand | G76: https://www.tourismthailand.org/Attraction/railay-beach
A77: merald Pool & Hot Springs (Krabi binnenland) | B77: 20 | E77: 46425 | F77: Khlong Thom Nuea, Khlong Thom District, Krabi 81120, Thailand | G77: https://www.tourismthailand.org/Attraction/sa-morakot-emerald-pool
A78: Similian | B78: 200 | E78: 46414 | G78: https://www.tourismthailand.org/Attraction/mu-ko-similan-national-park
B79: 0
B80: 0
B81: 0
B82: 0
B83: 0
B84: 0
A86: Tanzania
A92: Totaal atracties en excursies en NT parks | B92: =SUM(B3:B91) -> 5421
A93: Betaald | B93: =SUMIF(C2:C91,"Ja",B2:B91) -> 1245

Sheet Vluchten en vervoer
A2: vliegtickets
A3: Vertrek datum | B3: Vertrek tijd | C3: Van | D3: Naar | E3: Aankomst datum | F3: Aankomst rijd | G3: Kosten | H3: Vlucht Nummer | I3: Stoelen
A4: 46284 | B4: 0.32986111 | C4: Amsterdam | D4: Londen (Heathrow) | E4: 46284 | F4: 0.34375 | G4: 2043 | H4: BA0445 | I4: Nog niet gekozen
A5: 46284 | B5: 0.44791667 | C5: Londen (Heathrow) | D5: San Francisco | E5: 46284 | F5: 0.57638889 | G5: 0 | H5: BA0285 | I5: 30A, 30B, 31A, 31B
A6: 46311 | B6: 0.95486111 | C6: San Francisco | D6: Nadi (Fiji) | E6: 46313 | F6: 0.22222222 | G6: 1100 | H6: FJ871 | I6: 12A, 12B, 11A, 11B
A7: 46321 | B7: 0.34722222 | C7: Nadi (Fiji) | D7: Brisbane | E7: 46321 | F7: 0.44097222 | G7: 741 | H7: FJ921 | I7: 12A, 12B, 11A, 11B
A8: 46334 | B8: 0.48263889 | C8: Brisbane | D8: Cairns | E8: 46334 | F8: 0.58333333 | G8: 440 | H8: VA783 | I8: 17A, 18A, 17B, 18B
A9: 46344 | B9: 0.45486111 | C9: Cairns | D9: Sydney | E9: 46344 | F9: 0.62152778 | G9: 440 | H9: VA1416 | I9: 17A, 18A, 17B, 18B
A10: 46369 | B10: 0.50347222 | C10: Melbourne | D10: Christchurch | E10: 46369 | F10: 0.72222222 | G10: 1015 | H10: JQ171 | I10: 11A, 10A, 10B, 11B
A11: 46408 | B11: 0.47222222 | C11: Auckland | D11: Singapore | E11: 46408 | F11: 0.70486111 | G11: 1200 | H11: SQ4284 | I11: Nog niet gekozen
A12: 46412 | B12: 0.54166667 | C12: Singapore | D12: Phuket | E12: 46412 | F12: 0.58680556 | G12: 570 | H12: SQ732 | I12: 51A, 52A, 51B, 52B
A13: 46427 | B13: 0.34722222 | C13: Phuket | D13: Doha | E13: 46427 | F13: 0.47569444 | G13: 1300 | H13: QR843 | I13: 27J, 27K, 28J, 28K
A14: 46430 | B14: 0.35069444 | C14: Doha | D14: Tanzania (Kilimanjaro) | E14: 46430 | F14: 0.69097222 | G14: 1300 | H14: QR1476 | I14: 27J, 27K, 28J, 28K
A15: 46440 | B15: 0.90972222 | C15: Kilimanjaro (Tanzania) | D15: Amsterdam | E15: 46441 | F15: 0.31944444 | G15: 2600 | H15: KL0569 | I15: 35A, 35B, 34C, 35C
F29: totaal | G29: =SUM(G4:G28) -> 12749
A32: Auto en camper huur
A33: Ophaal datum | B33: Ophaal tijd | C33: Ophaal locatie | D33: Inlever locatie | E33: inlever datum | F33: Inlever tijd | G33: Kosten | H33: Reserverings nummer | I33: overige
A34: 46287 | B34: 0.41666667 | C34: Budget Howard Street 821 Howard Street San Fransisco 94103 | D34: San Francisco Airport (780 McDonnell Road) | E34: 46311 | F34: 0.83333333 | G34: 1153.1 | H34: 740.401.507 | I34: Toyota RAV4 of vergelijkbaar, Budget, tel. +1 415 957 9998
A35: 46324 | B35: 0.41666667 | C35: Hertz Brisbane Downtown, 55 Charlotte St, Brisbane City QLD 4000, Australië | D35: Hertz, Airport Dr, Brisbane Airport QLD 4007, Australië | E35: 46334 | F35: 0.39583333 | G35: 380 | H35: 711.800.522 | I35: Subaru Forester of vergelijkbaar, Hertz
A36: 46334 | B36: 0.58333333 | C36: Cairns Luchthaven (CNS) | D36: Cairns Luchthaven (CNS) | E36: 46344 | F36: 0.375 | G36: 239.1 | H36: D012668926 | I36: MG HS of vergelijkbaar (Standaard SUV), Bargain Car Rentals
A37: 46348 | B37: 0.45833333 | C37: Sixt Domain Carpark, 52 sir John Young Cresent, Sydney | D37: Shop 10, Southern Cross Station, Docklands VIC 3008 | E37: 42714 | F37: 0.45833333 | G37: 1250 | H37: 9.731.393.908 | I37: Mitsubishi Eclips of vergelijkbaar (Standaard SUV)
A38: 46372 | B38: 0.45833333 | C38: Christchurch airport, 170 Orchard Road Harewood | D38: Auckland downtown 60-64 The Strand Parnell | E38: 46406 | F38: 0.45833333 | G38: 1500 | H38: U-509894 | I38: Mitsubishi Outlander of vergelijkbaar (Premium SUV), Snap Rentals, borg NZD 2.000
F51: totaal | G51: =SUM(G34:G50) -> 4522.2
A54: Boten / bussen / trein / taxi
A55: reis datum vertrek | B55: Vertrek tijd | C55: Vertrek locatie | D55: Aankomst locatie | E55: aankomst datum | F55: aankomst tijd | G55: Kosten | H55: Reserverings nummer | I55: overige
C63: Thailand | G63: 480
F96: totaal | G96: =SUM(G56:G95) -> 480

Sheet To Do
A1: Fase | B1: Taak | C1: Details/Notities | D1: Status
A2: 45950 | B2: school – eerste overleg | C2: Afspraak met school en leerplicht; globaal plan voor onderwijs en verslaglegging. | D2: x
A3: 45985 | B3: Budget & noodbuffer bepalen | C3: Groffe raming kosten per land + noodbuffer bepalen; aparte spaarrekening/nood-creditcard kiezen. | D3: x
A4: 45985 | B4: Route & verblijfsduur per land definitief maken | C4: Data-blokken per land (USA, Fiji, Australië, NZ, Thailand, Tanzania) vastleggen; nodig voor verzekeringen/visa. | D4: x
A5: 45985 | B5: Hoofdvliegtickets boeken | C5: Intercontinentale vluchten (bijv. AMS–LA, LA–Fiji, Fiji–Aus, NZ–Thailand, Thailand–Tanzania, terug naar NL); kunnen ca. 11 maanden voor vertrek worden geboekt – nu oppakken. | D5: x
A6: 45992 | B6: Paspoorten Aanvragen | C6: Aflopende data checken; moeten minstens 6 maanden geldig zijn na terugkomst; zo nodig verlengen plannen. | D6: x
A8: 46023 | B8: Langdurige reisverzekering uitzoeken | C8: Werelddekking, medische kosten, repatriëring, sport; polisvoorwaarden vergelijken.
A9: 46023 | B9: Annuleringsverzekering kiezen | C9: Let op samengestelde reis (veel losse vluchten/accommodaties); voorwaarden goed checken. | D9: x
A10: 46023 | B10: Aansprakelijkheid & rechtsbijstand checken | C10: Werelddekking en gezinsdekking controleren; evt. upgraden.
A11: 46023 | B11: Basiszorgverzekering checken | C11: Checken hoe doorlopende dekking werkt bij 5 maanden weg; BRP ingeschreven blijven. | D11: x
A12: 46023 | B12: Vluchten Australie Nieuw Zeeland boeken | C12: Welke vluchten binnen landen/ tussen landen al geboekt zijn en welke nog moeten; in sheet verwerken. | D12: x
A14: 46054 | B14: GGD-reisadvies plannen | C14: Afspraak maken voor vaccinatie-advies voor alle landen; tijdig plannen i.v.m. series. | D14: x
A15: 46054 | B15: Tandarts- en huisartscontrole | C15: Controle voor vertrek; medicijnen op recept regelen + Engelstalige verklaring indien nodig. | D15: x
A16: 46054 | B16: Medische & bankmachtigingen regelen | C16: Toestemmingen voor elkaar/thuisfront; bankvolmachten; kopieën ID’s en paspoorten.
A18: 46083 | B18: Vluchten Thailand en Tanzania boeken | C18: Welke vluchten binnen landen/ tussen landen al geboekt zijn en welke nog moeten; in sheet verwerken. | D18: x
A19: 46082 | B19: Verzekeringen definitief afsluiten | C19: Reis-, annulerings-, aansprakelijkheid en eventuele aanvullingen daadwerkelijk afsluiten.
A20: 46082 | B20: Vaccinaties starten/afronden | C20: Eerste prikken zetten; series op tijd afronden voor vertrek. | D20: x
A21: 46082 | B21: Internationaal rijbewijs regelen | C21: Voor VS en Australië; bij ANWB aanvragen.
A22: 46082 | B22: Schoolafspraken vastleggen | C22: Zwarte-op-wit afspraken over leerdoelen, portfolio en terugkoppeling na de reis. | D22: x
A23: 46082 | B23: Huurders woning zoeken | C23: Huisoppas/onderverhuur | D23: x
A25: 46113 | B25: Onderwijsplan kinderen uitwerken | C25: Basisstructuur: dagelijks lezen, 3–4x per week rekenen/taal; materialen/apps selecteren. | D25: x
A26: 46113 | B26: ESTA aanvragen (USA) | C26: Voor alle gezinsleden; geldig tot 2 jaar, maar ruim op tijd regelen. | D26: x
A27: 46113 | B27: Visa/ETA Australië regelen | C27: eVisitor/ETA voor Australië; voorwaarden nalezen. | D27: x
A28: 46113 | B28: NZeTA + IVL aanvragen (Nieuw-Zeeland) | C28: Online aanvraag; ook voor kinderen.
A29: 46113 | B29: Visa-check overige landen | C29: Thailand, Tanzania, Fiji: actuele eisen checken; noteren wat wanneer aangevraagd moet worden. | D29: x
A31: 46143 | B31: Extra betaalmiddelen regelen | C31: Tweede creditcard per volwassene; limieten verhogen; reisnotitie bij bank. | D31: x
A32: 46143 | B32: Wise/Revolut account instellen | C32: Rekening openen, kaarten bestellen, testtransactie doen; budgetten per valuta instellen. | D32: x
A33: 46143 | B33: Thuisfront/contactpersoon aanwijzen | C33: Iemand die post, Belastingdienst en evt. school kan afhandelen. | D33: x
A34: 46143 | B34: Overzicht vaste lasten maken | C34: Lijst van abonnementen, verzekeringen en vaste lasten voor thuis; beslissen wat pauzeerbaar is. | D34: x
A36: 46174 | B36: Woningregeling uitwerken | C36: Huisoppas/onderverhuur regelen; afspraken vastleggen (sleutels, planten, onderhoud). | D36: x
A37: 46174 | B37: Abonnementen & energie optimaliseren | C37: Bepalen welke abonnementen tijdelijk stop of omlaag kunnen (sport, kranten, tv, etc.). | D37: x
A38: 46174 | B38: Auto | C38: Auto stallen of door iemand laten gebruiken; verzekering checken | D38: x
A39: 46174 | B39: Noodplan thuisfront | C39: Maken van eenvoudig draaiboek: bij schade, lekkage, storingen, belangrijke post.
A41: 46204 | B41: Onderwijs praktisch maken | C41: Lesmateriaal kopen/printen; apps installeren; basis-weekrooster maken. | D41: x
A42: 46204 | B42: Portfolio-structuur opzetten | C42: Folder/Drive/OneDrive map met submappen per maand/land; manier van verslaglegging afspreken. | D42: x
A43: 46204 | B43: Telecom & data plannen | C43: Keuze voor eSIM/roaming; per regio beste opties; automatische foto-back-up instellen.
A44: 46204 | B44: Reis-EHBO samenstellen | C44: Basis EHBO + specifieke medicatie voor kinderen; doseringen uitprinten en meenemen.
A46: 46235 | B46: Eerste en belangrijke overnachtingen controleren | C46: Checken of alle kritieke nachten (eerste nachten per continent, safari, eilanden) geboekt en bevestigd zijn.
A47: 46235 | B47: Autohuur/camperhuur dubbelchecken | C47: Alle boekingen, verzekeringen en kinderzitjes controleren; vouchercodes en voorwaarden printen.
A48: 46235 | B48: Noodcontacten & documenten in orde maken | C48: Overzicht verzekeringsnummers, alarmcentrale, ambassade, ICE-contacten; opslaan in telefoon en printen.
A49: 46235 | B49: Paklijst definitief maken | C49: Lijst per persoon (kleding, schoenen, schoolspullen); bepalen wat nog gekocht moet worden.
A51: BEGIN SEPT 2026 | B51: Papiermap & digitale map vullen | C51: Paspoorten, visa, polissen, medische verklaringen, vaccinatieboekjes, schoolafspraken, kopieën ID.
A52: BEGIN SEPT 2026 | B52: Financiële laatste check | C52: Noodcash regelen, kaartlimieten checken; overzicht reisbudget per land in sheet klaarzetten.
A53: BEGIN SEPT 2026 | B53: Noodplan verlies/diefstal uitwerken | C53: Stappenplan bij verlies paspoort/telefoon/kaart; blokkeernummers noteren en delen met thuisfront.
A54: BEGIN SEPT 2026 | B54: Offline voorbereiding | C54: Offline kaarten downloaden (Google Maps/Maps.me), belangrijke reserveringen en tickets offline opslaan.
A55: MID SEPT 2026 | B55: Huis & auto overdracht | C55: Laatste overdracht huis/auto aan oppas of familie; meterstanden en contactgegevens doorgeven.
A56: MID SEPT 2026 | B56: School & thuisfront informeren | C56: Definitieve vertrekdatum delen; laatste contactmoment met school/leerplicht en contactpersoon thuisfront.
A57: MID SEPT 2026 | B57: Laatste pakdag | C57: Definitief inpakken, laatste boodschappen, weging bagage en check van alle documenten.
A58: 19 SEPT 2026 | B58: VERTREK | C58: Vertrek naar Los Angeles / start wereldreis.

Sheet Noodnummers
A1: NOODNUMMERS WERELDREIS 2026–2027
A2: Bij direct levensgevaar: bel eerst het lokale alarmnummer. Bel daarna zo snel mogelijk Special ISIS; voor consulaire nood is Nederland Wereldwijd 24/7 bereikbaar.
A3: Land | B3: Algemeen alarm | C3: Politie | D3: Ambulance | E3: Brandweer | F3: Ambassade / consulaat | G3: Nederland Wereldwijd | H3: Ziekenhuis / medische hulp | I3: Special ISIS | J3: CZ Helpline | K3: Belangrijk
A4: Verenigde Staten | B4: 911 | C4: 911 | D4: 911 | E4: 911 | F4: Consulaat-generaal San Francisco +1 415 291 2033 | G4: +31 247 247 247 (24 uur per dag) | H4: Bij spoed: dichtstbijzijnde ER via 911. San Francisco: Zuckerberg SF General, 1001 Potrero Ave +1 628 206 8000 | I4: +1 800 694 9832 (gratis vanuit VS) Global: +31 182 544 555 | J4: +31 13 468 04 02 (24 uur per dag) | K4: Zorgkosten kunnen zeer hoog zijn. Bel Special ISIS bij opname, ongeval of repatriëring zo snel mogelijk.
A5: Fiji | B5: 911 | C5: 917 | D5: 911 | E5: 910 | F5: Geen Nederlandse ambassade in Fiji. Ambassade Wellington: +64 4 471 6390 | G5: +31 247 247 247 (24 uur per dag) | H5: Nadi Hospital: +679 670 1128 Lautoka Hospital: +679 666 0399 Op een eiland: waarschuw resort/bootoperator direct. | I5: +31 182 544 555 Goudse Alarmcentrale | J5: +31 13 468 04 02 (24 uur per dag) | K5: Ambulance- en evacuatiemogelijkheden zijn buiten de grote plaatsen en op eilanden beperkt. Geef eiland, resort en aanlegsteiger door.
A6: Australië | B6: 000 112 vanaf mobiel is alternatief | C6: 000 Niet-spoed: 131 444 | D6: 000 (spoed) | E6: 000 (spoed) | F6: Ambassade Canberra: +61 2 6220 9400 Consulaat Sydney: +61 2 8305 6800 | G6: +31 247 247 247 (24 uur per dag) | H6: Bij spoed: 000. Healthdirect verpleegkundige: 1800 022 222 (24/7) | I6: +31 182 544 555 Goudse Alarmcentrale | J6: +31 13 468 04 02 (24 uur per dag) | K6: Bel 000 alleen bij levensgevaar of tijdkritische situaties. Gebruik Healthdirect voor medische twijfel zonder acute nood.
A7: Nieuw-Zeeland | B7: 111 | C7: 111 Niet-spoed: 105 | D7: 111 | E7: 111 | F7: Ambassade Wellington +64 4 471 6390 | G7: +31 247 247 247 (24 uur per dag) | H7: Bij spoed: 111. Healthline: 0800 611 116 (24/7) | I7: +31 182 544 555 Goudse Alarmcentrale | J7: +31 13 468 04 02 (24 uur per dag) | K7: 111 is voor politie, brandweer en ambulance. Gebruik 105 alleen voor niet-dringende politiezaken.
A8: Singapore | B8: 999 politie 995 brandweer/ambulance | C8: 999 | D8: 995 | E8: 995 | F8: Ambassade Singapore +65 6737 1155 | G8: +31 247 247 247 (24 uur per dag) | H8: Kinderen: KKH Children's Emergency, 100 Bukit Timah Rd +65 6225 5554 Volwassenen: SGH Emergency, 1 Hospital Boulevard Niet-spoed: NurseFirst 6262 6262 | I8: +31 182 544 555 Goudse Alarmcentrale | J8: +31 13 468 04 02 (24 uur per dag) | K8: Gebruik tijdens jullie reis NurseFirst voor niet-levensbedreigende medische vragen.
A9: Thailand | B9: 191 algemeen/politie 1669 medisch | C9: 191 Toeristenpolitie: 1155 | D9: 1669 | E9: 199 | F9: Ambassade Bangkok +66 2 309 5200 | G9: +31 247 247 247 (24 uur per dag) | H9: Bangkok Hospital Phuket, Emergency & Trauma Center (24/7) +66 76 254 425 Elders: bel 1669 en waarschuw hotel/resort. | I9: +31 182 544 555 Goudse Alarmcentrale | J9: +31 13 468 04 02 (24 uur per dag) | K9: Toeristenpolitie 1155 biedt 24/7 hulp in meerdere talen. Bewaar de naam en het adres van de accommodatie ook in het Thais.
A10: Qatar | B10: 999 | C10: 999 | D10: 999 | E10: 999 | F10: Ambassade Doha +974 4495 4700 | G10: +31 247 247 247 (24 uur per dag) | H10: Hamad General Hospital, Adult Emergency (24/7) +974 4434 2421 / 2422 Kinderen t/m 14 jaar: Pediatric Emergency Center via 999. | I10: +31 182 544 555 Goudse Alarmcentrale | J10: +31 13 468 04 02 (24 uur per dag) | K10: 999 verbindt met politie, Civil Defence en ambulance. Kinderen t/m 14 jaar gaan naar een Pediatric Emergency Center.
A11: Tanzania | B11: 112 politie 115 ambulance | C11: 112 | D11: 115 | E11: 114 | F11: Ambassade Dar es Salaam +255 22 219 4000 | G11: +31 247 247 247 (24 uur per dag) | H11: Arusha Lutheran Medical Centre (24/7) Spoed: +255 766 909 113 Tijdens safari: informeer gids/lodge direct voor vervoer of evacuatie. | I11: +31 182 544 555 Goudse Alarmcentrale | J11: +31 13 468 04 02 (24 uur per dag) | K11: De bereikbaarheid en responstijd kunnen buiten steden beperkt zijn. Laat gids/lodge coördineren en bel de verzekeraar direct bij mogelijke evacuatie.
A23: Gecontroleerd op 12 augustus 2026 • Nummers kunnen wijzigen: controleer kort voor vertrek en bewaar dit bestand ook offline.

Sheet Paklijst
A2: DOCUMENTEN & ADMINISTRATIE
A3: Per persoon
A4: Paspoort
A5: Kopie paspoort (papier)
A6: Digitale kopie paspoort
A7: Reisverzekering
A8: Vliegtickets/e-tickets
A9: Zorgpas
A10: Bankpas
A11: Creditcard
A12: Gezamenlijk
A13: Rijbewijs
... A228: Reservekleding kinderen

Sheet Dagplanning - USA
A1: Datum | B1: Dag | C1: Route | D1: Beschrijving | E1: Afstand | F1: Reistijd | G1: informatie | H1: Google maps | I1: Kolom 1
A2: Datum | B2: Dag | C2: Route | D2: Beschrijving | E2: Afstand | F2: Reistijd | G2: informatie | H2: Google maps | I2: Komoot wandeling
A3: 46284 | B3: 1 | C3: ✈️ Aankomst San Francisco | D3: Aankomst, rustig bijkomen. Aankomst tijd 13:50 uur - Avondwandeling langs de baai. | H3: https://www.google.com/maps/dir/?api=1&origin=San%20Francisco%20International%20Airport%2C%20San%20Francisco%2C%20CA&destination=Holiday%20Inn%20San%20Francisco-Golden%20Gateway%2C%201500%20Van%20Ness%20Avenue%2C%20San%20Francisco%2C%20CA%2094109&waypoints=Holiday%20Inn%20San%20Francisco-Golden%20Gateway%2C%201500%20Van%20Ness%20Avenue%2C%20San%20Francisco%2C%20CA%2094109%7CFort%20Mason%20Great%20Meadow%2C%20Bay%20Street%2C%20San%20Francisco%2C%20CA%7CAquatic%20Park%20Cove%2C%20San%20Francisco%2C%20CA
A4: 46285 | B4: 2 | C4: San Francisco | D4: - 09:00 Cable car rit (Powell–Hyde) Powell Street → Fisherman's Wharf - 10:00 Pier 39 – zeeleeuwen Pier 39 Korte stop + wandelen - 11:30 Lunch Fisherman's Wharf Fisherman's Wharf Eerder lunchen voorkomt drukte - 13:00 Museum keuze (Exploratorium of California Academy of Sciences) - 15:30 Chinatown verkennen Chinatown (Grant Avenue) Kort + gericht - 17:30 Diner North Beach North Beach (Little Italy) Rustige afsluiter dag - 19:00 Einde dag / terug naar hotel Geen late avond i.v.m. jetlag | H4: https://www.google.com/maps/dir/?api=1&origin=Holiday%20Inn%20San%20Francisco-Golden%20Gateway%2C%201500%20Van%20Ness%20Avenue%2C%20San%20Francisco%2C%20CA%2094109&destination=Holiday%20Inn%20San%20Francisco-Golden%20Gateway%2C%201500%20Van%20Ness%20Avenue%2C%20San%20Francisco%2C%20CA%2094109&waypoints=Powell%20Street%20Cable%20Car%20Turnaround%2C%20Powell%20Street%20and%20Market%20Street%2C%20San%20Francisco%2C%20CA%7CHyde%20Street%20and%20Beach%20Street%2C%20San%20Francisco%2C%20CA%7CSea%20Lion%20Viewing%20Area%2C%20Pier%2039%2C%20San%20Francisco%2C%20CA%7CFisherman's%20Wharf%2C%20San%20Francisco%2C%20CA%7CExploratorium%2C%20Pier%2015%2C%20San%20Francisco%2C%20CA%2094111%7CDragon's%20Gate%2C%20Bush%20Street%20and%20Grant%20Avenue%2C%20San%20Francisco%2C%20CA%7CNorth%20Beach%2C%20San%20Francisco%2C%20CA&travelmode=transit
A5: 46286 | B5: 3 | C5: San Francisco | D5: - 09:00 Start fietstocht Golden Gate vanaf Fisherman's Wharf - 10:30 Golden Gate Bridge viewpoint Foto + korte pauze - 11:30 Aankomst Sausalito Sausalito wandelen + ijsje - 12:00 Lunch Sausalito Sausalito waterkant - 14:00 Ferry terug naar San Francisco Sausalito → Pier 41/39 niet te laat i.v.m. drukte - 15:30 Lombard Street Lombard Street 20–30 min stop - 16:30 Mission District of Golden Gate Par - 18:00 Twin Peaks (optioneel sunset) Uitsluitend bij helder weer - 19:30 Einde dag Avond vrij | G5: https://www.blazingsaddles.com/ https://bikeandview.com/bike-rental | H5: https://www.google.com/maps/dir/?api=1&origin=Holiday%20Inn%20San%20Francisco-Golden%20Gateway%2C%201500%20Van%20Ness%20Avenue%2C%20San%20Francisco%2C%20CA%2094109&destination=Holiday%20Inn%20San%20Francisco-Golden%20Gateway%2C%201500%20Van%20Ness%20Avenue%2C%20San%20Francisco%2C%20CA%2094109&waypoints=Fisherman's%20Wharf%2C%20San%20Francisco%2C%20CA%7CGolden%20Gate%20Bridge%20Welcome%20Center%2C%20San%20Francisco%2C%20CA%7CGolden%20Gate%20Bridge%20Vista%20Point%2C%20US-101%2C%20Sausalito%2C%20CA%2094965%7CSausalito%20Ferry%20Landing%2C%20Sausalito%2C%20CA%7CSan%20Francisco%20Ferry%20Building%2C%201%20Ferry%20Building%2C%20San%20Francisco%2C%20CA%7CFisherman's%20Wharf%2C%20San%20Francisco%2C%20CA%7CLombard%20Street%2C%20San%20Francisco%2C%20CA%7CGolden%20Gate%20Park%2C%20San%20Francisco%2C%20CA%7CTwin%20Peaks%2C%20San%20Francisco%2C%20CA&travelmode=bicycling
A6: 46287 | B6: 4 | C6: San Francisco → Monterey / Carmel | D6: - 09:00 Vertrek richting Monterey via Highway 1. - Optioneel stop: Santa Cruz Boardwalk of pier met zeeleeuwen. - 12:00 Aankomst Monterey – lunch. - 13:00 17-Mile Drive bij Carmel-by-the-Sea (tol ~$12). - 14:30 Point Lobos State Reserve – max 1,5 uur. Zeeotters bij Cypress Grove & China Cove. - 16:30 Carmel-by-the-Sea dorpje verkennen. | E6: 200 | F6: 2.3 | H6: https://www.google.com/maps/dir/?api=1&origin=433%20Powell%20Street%2C%20San%20Francisco%2C%20CA%2094102&destination=707%20Pacific%20Street%2C%20Monterey%2C%20CA%2093940&travelmode=driving&waypoints=Santa%20Cruz%20Wharf%2C%20Santa%20Cruz%2C%20CA%7COld%20Fisherman's%20Wharf%2C%20Monterey%2C%20CA%7CPacific%20Grove%20Gate%2C%2017%20Mile%20Drive%2C%20CA%7CSpanish%20Bay%2C%20Pebble%20Beach%2C%20CA%7CLone%20Cypress%2C%20Pebble%20Beach%2C%20CA%7CPoint%20Lobos%20State%20Natural%20Reserve%2C%20CA%7CCarmel-by-the-Sea%2C%20CA | I6: https://www.komoot.com/nl-nl/tour/2614904856 https://www.komoot.com/nl-nl/tour/2614897863
A7: 46288 | B7: 5 | C7: Monterey / Carmel → San Simeon (Big Sur route) | D7: - 10:00–13:00 Whale watch tour vanuit Monterey (boek vooraf!). - 14:00 Vertrek richting San Simeon via Highway 1. - Bixby Creek Bridge & Hurricane Point – fotostop. - Julia Pfeiffer Burns SP – McWay Falls viewpoint (iconische waterval, 15 min). - Pfeiffer Big Sur SP óf Andrew Molera – één korte wandeling (kies vooraf). - Elephant Seals bij Piedras Blancas – gratis, indrukwekkend! | E7: 240 | F7: 2.3 | H7: https://www.google.com/maps/dir/?api=1&origin=707%20Pacific%20Street%2C%20Monterey%2C%20CA%2093940&destination=9260%20Castillo%20Drive%2C%20San%20Simeon%2C%20CA%2093452&travelmode=driving&waypoints=Monterey%20Bay%20Whale%20Watch%2C%20Monterey%2C%20CA%7CBixby%20Creek%20Bridge%2C%20CA%7CHurricane%20Point%20View%2C%20CA%7CPfeiffer%20Big%20Sur%20State%20Park%2C%20CA%7CMcWay%20Falls%2C%20CA%7CPiedras%20Blancas%20Elephant%20Seal%20Rookery%2C%20CA | I7: https://www.komoot.com/nl-nl/tour/2702548958 https://www.komoot.com/nl-nl/tour/2614928316 https://www.komoot.com/nl-nl/tour/2614923839
A8: 46289 | B8: 6 | C8: San Simeon → Santa Barbara | D8: - 09:00 Vertrek richting Morro Bay. - Morro Bay & Morro Rock – korte stop, strandwandeling. - 11:30 Lunch aan zee in Morro Bay. - 13:00 Verder naar Santa Barbara. - Santa Barbara verkennen: State Street, pier en strandpromenade. - Optioneel: kijk of er een raketlancering is bij Vandenberg (check 24u van tevoren). | E8: 220 | F8: 2.15 | H8: https://www.google.com/maps/dir/?api=1&origin=9260%20Castillo%20Drive%2C%20San%20Simeon%2C%20CA%2093452&destination=180%20Avenue%20of%20Flags%2C%20Buellton%2C%20CA%2093427&travelmode=driving&waypoints=Morro%20Rock%2C%20Morro%20Bay%2C%20CA%7CState%20Street%2C%20Santa%20Barbara%2C%20CA%7CStearns%20Wharf%2C%20Santa%20Barbara%2C%20CA
A9: 46290 | B9: 7 | C9: Santa Barbara → Los Angeles | D9: - 09:30 Vertrek via Malibu – meerdere strandstops mogelijk. - El Matador Beach – wilde rotsachtige stranden, mooie foto's. - Zuma Beach – brede zandsstranden, goed voor kinderen. - 13:00 Lunch in Malibu. - 14:30 Aankomst Venice Beach. | E9: 165 | F9: 3 | H9: https://www.google.com/maps/dir/?api=1&origin=180%20Avenue%20of%20Flags%2C%20Buellton%2C%20CA%2093427&destination=14000%20Palawan%20Way%2C%20Marina%20del%20Rey%2C%20CA%2090292&travelmode=driving&waypoints=Zuma%20Beach%2C%20Malibu%2C%20CA%7CEl%20Matador%20State%20Beach%2C%20Malibu%2C%20CA%7CMalibu%20Pier%2C%20Malibu%2C%20CA%7CVenice%20Beach%2C%20Los%20Angeles%2C%20CA
A10: 46291 | B10: 8 | C10: Los Angeles | D10: Dag 1 – Hollywood & Griffith Park - 09:00 Hollywood Walk of Fame & TCL Chinese Theatre. - 10:30 Dolby Theatre (bekend van de Oscars). - 12:00 Lunch in Hollywood. - 13:30 Griffith Park – DASH bus of Uber (parkeren is drama). - 14:00 Griffith Observatory – uitzicht over de stad én Hollywood Sign. - 17:30 Zonsondergang bij het observatorium. - Optioneel: kleine hike richting Hollywood Sign | E10: 30 | F10: 0.3 | H10: https://www.google.com/maps/dir/?api=1&origin=14000%20Palawan%20Way%2C%20Marina%20del%20Rey%2C%20CA%2090292&destination=14000%20Palawan%20Way%2C%20Marina%20del%20Rey%2C%20CA%2090292&travelmode=driving&waypoints=Hollywood%20Walk%20of%20Fame%2C%20Los%20Angeles%2C%20CA%7CTCL%20Chinese%20Theatre%2C%20Los%20Angeles%2C%20CA%7CDolby%20Theatre%2C%20Los%20Angeles%2C%20CA%7CGriffith%20Observatory%2C%20Los%20Angeles%2C%20CA
A11: 46292 | B11: 9 | C11: Los Angeles | D11: Dag 2 – Stranden & relaxen - 09:00 Santa Monica Pier & Beach – iconisch, leuk met kinderen. - 10:30 Fietstocht Venice Beach → Santa Monica (huur e-bikes of fietsen). - 12:30 Lunch op de boulevard. - 14:00 Venice Canals – charmante wandeling langs bruggetjes en kanalen. - 16:00 Vrije tijd / zwemmen. - 18:30 Diner bij Third Street Promenade, Santa Monica. | H11: https://www.google.com/maps/dir/?api=1&origin=14000%20Palawan%20Way%2C%20Marina%20del%20Rey%2C%20CA%2090292&destination=14000%20Palawan%20Way%2C%20Marina%20del%20Rey%2C%20CA%2090292&travelmode=bicycling&waypoints=Santa%20Monica%20Pier%2C%20Santa%20Monica%2C%20CA%7CVenice%20Beach%20Skatepark%2C%20Los%20Angeles%2C%20CA%7CVenice%20Canals%2C%20Los%20Angeles%2C%20CA%7CThird%20Street%20Promenade%2C%20Santa%20Monica%2C%20CA
A12: 46293 | B12: 10 | C12: Los Angeles → Anaheim | D12: Dag 3 – Cultuur & Downtown LA - 09:30 The Broad Museum (gratis, reserveren!) of LACMA – kies één. - Walt Disney Concert Hall – architectonisch hoogtepunt, buiten bekijken. - El Pueblo de Los Angeles – historische wijk met Mexicaanse invloeden. - Lunch in Little Tokyo of Chinatown. - 14:30 Rijden naar Anaheim. | E12: 30 | F12: 1 | H12: https://www.google.com/maps/dir/?api=1&origin=14000%20Palawan%20Way%2C%20Marina%20del%20Rey%2C%20CA%2090292&destination=11767%20Harbor%20Boulevard%2C%20Garden%20Grove%2C%20CA%2092840&travelmode=driving&waypoints=The%20Broad%2C%20Los%20Angeles%2C%20CA%7CWalt%20Disney%20Concert%20Hall%2C%20Los%20Angeles%2C%20CA%7CEl%20Pueblo%20de%20Los%20Angeles%20Historical%20Monument%2C%20Los%20Angeles%2C%20CA%7CLittle%20Tokyo%2C%20Los%20Angeles%2C%20CA
A13: 46294 | B13: 11 | C13: Anaheim | D13: DISNEY | E13: - | F13: - | H13: https://www.google.com/maps/dir/?api=1&origin=11767%20Harbor%20Boulevard%2C%20Garden%20Grove%2C%20CA%2092840&destination=11767%20Harbor%20Boulevard%2C%20Garden%20Grove%2C%20CA%2092840&travelmode=driving&waypoints=Mickey%20and%20Friends%20Parking%20Structure%2C%20Anaheim%2C%20CA
A14: 46295 | B14: 12 | C14: Anaheim → Joshua Tree → Kingman | D14: - 07:30 Vroeg vertrek – lange dag! - 10:00 Joshua Tree National Park – Keys View (panoramisch uitzicht). - Korte hike: Skull Rock Nature Trail (2,7 km, kindvriendelijk). - 12:30 Picknick of lunch in/bij de park. | E14: 450 | F14: 5.3 | H14: https://www.google.com/maps/dir/?api=1&origin=11767%20Harbor%20Boulevard%2C%20Garden%20Grove%2C%20CA%2092840&destination=2815%20East%20Andy%20Devine%20Avenue%2C%20Kingman%2C%20AZ%2086401&travelmode=driving&waypoints=Joshua%20Tree%20National%20Park%20West%20Entrance%2C%20CA%7CKeys%20View%2C%20Joshua%20Tree%20National%20Park%2C%20CA%7CSkull%20Rock%2C%20Joshua%20Tree%20National%20Park%2C%20CA%7CJoshua%20Tree%20National%20Park%20North%20Entrance%2C%20CA | I14: https://www.komoot.com/nl-nl/tour/2614761117 https://www.komoot.com/nl-nl/tour/2702560442 https://www.komoot.com/nl-nl/tour/2614752433 https://www.komoot.com/nl-nl/tour/2687144756 https://www.komoot.com/nl-nl/tour/2687144846
A15: 46296 | B15: 13 | C15: Kingman → Grand Canyon | D15: - 09:00 Vertrek via Route 66. - Stop bij Seligman – historisch Route 66 stadje, Westside Lilo's Café. - 14:00 Aankomst Tusayan - 14:45 IMAX Grand Canyon Movie in Tusayan (goede introductie voor kinderen). - 16:00 Grand Canyon South Rim – Visitor Center & Mather Point. - 17:30 Hopi Point voor zonsondergang (shuttle Hermit Road) óf Yaki Point (eigen auto). - 18:13 Zonsondergang South Rim. - 19:00 Terug naar Tusayan voor diner. | E15: 230 | F15: 3.3 | H15: https://www.google.com/maps/dir/?api=1&origin=2815%20East%20Andy%20Devine%20Avenue%2C%20Kingman%2C%20AZ%2086401&destination=226%20Highway%2064%2C%20Tusayan%2C%20AZ%2086023&travelmode=driving&waypoints=Seligman%2C%20AZ%7CGrand%20Canyon%20IMAX%20Theater%2C%20Tusayan%2C%20AZ%7CGrand%20Canyon%20Visitor%20Center%2C%20AZ%7CMather%20Point%2C%20Grand%20Canyon%2C%20AZ%7CGrand%20Canyon%20Village%2C%20AZ
A16: 46297 | B16: 14 | C16: Grand Canyon → Kayenta | D16: - 09:00 Terug naar South Rim. - 09:30 Rim Trail – 5 km heen (evt bus terug), prachtige rand-wandeling. - 11:00 Scenic Drive richting Desert View: Grandview, Moran & Lipan Point. - 12:30 Navajo Point – picknick (neem eigen eten mee). - 14:30 Vertrek richting Kayenta. | E16: 200 | F16: 2.3 | H16: https://www.google.com/maps/dir/?api=1&origin=226%20Highway%2064%2C%20Tusayan%2C%20AZ%2086023&destination=Hampton%20Inn%20Kayenta%2C%20US%20Highway%20160%2C%20Kayenta%2C%20AZ%2086033&travelmode=driving&waypoints=Mather%20Point%2C%20Grand%20Canyon%2C%20AZ%7CBright%20Angel%20Trailhead%2C%20Grand%20Canyon%2C%20AZ%7CGrandview%20Point%2C%20Grand%20Canyon%2C%20AZ%7CMoran%20Point%2C%20Grand%20Canyon%2C%20AZ%7CLipan%20Point%2C%20Grand%20Canyon%2C%20AZ%7CNavajo%20Point%2C%20Grand%20Canyon%2C%20AZ%7CDesert%20View%20Watchtower%2C%20Grand%20Canyon%2C%20AZ | I16: https://www.komoot.com/nl-nl/tour/2614048812 https://www.komoot.com/nl-nl/tour/2614052612
A17: 46298 | B17: 15 | C17: Bluff (Monument Valley) | D17: - 08:00 vertrek naar Monument valley - 09:00 Wildcat Trail (6,4 km) – vroeg vanwege warmte, ook voor kinderen. - Navajo Tribal Park – uitzichtpunten langs de Valley Drive (eigen auto, ~30 km lus). - Lunch bij foodtruck of The View Restaurant. - Middag: richting Mexican Hat → Forest Gump Point (Highway 163, iconische foto!). - Goosenecks State Park – spectaculaire meanders van de San Juan River. | E17: 100 | F17: 1.3 | H17: https://www.google.com/maps/dir/?api=1&origin=Hampton%20Inn%20Kayenta%2C%20US%20Highway%20160%2C%20Kayenta%2C%20AZ%2086033&destination=The%20View%20Hotel%2C%20Monument%20Valley%20Tribal%20Park%2C%20AZ%2084536&travelmode=driving&waypoints=Wildcat%20Trailhead%2C%20Monument%20Valley%2C%20AZ%7CJohn%20Ford's%20Point%2C%20Monument%20Valley%2C%20AZ%7CForrest%20Gump%20Point%2C%20Mexican%20Hat%2C%20UT%7CMexican%20Hat%2C%20UT%7CGoosenecks%20State%20Park%2C%20UT | I17: https://www.komoot.com/nl-nl/tour/2614787726 https://www.komoot.com/nl-nl/tour/3015176711 https://www.komoot.com/nl-nl/tour/2614807185 https://www.komoot.com/nl-nl/tour/2614793120 https://www.komoot.com/nl-nl/tour/2614804991
A18: 46299 | B18: 16 | C18: Bluff (Monument Valley) → Page → Kanab | D18: - 09:10 Vertrek uiterlijk – Canyon-X tour (2u 20 rijden. - Canyon-X bezoek om 11:40. - Horseshoe Bend – 1,5 uur retour wandeling (let op: geen hekken, pas op met kinderen). - Lunch in Page. - 15:00 Rijden naar Kanab (~1-1,5 uur). | E18: 330 | F18: 3.5 | H18: https://www.google.com/maps/dir/?api=1&origin=The%20View%20Hotel%2C%20Monument%20Valley%20Tribal%20Park%2C%20AZ%2084536&destination=217%20South%20100%20East%2C%20Kanab%2C%20UT%2084741&travelmode=driving&waypoints=Antelope%20Canyon%20X%20by%20Taadidiin%20Tours%2C%20AZ%7CHorseshoe%20Bend%2C%20Page%2C%20AZ%7CPage%2C%20AZ
A19: 46300 | B19: 17 | C19: Kanab → Bryce Canyon NP | D19: - 09:00 Vertrek richting Bryce Canyon. - Navajo Loop Trail (2,4 km) – door hoodoos, kindvriendelijk maar steil omhoog. Combineer met Peek-a-Boo Loop = totaal ~8 km (voor fitte kinderen). - Lunch bij het park of Bryce Canyon City. - Bristlecone Loop Trail (2 km, mooie oude pijnbomen). - Bryce point naar Inspiration 2,7km of sunset point 3,7 km (rim trail shuttle bus nemen) - Zonsondergang bij Bryce Point. https://www.nps.gov/brca/planyourvisit/shuttle.htm | E19: 140 | F19: 2 | H19: https://www.google.com/maps/dir/?api=1&origin=217%20South%20100%20East%2C%20Kanab%2C%20UT%2084741&destination=Bryce%20Vistas%2C%20270%20East%201250%20North%2C%20Tropic%2C%20UT%2084776&travelmode=driving&waypoints=Sunset%20Point%2C%20Bryce%20Canyon%20National%20Park%2C%20UT%7CRainbow%20Point%2C%20Bryce%20Canyon%20National%20Park%2C%20UT%7CInspiration%20Point%2C%20Bryce%20Canyon%20National%20Park%2C%20UT%7CBryce%20Point%2C%20Bryce%20Canyon%20National%20Park%2C%20UT | I19: https://www.komoot.com/nl-nl/tour/2688381072 https://www.komoot.com/nl-nl/tour/2688359078 https://www.komoot.com/nl-nl/tour/2688333419 https://www.komoot.com/nl-nl/tour/2688333470 https://www.komoot.com/nl-nl/tour/2688334893 https://www.komoot.com/nl-nl/tour/2688356249 https://www.komoot.com/nl-nl/tour/3018387564 https://www.komoot.com/nl-nl/tour/2688338966 https://www.komoot.com/nl-nl/tour/2688394606
A20: 46301 | B20: 18 | C20: Bryce Canyon → Zion NP | D20: - 08:00 Ochtendwandeling nog in Bryce (golden hour 07:00 -08:30). - 10:00 Vertrek via Red Canyon richting Zion. - Evt. lunch bij Archie's Food to Die For (GF-opties) onderweg. - Aankomst Zion – Canyon Overlook Trail (parkeer eerste vrije plek DRUK!!). - Watchman Trail als Canyon Overlook te druk is (3,3 km, mooi uitzicht). - Inchecken The Riv at Zion, Virgin (239 UT-9). - Zwemmen bij accommodatie. | E20: 140 | F20: 2 | H20: https://www.google.com/maps/dir/?api=1&origin=Bryce%20Vistas%2C%20270%20East%201250%20North%2C%20Tropic%2C%20UT%2084776&destination=865%20Zion%20Park%20Boulevard%2C%20Springdale%2C%20UT%2084767&travelmode=driving&waypoints=Sunrise%20Point%2C%20Bryce%20Canyon%20National%20Park%2C%20UT%7CRed%20Canyon%20Visitor%20Center%2C%20UT%7CArchie's%20Food%20to%20Die%20For%2C%20Orderville%2C%20UT%7CCanyon%20Overlook%20Trailhead%2C%20Zion%20National%20Park%2C%20UT | I20: https://www.komoot.com/nl-nl/tour/2614846720 https://www.komoot.com/nl-nl/tour/3018369235
A21: 46302 | B21: 19 | C21: Zion NP | D21: - 07:30 Canyon Overlook Trail vroeg in de ochtend (als vorige dag te druk). - 09:30 Shuttle naar Temple of Sinawava. - Riverside Walk (3,2 km, kindvriendelijk, verhard pad). - The Narrows – gedeeltelijk, tot waar het kindvriendelijk is (waterschoenen mee!). - Middag: terug naar appartement, zwemmen en rusten. - Avond: Watchman Trail (evt Bas alleen of rustige gezinsversie). | H21: https://www.google.com/maps/dir/?api=1&origin=865%20Zion%20Park%20Boulevard%2C%20Springdale%2C%20UT%2084767&destination=865%20Zion%20Park%20Boulevard%2C%20Springdale%2C%20UT%2084767&travelmode=driving&waypoints=Canyon%20Overlook%20Trailhead%2C%20Zion%20National%20Park%2C%20UT%7CZion%20Canyon%20Visitor%20Center%2C%20Springdale%2C%20UT | I21: https://www.komoot.com/nl-nl/tour/2614840133 https://www.komoot.com/nl-nl/tour/3018288639 https://www.komoot.com/nl-nl/tour/3018332060 https://www.komoot.com/nl-nl/tour/2614829414 https://www.komoot.com/nl-nl/tour/2614850170 https://www.komoot.com/nl-nl/tour/3018344170
A22: 46303 | B22: 20 | C22: Zion NP | D22: - 06:30–10:00 Angels Landing (Bas alleen). - Ochtend gezin: rustig ontbijt, spelen bij accommodatie. - 10:30 Gezamenlijk: Emerald Pools Trail – Lower & Middle pools (4 km, kindvriendelijk). - Lunch in Springdale. - Middag: vrije tijd, zwemmen of Pa'rus Trail (fietsvriendelijk, langs de rivier). | H22: https://www.google.com/maps/dir/?api=1&origin=865%20Zion%20Park%20Boulevard%2C%20Springdale%2C%20UT%2084767&destination=865%20Zion%20Park%20Boulevard%2C%20Springdale%2C%20UT%2084767&travelmode=driving&waypoints=Zion%20Canyon%20Visitor%20Center%2C%20Springdale%2C%20UT | I22: https://www.komoot.com/nl-nl/tour/2614843688 https://www.komoot.com/nl-nl/tour/3018343849 https://www.komoot.com/nl-nl/tour/3018344770 https://www.komoot.com/nl-nl/tour/3018411685 https://www.komoot.com/nl-nl/tour/3031401825 https://www.komoot.com/nl-nl/tour/3018340557
A23: 46304 | B23: 21 | C23: Zion NP → Las Vegas | D23: - 08:00 Vertrek richting Valley of Fire State Park (aanrader!). 2 u 15 rijden - Valley of Fire: Mouse's Tank Road → White Domes Trail (2,2 km, indrukwekkend rood landschap). - Rainbow Vista als extra stop. - Lunch onderweg. - Aankomst Las Vegas in de middag (rit totaal ~4 uur + 1 uur wandelen). - Avond: eerste verkenning van de Strip. | E23: 280 | F23: 3.45 | H23: https://www.google.com/maps/dir/?api=1&origin=865%20Zion%20Park%20Boulevard%2C%20Springdale%2C%20UT%2084767&destination=125%20East%20Harmon%20Avenue%2C%20Las%20Vegas%2C%20NV%2089109&travelmode=driving&waypoints=Valley%20of%20Fire%20East%20Entrance%2C%20NV%7CRainbow%20Vista%2C%20Valley%20of%20Fire%2C%20NV%7CMouse's%20Tank%20Trailhead%2C%20Valley%20of%20Fire%2C%20NV%7CWhite%20Domes%20Trailhead%2C%20Valley%20of%20Fire%2C%20NV%7CValley%20of%20Fire%20West%20Entrance%2C%20NV | I23: https://www.komoot.com/nl-nl/tour/2687154335 https://www.komoot.com/nl-nl/tour/3020471843
A24: 46305 | B24: 22 | C24: Las Vegas | D24: - Rustige ochtend bij het zwembad. - 11:00 Bezoek The Venetian of Caesars Palace (gratis te betreden, indrukwekkend). - 13:00 Lunch op de Strip of in een foodcourt (goedkoper). - Middag met kinderen: Springs Preserve of Discovery Children's Museum. - 18:00 Fremont Street Experience – lichtshow & straatentertainment (niet te laat ivm drukte etc) - Gratis tips: https://www.visitlasvegas.com/experience/post/free-things-to-do-in-las-vegas/ | E24: - | F24: - | G24: Activiteit Las Vegas Tournament of Kings AREA15 Pinball Hall of Fame The Neon Museum Bellagio Fountains Flyover Las Vegas Downtown Container Park Flamingo Wildlife Habitat Bellagio Conservatory & Botanical Gardens | H24: https://www.google.com/maps/dir/?api=1&origin=125%20East%20Harmon%20Avenue%2C%20Las%20Vegas%2C%20NV%2089109&destination=125%20East%20Harmon%20Avenue%2C%20Las%20Vegas%2C%20NV%2089109&travelmode=driving&waypoints=The%20Venetian%20Las%20Vegas%2C%20NV%7CCaesars%20Palace%2C%20Las%20Vegas%2C%20NV%7CSprings%20Preserve%2C%20Las%20Vegas%2C%20NV%7CFremont%20Street%20Experience%2C%20Las%20Vegas%2C%20NV
A25: 46306 | B25: 23 | C25: Las Vegas → Mammoth Lakes | D25: ( Let op Tanken weinig benzine stations) 09:00 Vertrek Las Vegas * 11:00 Dante’s View (20-30 min) * 12:00 Zabriskie Point (15-20 min) * 12:30 Lunch bij Furnace Creek * 13:45 Badwater Basin (20-30 min) * 14:30 Artist’s Drive (30-45 min) * 15:45 Mesquite Flat Sand Dunes (20-30 min) * 16:15 Vertrek richting Mammoth Lakes * 18:30 Aankomst Mammoth Lakes - Neem veel water mee – ook in oktober kan het 30°C+ zijn. - Lunch onderweg (neem picknick mee, geen goed eten onderweg). | E25: 530 | F25: 6 | H25: https://www.google.com/maps/dir/?api=1&origin=125%20East%20Harmon%20Avenue%2C%20Las%20Vegas%2C%20NV%2089109&destination=4000%20Meridian%20Boulevard%2C%20Mammoth%20Lakes%2C%20CA%2093546&travelmode=driving&waypoints=Dante's%20View%2C%20Death%20Valley%20National%20Park%2C%20CA%7CZabriskie%20Point%2C%20Death%20Valley%20National%20Park%2C%20CA%7CFurnace%20Creek%2C%20Death%20Valley%20National%20Park%2C%20CA%7CBadwater%20Basin%2C%20Death%20Valley%20National%20Park%2C%20CA%7CArtists%20Palette%2C%20Death%20Valley%20National%20Park%2C%20CA%7CMesquite%20Flat%20Sand%20Dunes%2C%20Death%20Valley%20National%20Park%2C%20CA
A26: 46307 | B26: 24 | C26: Mammoth Lakes | D26: - 09:00 Convict Lake – korte wandeling langs het meer (3,2 km lus, prachtig). - 11:00 Lake George of Twin Lakes – rustige picknickplek. - 13:00 Lunch in Mammoth Lakes. even rusten en zwemmen evt - 16:30 Mono Lake als we zin hebben (South Tufa Area), korte wandeling (~1 km). - Optioneel avond: Devil's Postpile National Monument (als nog open in okt). | E26: - | F26: - | H26: https://www.google.com/maps/dir/?api=1&origin=4000%20Meridian%20Boulevard%2C%20Mammoth%20Lakes%2C%20CA%2093546&destination=4000%20Meridian%20Boulevard%2C%20Mammoth%20Lakes%2C%20CA%2093546&travelmode=driving&waypoints=Convict%20Lake%2C%20CA%7CLake%20George%2C%20Mammoth%20Lakes%2C%20CA%7CTwin%20Lakes%2C%20Mammoth%20Lakes%2C%20CA%7C4000%20Meridian%20Boulevard%2C%20Mammoth%20Lakes%2C%20CA%2093546%7CMono%20Lake%20South%20Tufa%20Area%2C%20CA | I26: https://www.komoot.com/nl-nl/tour/3020649321 https://www.komoot.com/nl-nl/tour/2614869950 https://www.komoot.com/nl-nl/tour/3020626720 https://www.komoot.com/nl-nl/tour/3020610105 https://www.komoot.com/nl-nl/tour/3020605210 https://www.komoot.com/nl-nl/tour/2614876475
A27: 46308 | B27: 25 | C27: Mammoth Lakes → Yosemite NP | D27: 08:00 Vertrek Mammoth Lakes via Tioga Pass Tuolumne Meadows – korte stop (20–30 min) Tenaya Lake – korte stop (15–20 min) Olmsted Point – uitzichtstop (20 min) Lunch onderweg 15:30 Tunnel View – eerste WOW-uitzicht 16:00 Glacier Point Glacier Point 18:15 Zonsondergang Glacier Point 19:30 Aankomst Yosemite View Lodge | E27: 170 | F27: 3.3 | H27: https://www.google.com/maps/dir/?api=1&origin=4000%20Meridian%20Boulevard%2C%20Mammoth%20Lakes%2C%20CA%2093546&destination=11136%20Highway%20140%2C%20El%20Portal%2C%20CA%2095318&travelmode=driving&waypoints=Tuolumne%20Meadows%2C%20Yosemite%20National%20Park%2C%20CA%7CTenaya%20Lake%2C%20Yosemite%20National%20Park%2C%20CA%7COlmsted%20Point%2C%20Yosemite%20National%20Park%2C%20CA%7CTunnel%20View%2C%20Yosemite%20National%20Park%2C%20CA%7CGlacier%20Point%2C%20Yosemite%20National%20Park%2C%20CA | I27: https://www.komoot.com/nl-nl/tour/3020763322
A28: 46309 | B28: 26 | C28: Yosemite NP | D28: 07:30 Vertrek naar Yosemite Valley 08:30 – 10:30 Mist Trail tot Vernal Fall Bridge Vernal Fall 10:45 Bridalveil Fall (10–15 min stop) 11:00 Lunch in de Valley 12:00 Sentinel Beach – relaxen / spelen 13:00 Lower Yosemite Fall + Cook’s Meadow 15:00 El Capitan Meadow 16:00 Valley View 17:00 Terug naar Yosemite View Lodge | E28: - | F28: - | H28: https://www.google.com/maps/dir/?api=1&origin=11136%20Highway%20140%2C%20El%20Portal%2C%20CA%2095318&destination=11136%20Highway%20140%2C%20El%20Portal%2C%20CA%2095318&travelmode=driving&waypoints=Curry%20Village%20Parking%2C%20Yosemite%20National%20Park%2C%20CA%7CBridalveil%20Fall%20Parking%2C%20Yosemite%20National%20Park%2C%20CA%7CSentinel%20Beach%20Picnic%20Area%2C%20Yosemite%20National%20Park%2C%20CA%7CYosemite%20Village%20Parking%2C%20Yosemite%20National%20Park%2C%20CA%7CEl%20Capitan%20Meadow%2C%20Yosemite%20National%20Park%2C%20CA%7CValley%20View%2C%20Yosemite%20National%20Park%2C%20CA | I28: https://www.komoot.com/nl-nl/tour/2614894382 https://www.komoot.com/nl-nl/tour/2614886321 https://www.komoot.com/nl-nl/tour/2614885563 https://www.komoot.com/nl-nl/tour/2614891266 https://www.komoot.com/nl-nl/tour/2614891971 https://www.komoot.com/nl-nl/tour/2614882594 https://www.komoot.com/nl-nl/tour/3021993273
A29: 46310 | B29: 27 | C29: Yosemite NP → San Francisco | D29: - 09:00 - 10:00 Zwemmen - 10:15 Vertrek richting San Francisco. - Stop bij Merced Grove of Tuolumne Grove – giant sequoia's (korte wandeling, indrukwekkend!). - 13:00 Lunch onderweg. - Cultured Pickle Shop ??? net voor SF - 16:00–16:30 Aankomst San Francisco. | E29: 310 | F29: 4.15 | H29: https://www.google.com/maps/dir/?api=1&origin=11136%20Highway%20140%2C%20El%20Portal%2C%20CA%2095318&destination=1630%20Pacific%20Avenue%2C%20San%20Francisco%2C%20CA%2094109&travelmode=driving&waypoints=Merced%20Grove%20Trailhead%2C%20Yosemite%20National%20Park%2C%20CA%7CThe%20Cultured%20Pickle%20Shop%2C%20800%20Bancroft%20Way%2C%20Berkeley%2C%20CA | I29: https://www.komoot.com/nl-nl/tour/3020842159
A30: 46311 | B30: 28 | C30: San Francisco ✈️ Vertrek | D30: Laat vertrek (22:55), overdag tijd voor laatste wandeling of shoppen. | E30: - | F30: -

Sheet Dagplanning - Fiji
A1: Datum | B1: Dag | C1: Route | D1: Beschrijving | E1: Afstand | F1: Reistijd | G1: informatie
A2: 46312 | C2: Door vlucht dag verschil
A3: 46313 | B3: Dag 1 | C3: ✈️ Aankomst Nadi | D3: Transfer naar Plantation Resort om 08:00 | F3: 1u | G3: Vertrek 8:00:00 Aaankomst 08:50
A4: 46314 | B4: Dag 2 | C4: Plantation Resort | D4: Plantation Resort
A5: 46315 | B5: Dag 3 | C5: Plantation Resort → Port Denarau | D5: vertek 15:45 | F5: 1u
A6: 46316 | B6: Dag 4 | C6: Port Denarau | D6: Eco trax
A7: 46317 | B7: Dag 5 | C7: Port Denarau → Kuata Island | D7: Vertrek 08:45 ferry Yasawa Flyer vanuit Port Denarau → 10:30 | F7: 1u45
A8: 46318 | B8: Dag 6 | C8: Kuata Island | D8: Excursies: snorkelen met rifhaaien (optioneel), kajakken, wandelen naar viewpoints. | G8: Vertrek 8:45:00 Aankomst 18:00
A9: 46319 | B9: Dag 7 | C9: Kuata Island | D9: snorkelen, kajakken, wandelen naar viewpoints.
A10: 46320 | B10: Dag 8 | C10: Kuata Island | D10: 14:50 ferry vertrek → 17:35 aankomst Port Denarau. Taxi naar airport hotel | F10: 1u45
A11: 46321 | B11: Dag 9 | C11: ✈️ Vertrek Nadi → Brisbane | D11: Vlucht naar Brisbane. om 08:20

Sheet Dagplanning - Brisbane EO
A1: Datum | B1: Dag | C1: Route | D1: Beschrijving | E1: Afstand | F1: Reistijd | G1: informatie | H1: Google maps | I1: Komoot wandeling
A2: 46321 | B2: 1 | C2: Brisbane | D2: Dag 1 – Aankomst Brisbane Rustige wandeling langs Brisbane River of South Bank | E2: - | F2: - | G2: Rustige start i.v.m. jetlag | H2: https://www.google.com/maps/dir/?api=1&origin=1%20Cordelia%20Street%2C%20South%20Brisbane%20QLD%204101%2C%20Australia&destination=1%20Cordelia%20Street%2C%20South%20Brisbane%20QLD%204101%2C%20Australia&travelmode=walking&waypoints=South%20Bank%20Parklands%2C%20Brisbane%20QLD%2C%20Australia%7CClem%20Jones%20Promenade%2C%20South%20Brisbane%20QLD%2C%20Australia
A3: 46322 | B3: 2 | C3: Brisbane | D3: Dag 2 – Brisbane stad & South Bank; - South Bank Parklands - Streets Beach - GOMA / QAG (kindvriendelijk) | E3: - | F3: - | G3: Zwemkleding mee | H3: https://www.google.com/maps/dir/?api=1&origin=1%20Cordelia%20Street%2C%20South%20Brisbane%20QLD%204101%2C%20Australia&destination=1%20Cordelia%20Street%2C%20South%20Brisbane%20QLD%204101%2C%20Australia&travelmode=walking&waypoints=South%20Bank%20Parklands%2C%20Brisbane%20QLD%2C%20Australia%7CStreets%20Beach%2C%20South%20Brisbane%20QLD%2C%20Australia%7CQueensland%20Art%20Gallery%20and%20Gallery%20of%20Modern%20Art%2C%20South%20Brisbane%20QLD%2C%20Australia
A4: 46323 | B4: 3 | C4: Brisbane | D4: Dag 3 – Wildlife & uitzicht - Lone Pine Koala Sanctuary, Kangoeroes voeren - Mt Coot-tha Lookout - Optioneel planetarium | E4: 30 | F4: 0.45 | G4: Grote hit bij kinderen | H4: https://www.google.com/maps/dir/?api=1&origin=1%20Cordelia%20Street%2C%20South%20Brisbane%20QLD%204101%2C%20Australia&destination=1%20Cordelia%20Street%2C%20South%20Brisbane%20QLD%204101%2C%20Australia&travelmode=driving&waypoints=Lone%20Pine%20Koala%20Sanctuary%2C%20Fig%20Tree%20Pocket%20QLD%2C%20Australia%7CMount%20Coot-tha%20Summit%20Lookout%2C%20Mount%20Coot-tha%20QLD%2C%20Australia%7CSir%20Thomas%20Brisbane%20Planetarium%2C%20Mount%20Coot-tha%20QLD%2C%20Australia
A5: 46324 | B5: 4 | C5: Byron bay | D5: Dag 4 – Brisbane → Byron bay - Strand Burleigh Heads - Korte kustwandeling | E5: 150 | F5: 2 | G5: Burleigh rustiger dan Surfers Paradise | H5: https://www.google.com/maps/dir/?api=1&origin=1%20Cordelia%20Street%2C%20South%20Brisbane%20QLD%204101%2C%20Australia&destination=1%20Bundaleer%20Road%2C%20Broken%20Head%20NSW%202481%2C%20Australia&travelmode=driving&waypoints=Burleigh%20Heads%20Beach%2C%20Burleigh%20Heads%20QLD%2C%20Australia%7CBurleigh%20Head%20National%20Park%2C%20Burleigh%20Heads%20QLD%2C%20Australia
A6: 46325 | B6: 5 | C6: Byron bay | D6: Dag 5 – Byron bay - Strand - Mullumbimby ?? | E6: 0 | F6: 0 | G6: Educatief & actief | H6: https://www.google.com/maps/dir/?api=1&origin=1%20Bundaleer%20Road%2C%20Broken%20Head%20NSW%202481%2C%20Australia&destination=1%20Bundaleer%20Road%2C%20Broken%20Head%20NSW%202481%2C%20Australia&travelmode=driving&waypoints=Main%20Beach%2C%20Byron%20Bay%20NSW%2C%20Australia%7CMullumbimby%20NSW%2C%20Australia | I6: https://www.komoot.com/nl-nl/tour/2798963717
A7: 46326 | B7: 6 | C7: Byron bay | D7: Dag 6 – Byron bay | E7: 0 | F7: 0 | H7: https://www.google.com/maps/dir/?api=1&origin=1%20Bundaleer%20Road%2C%20Broken%20Head%20NSW%202481%2C%20Australia&destination=1%20Bundaleer%20Road%2C%20Broken%20Head%20NSW%202481%2C%20Australia&travelmode=driving&waypoints=Byron%20Bay%20NSW%2C%20Australia
A8: 46327 | B8: 7 | C8: Lamington | D8: Dag 7 – Byron bay → Springbrook National Park - Natural Bridge (glow worms) - Purling Brook Falls - Regenwoudwandelingen | E8: 100 | F8: 2 | G8: Goede schoenen meenemen | H8: https://www.google.com/maps/dir/?api=1&origin=1%20Bundaleer%20Road%2C%20Broken%20Head%20NSW%202481%2C%20Australia&destination=8%20Canyon%20Parade%2C%20Springbrook%20QLD%204213%2C%20Australia&travelmode=driving&waypoints=Natural%20Bridge%2C%20Springbrook%20National%20Park%20QLD%2C%20Australia%7CPurling%20Brook%20Falls%2C%20Springbrook%20QLD%2C%20Australia
A9: 46328 | B9: 8 | C9: Rainbow beach | D9: Dag 8 – Lamington NT → Tin Can Bay of Rainbow beach - Rit van 4 uur | E9: 350 | F9: 4 | H9: https://www.google.com/maps/dir/?api=1&origin=8%20Canyon%20Parade%2C%20Springbrook%20QLD%204213%2C%20Australia&destination=48%2F5%20Rainbow%20Shores%20Drive%2C%20Rainbow%20Beach%20QLD%204581%2C%20Australia&travelmode=driving
A10: 46329 | B10: 9 | C10: Rainbow beach | D10: Dag 9 – Rainbowbeach - Tin can bay (dofijnen voeren) om 07:00 aanwezig zijn - Strand of excursie | E10: 110 | F10: 1.3 | G10: Niet hele walk lopen met kinderen | H10: https://www.google.com/maps/dir/?api=1&origin=48%2F5%20Rainbow%20Shores%20Drive%2C%20Rainbow%20Beach%20QLD%204581%2C%20Australia&destination=48%2F5%20Rainbow%20Shores%20Drive%2C%20Rainbow%20Beach%20QLD%204581%2C%20Australia&travelmode=driving&waypoints=Barnacles%20Dolphin%20Centre%2C%20Tin%20Can%20Bay%20QLD%2C%20Australia%7CRainbow%20Beach%20QLD%2C%20Australia
A11: 46330 | B11: 10 | C11: Noosa | D11: Dag 10 – Noosa - Strand Main Beach of Little Cove | E11: 0 | F11: 0 | G11: Vooraf boeken | H11: https://www.google.com/maps/dir/?api=1&origin=48%2F5%20Rainbow%20Shores%20Drive%2C%20Rainbow%20Beach%20QLD%204581%2C%20Australia&destination=19%20Katharina%20Street%2C%20Noosa%20Heads%20QLD%204567%2C%20Australia&travelmode=driving&waypoints=Noosa%20Main%20Beach%2C%20Noosa%20Heads%20QLD%2C%20Australia
A12: 46331 | B12: 11 | C12: Noosa | D12: Dag 11 – Noosa Everglades - Boottocht of kajak | E12: 0 | F12: 0 | H12: https://www.google.com/maps/dir/?api=1&origin=19%20Katharina%20Street%2C%20Noosa%20Heads%20QLD%204567%2C%20Australia&destination=19%20Katharina%20Street%2C%20Noosa%20Heads%20QLD%204567%2C%20Australia&travelmode=driving&waypoints=Habitat%20Noosa%20Everglades%20Eco%20Camp%2C%20Cootharaba%20QLD%2C%20Australia
A13: 46332 | B13: 12 | C13: Noosa | D13: Dag 12 – Noosa National Park & strand - Coastal Walk (gedeeltelijk), Kans op dolfijnen & koala’s | E13: 0 | F13: 0 | H13: https://www.google.com/maps/dir/?api=1&origin=19%20Katharina%20Street%2C%20Noosa%20Heads%20QLD%204567%2C%20Australia&destination=19%20Katharina%20Street%2C%20Noosa%20Heads%20QLD%204567%2C%20Australia&travelmode=walking&waypoints=Noosa%20National%20Park%20Carpark%2C%20Noosa%20Heads%20QLD%2C%20Australia%7CDolphin%20Point%20Lookout%2C%20Noosa%20Heads%20QLD%2C%20Australia%7CLittle%20Cove%20Beach%2C%20Noosa%20Heads%20QLD%2C%20Australia
A14: 46333 | B14: 13 | C14: Maleny / Montville | D14: Dag 13 – Noosa → Sunshine coast Hinterland - Rit naar Maleny / Beerwa - Montville dorpje & uitzicht - Glass House Mountains (wandeling met uitzicht) | E14: 80 | F14: 1 | G14: Australia Zoo = hele dag | H14: https://www.google.com/maps/dir/?api=1&origin=19%20Katharina%20Street%2C%20Noosa%20Heads%20QLD%204567%2C%20Australia&destination=123%20Old%20Peachester%20Road%2C%20Beerwah%20QLD%2C%20Australia&travelmode=driving&waypoints=Montville%20QLD%2C%20Australia%7CMaleny%20QLD%2C%20Australia%7CGlass%20House%20Mountains%20Lookout%2C%20Glass%20House%20Mountains%20QLD%2C%20Australia
A15: 46334 | B15: 14 | C15: Brisbane | D15: Dag 14 – Vertrek naar Cairns - Auto inleveren - Vlucht verder | E15: 100 | F15: 1.2 | G15: Laatste souvenirs | H15: https://www.google.com/maps/dir/?api=1&origin=123%20Old%20Peachester%20Road%2C%20Beerwah%20QLD%2C%20Australia&destination=Brisbane%20Airport%20Car%20Rental%20Returns%2C%20Brisbane%20Airport%20QLD%204008%2C%20Australia&travelmode=driving

Sheet Dagplanning - FNQ
A1: Datum | B1: Dag | C1: Route | D1: Beschrijving | E1: Afstand | F1: Reistijd | G1: informatie | H1: Google Maps-link | I1: Komoot wandeling
A2: 46334 | B2: 1 | C2: Port Douglas | D2: Dag 1 – Vlucht Brisbane - Cairns Aankomst Port Douglas - Wandeling langs Four Mile Beach - Diner in het centrum van Port Douglas | E2: - | F2: - | G2: Relaxen na aankomst | H2: https://www.google.com/maps/dir/?api=1&origin=19-37%20Saint%20Crispins%20Avenue%2C%20Port%20Douglas%20QLD%204877%2C%20Australia&destination=19-37%20Saint%20Crispins%20Avenue%2C%20Port%20Douglas%20QLD%204877%2C%20Australia&travelmode=driving&waypoints=Four%20Mile%20Beach%2C%20Port%20Douglas%20QLD%2C%20Australia%7CMacrossan%20Street%2C%20Port%20Douglas%20QLD%2C%20Australia
A3: 46335 | B3: 2 | C3: Port Douglas | D3: Dag 2 – Mossman Gorge & Silky Oaks Lodge - Ochtend: bezoek aan Mossman Gorge – korte wandelingen, zwemmen in de rivier - Lunch bij Silky Oaks Lodge (prachtig gelegen in de jungle) - Middag: vrije tijd bij het zwembad of op het strand | E3: 20 km | F3: 25 min | G3: Shuttle Mossman Gorge reserveren | H3: https://www.google.com/maps/dir/?api=1&origin=19-37%20Saint%20Crispins%20Avenue%2C%20Port%20Douglas%20QLD%204877%2C%20Australia&destination=19-37%20Saint%20Crispins%20Avenue%2C%20Port%20Douglas%20QLD%204877%2C%20Australia&travelmode=driving&waypoints=Mossman%20Gorge%20Cultural%20Centre%2C%20Mossman%20Gorge%20QLD%2C%20Australia%7CSilky%20Oaks%20Lodge%2C%20Finlayvale%20Road%2C%20Mossman%20QLD%2C%20Australia
A4: 46336 | B4: 3 | C4: Port Douglas | D4: Dag 3 – Cape Tribulation & Daintree - Vroege rit richting Daintree National Park (veerboot over de Daintree River) - Bezoek aan Daintree Discovery Centre (skywalk door het regenwoud) - Rit naar Cape Tribulation: strandwandeling, uitzichtpunt bij Kulki Lookout | E4: 85 km | F4: 1u50 | H4: https://www.google.com/maps/dir/?api=1&origin=19-37%20Saint%20Crispins%20Avenue%2C%20Port%20Douglas%20QLD%204877%2C%20Australia&destination=19-37%20Saint%20Crispins%20Avenue%2C%20Port%20Douglas%20QLD%204877%2C%20Australia&travelmode=driving&waypoints=Daintree%20Ferry%2C%20Cape%20Tribulation%20Road%2C%20Lower%20Daintree%20QLD%2C%20Australia%7CDaintree%20Rainforest%20Discovery%20Centre%2C%20Cow%20Bay%20QLD%2C%20Australia%7CKulki%20Lookout%2C%20Cape%20Tribulation%20QLD%2C%20Australia%7CCape%20Tribulation%20Beach%2C%20QLD%2C%20Australia
A5: 46337 | B5: 4 | C5: Port Douglas | D5: Dag 4 – Low Isles snorkeltour - Ochtend: halve dag snorkeltour naar de Low Isles (zeeschildpadden, koraal, vissen) - Middag: ontspanning in Port Douglas - WAGS bij de jachthaven 15:30 aanwezig!! (leuke ervaring en lekker eten) | G5: https://pdyc.org/sailing-port-douglas/ | H5: https://www.google.com/maps/dir/?api=1&origin=19-37%20Saint%20Crispins%20Avenue%2C%20Port%20Douglas%20QLD%204877%2C%20Australia&destination=19-37%20Saint%20Crispins%20Avenue%2C%20Port%20Douglas%20QLD%204877%2C%20Australia&travelmode=driving&waypoints=Crystalbrook%20Superyacht%20Marina%2C%20Wharf%20Street%2C%20Port%20Douglas%20QLD%2C%20Australia%7CPort%20Douglas%20Yacht%20Club%2C%201%20Spinnaker%20Close%2C%20Port%20Douglas%20QLD%2C%20Australia
A6: 46338 | B6: 5 | C6: Port Douglas | D6: Dag 5 – Wildlife Sanctuary & stranddag - Bezoek aan het Rainforest Habitat Wildlife Sanctuary - Middag: relaxen aan Four Mile Beach of vrije tijd bij het resort - Avondwandeling langs de boulevard en diner in Port Douglas | H6: https://www.google.com/maps/dir/?api=1&origin=19-37%20Saint%20Crispins%20Avenue%2C%20Port%20Douglas%20QLD%204877%2C%20Australia&destination=19-37%20Saint%20Crispins%20Avenue%2C%20Port%20Douglas%20QLD%204877%2C%20Australia&travelmode=driving&waypoints=Wildlife%20Habitat%20Port%20Douglas%2C%201%20Port%20Douglas%20Road%2C%20Port%20Douglas%20QLD%2C%20Australia%7CFour%20Mile%20Beach%2C%20Port%20Douglas%20QLD%2C%20Australia%7CMacrossan%20Street%2C%20Port%20Douglas%20QLD%2C%20Australia
A7: 46339 | B7: 6 | C7: Port Douglas | D7: Dag 6 – Wildlife Sanctuary & stranddag - Bezoek aan het Rainforest Habitat Wildlife Sanctuary - Middag: relaxen aan Four Mile Beach of vrije tijd bij het resort - Avondwandeling langs de boulevard en diner in Port Douglas | H7: https://www.google.com/maps/dir/?api=1&origin=19-37%20Saint%20Crispins%20Avenue%2C%20Port%20Douglas%20QLD%204877%2C%20Australia&destination=19-37%20Saint%20Crispins%20Avenue%2C%20Port%20Douglas%20QLD%204877%2C%20Australia&travelmode=driving&waypoints=Wildlife%20Habitat%20Port%20Douglas%2C%201%20Port%20Douglas%20Road%2C%20Port%20Douglas%20QLD%2C%20Australia%7CFour%20Mile%20Beach%2C%20Port%20Douglas%20QLD%2C%20Australia%7CMacrossan%20Street%2C%20Port%20Douglas%20QLD%2C%20Australia
A8: 46340 | B8: 7 | C8: Port Douglas | D8: Dag 7 – Vrije dag / extra excursie - genieten van zwembad, strand | G8: River Drift Experience - Daintree Rainforest - Back Country Bliss Adventures | H8: https://www.google.com/maps/dir/?api=1&origin=19-37%20Saint%20Crispins%20Avenue%2C%20Port%20Douglas%20QLD%204877%2C%20Australia&destination=19-37%20Saint%20Crispins%20Avenue%2C%20Port%20Douglas%20QLD%204877%2C%20Australia&travelmode=walking&waypoints=Four%20Mile%20Beach%2C%20Port%20Douglas%20QLD%2C%20Australia
A9: 46341 | B9: 8 | C9: Atherton Tablelands (via Mareeba) | D9: Dag 8 – Port Douglas → Atherton Tablelands (via Mareeba) (Yungaburra) - Rit via Mareeba naar de Atherton Tablelands (ca. 2 uur) - Stop bij koffie- en theetuinen in Mareeba - Bezoek Granite Gorge (rotswallaby’s) | E9: 120 km | F9: 2u | H9: https://www.google.com/maps/dir/?api=1&origin=19-37%20Saint%20Crispins%20Avenue%2C%20Port%20Douglas%20QLD%204877%2C%20Australia&destination=7%20Rykers%20Road%2C%20Cape%20Tribulation%20QLD%204873%2C%20Australia&travelmode=driving&waypoints=Coffee%20Works%20Mareeba%2C%20136%20Mason%20Street%2C%20Mareeba%20QLD%204880%2C%20Australia%7CGranite%20Gorge%20Nature%20Park%2C%20Chewko%20Road%2C%20Mareeba%20QLD%2C%20Australia
A10: 46342 | B10: 9 | C10: Atherton Tablelands | D10: Dag 9 – Atherton Tablelands (watervallenroute) - Lake Eacham (±1 uur) - Lake Barrine (±45 min) - Start de Waterfall Circuit: - Millaa Millaa Falls, Zillie Falls, Ellinjaa Falls - Curtain Fig Tree bij Yungaburra - Babinda Boulders (zwemmen in de natuurlijke poelen) | E10: 100 km | F10: 2u | G10: Vroeg platypus kijken in Yungaburra | H10: https://www.google.com/maps/dir/?api=1&origin=7%20Rykers%20Road%2C%20Cape%20Tribulation%20QLD%204873%2C%20Australia&destination=Eacham%20Close%2C%20Lake%20Eacham%20QLD%204884%2C%20Australia&travelmode=driving&waypoints=Lake%20Barrine%2C%20QLD%2C%20Australia%7CCurtain%20Fig%20Tree%2C%20Yungaburra%20QLD%2C%20Australia%7CMillaa%20Millaa%20Falls%2C%20QLD%2C%20Australia%7CZillie%20Falls%2C%20QLD%2C%20Australia%7CEllinjaa%20Falls%2C%20QLD%2C%20Australia
A11: 46343 | B11: 10 | C11: Terug naar Cairns | D11: Dag 10 – Atherton Tablelands → Cairns / northern beaches - Babinda Boulders (ochtend) (±1–1,5 uur) - Kuranda - Barron Falls Lookout – korte maar indrukwekkende stop - Kuranda Village (marktjes, ijsje, souvenirs) - Optioneel: stop bij Josephine Falls of Walshs Pyramid uitzichtpunt onderweg | E11: 100 km | F11: 2 uur | G11: Lunchstop Kuranda Village | H11: https://www.google.com/maps/dir/?api=1&origin=Eacham%20Close%2C%20Lake%20Eacham%20QLD%204884%2C%20Australia&destination=18-26%20Cannon%20Street%2C%20Manunda%20QLD%204870%2C%20Australia&travelmode=driving&waypoints=Babinda%20Boulders%2C%20Babinda%20QLD%2C%20Australia%7CJosephine%20Falls%2C%20Wooroonooran%20QLD%2C%20Australia%7CWalshs%20Pyramid%20Lookout%2C%20Gordonvale%20QLD%2C%20Australia%7CKuranda%20Village%2C%20Kuranda%20QLD%2C%20Australia%7CBarron%20Falls%20Lookout%2C%20Kuranda%20QLD%2C%20Australia
A12: 46344 | B12: 11 | C12: Cairns naar Sydney | D12: Dag 11 – Cairns → Sydney - Rit terug naar Cairns | H12: https://www.google.com/maps/dir/?api=1&origin=18-26%20Cannon%20Street%2C%20Manunda%20QLD%204870%2C%20Australia&destination=Cairns%20Airport%20Domestic%20Terminal%2C%20Cairns%20Airport%20QLD%204870%2C%20Australia&travelmode=driving

Sheet Dagplanning - Sydney - mt Maced
A1: Datum | B1: Dag | C1: Route | D1: Beschrijving | E1: Afstand | F1: Reistijd | G1: informatie | H1: Google Maps-route | I1: Komoot wandeling
A2: 46344 | B2: 1 | C2: Cairns ➔ Sydney (ochtend vlucht) | D2: Dag 1 – Sydney - Middag: rondje lopen bij Circular Quay en opera houde - Avond: diner bij Circular Quay met uitzicht op Opera House | H2: https://www.google.com/maps/dir/?api=1&origin=5%20Milson%20Rd%2C%20Cremorne%20Point%20NSW%202090%2C%20Australia&destination=5%20Milson%20Rd%2C%20Cremorne%20Point%20NSW%202090%2C%20Australia&travelmode=driving&waypoints=Circular%20Quay%2C%20Sydney%20NSW%2C%20Australia%7CSydney%20Opera%20House%2C%20Bennelong%20Point%2C%20Sydney%20NSW%2C%20Australia
A3: 46345 | B3: 2 | C3: Sydney | D3: Dag 2 – Sydney - Ochtend: klim naar de Pylon Lookout & Museum (op de Harbour Bridge) - Sydney Harbour ferry dagtocht – bijv. Manly of Taronga Zoo - Middag: relax op Bondi of korte kustwandeling Bondi–Coogee - Avond: Darling Harbour verkennen | H3: https://www.google.com/maps/dir/?api=1&origin=5%20Milson%20Rd%2C%20Cremorne%20Point%20NSW%202090%2C%20Australia&destination=5%20Milson%20Rd%2C%20Cremorne%20Point%20NSW%202090%2C%20Australia&travelmode=driving&waypoints=Pylon%20Lookout%2C%20Sydney%20Harbour%20Bridge%2C%20The%20Rocks%20NSW%2C%20Australia%7CTaronga%20Zoo%20Sydney%2C%20Bradleys%20Head%20Rd%2C%20Mosman%20NSW%2C%20Australia%7CBondi%20Beach%2C%20NSW%2C%20Australia%7CDarling%20Harbour%2C%20Sydney%20NSW%2C%20Australia
A4: 46346 | B4: 3 | C4: Sydney | D4: Dag 3 – Sydney - Dagtrip naar Bondi - Alternatief: city highlights (bijv. Art Gallery of NSW of Powerhouse Museum) - Avond: diner in The Rocks | H4: https://www.google.com/maps/dir/?api=1&origin=5%20Milson%20Rd%2C%20Cremorne%20Point%20NSW%202090%2C%20Australia&destination=5%20Milson%20Rd%2C%20Cremorne%20Point%20NSW%202090%2C%20Australia&travelmode=driving&waypoints=Art%20Gallery%20of%20New%20South%20Wales%2C%20Art%20Gallery%20Rd%2C%20Sydney%20NSW%2C%20Australia%7CBarangaroo%20Reserve%2C%20Hickson%20Rd%2C%20Barangaroo%20NSW%2C%20Australia%7CThe%20Rocks%2C%20Sydney%20NSW%2C%20Australia | I4: https://www.komoot.com/nl-nl/tour/3109676328
A5: 46347 | B5: 4 | C5: Sydney | D5: Dag 4 – Sydney - Bezoek Australian Museum (dino’s, Aboriginal cultuur, natuurhistorie) - Wandeling naar Macquarie’s Chair met uitzicht over de haven - Ontspannen door de Royal Botanic Gardens | H5: https://www.google.com/maps/dir/?api=1&origin=5%20Milson%20Rd%2C%20Cremorne%20Point%20NSW%202090%2C%20Australia&destination=5%20Milson%20Rd%2C%20Cremorne%20Point%20NSW%202090%2C%20Australia&travelmode=driving&waypoints=Australian%20Museum%2C%201%20William%20St%2C%20Darlinghurst%20NSW%2C%20Australia%7CMrs%20Macquarie's%20Chair%2C%20Sydney%20NSW%2C%20Australia%7CRoyal%20Botanic%20Garden%20Sydney%2C%20NSW%2C%20Australia
A6: 46348 | B6: 5 | C6: Sydney → Bendalong | D6: Dag 5 – Sydney → Bendalong Rit langs de Grand Pacific Drive (Sea Cliff Bridge) Stop in Kiama (blowhole) Middagwandeling langs Hyams Beach | E6: 200 | F6: 3 | H6: https://www.google.com/maps/dir/?api=1&origin=5%20Milson%20Rd%2C%20Cremorne%20Point%20NSW%202090%2C%20Australia&destination=1%20Waratah%20Street%2C%20Bendalong%20NSW%202539%2C%20Australia&travelmode=driving&waypoints=Sea%20Cliff%20Bridge%2C%20Clifton%20NSW%2C%20Australia%7CKiama%20Blowhole%2C%20Kiama%20NSW%2C%20Australia%7CHyams%20Beach%2C%20NSW%2C%20Australia
A7: 46349 | B7: 6 | C7: Bendalong | D7: Dag 6 – Bendalong - Ochtend: dolfijnen- of walvissentocht (seizoen afhankelijk) - Snorkelen of zwemmen in Jervis Bay Marine Park - Middag: wandelen in Booderee National Park | H7: https://www.google.com/maps/dir/?api=1&origin=1%20Waratah%20Street%2C%20Bendalong%20NSW%202539%2C%20Australia&destination=1%20Waratah%20Street%2C%20Bendalong%20NSW%202539%2C%20Australia&travelmode=driving&waypoints=Huskisson%20Wharf%2C%20Huskisson%20NSW%2C%20Australia%7CGreen%20Patch%2C%20Booderee%20National%20Park%2C%20Jervis%20Bay%20NSW%2C%20Australia%7CMurrays%20Beach%2C%20Jervis%20Bay%20Territory%2C%20Australia
A8: 46350 | B8: 7 | C8: Bendalong | D8: Dag 7 – Bendalong | H8: https://www.google.com/maps/dir/?api=1&origin=1%20Waratah%20Street%2C%20Bendalong%20NSW%202539%2C%20Australia&destination=1%20Waratah%20Street%2C%20Bendalong%20NSW%202539%2C%20Australia&travelmode=driving&waypoints=Bendalong%20Beach%2C%20Bendalong%20NSW%2C%20Australia%7CWasherwomans%20Beach%2C%20Bendalong%20NSW%2C%20Australia
A9: 46351 | B9: 8 | C9: Bendalong → Tuross Head | D9: Dag 7 – Bendalong → Tuross Head Rit langs de kust richting Tuross Head Stop bij kleine stranden onderweg Middag: lagunes en strand verkennen (Tuross Inlet, Dolphin Point) | E9: 150 | F9: 2.15 | G9: Sapphire Coast, Tathra Beach https://naroomacharters.com.au/snorkelling-with-the-seals | H9: https://www.google.com/maps/dir/?api=1&origin=1%20Waratah%20Street%2C%20Bendalong%20NSW%202539%2C%20Australia&destination=Discovery%20Parks%20-%20Narooma%20Beach%2C%207323%20Princes%20Hwy%2C%20Narooma%20NSW%202546%2C%20Australia&travelmode=driving&waypoints=Dolphin%20Point%2C%20NSW%2C%20Australia%7CTuross%20Head%2C%20NSW%2C%20Australia%7CTuross%20Inlet%2C%20NSW%2C%20Australia
A10: 46352 | B10: 9 | C10: Tuross Head | D10: Dag 8 – Tuross Head Kajak of zwemmen in Tuross Inlet Kleine strandwandelingen en lagunes verkennen Optioneel: korte dagtrip Narooma (Mill Bay Boardwalk of Montague Island boottocht) | H10: https://www.google.com/maps/dir/?api=1&origin=Discovery%20Parks%20-%20Narooma%20Beach%2C%207323%20Princes%20Hwy%2C%20Narooma%20NSW%202546%2C%20Australia&destination=Discovery%20Parks%20-%20Narooma%20Beach%2C%207323%20Princes%20Hwy%2C%20Narooma%20NSW%202546%2C%20Australia&travelmode=driving&waypoints=Narooma%20Wharf%2C%20Narooma%20NSW%2C%20Australia%7CMill%20Bay%20Boardwalk%2C%20North%20Narooma%20NSW%2C%20Australia%7CTuross%20Inlet%2C%20NSW%2C%20Australia
A11: 46353 | B11: 10 | C11: Tuross Head → Eden | D11: Dag 9 – Tuross Head → Eden Rit langs Sapphire Coast Stop bij kleine baaien en uitzichtpunten Middag: zwemmen of snorkelen bij Bar Beach | E11: 140 | F11: 1.4 | H11: https://www.google.com/maps/dir/?api=1&origin=Discovery%20Parks%20-%20Narooma%20Beach%2C%207323%20Princes%20Hwy%2C%20Narooma%20NSW%202546%2C%20Australia&destination=731%20Princes%20Hwy%2C%20Boydtown%20NSW%202551%2C%20Australia&travelmode=driving&waypoints=Bermagui%20Blue%20Pool%2C%20Bermagui%20NSW%2C%20Australia%7CTathra%20Beach%2C%20Tathra%20NSW%2C%20Australia%7CBar%20Beach%2C%20Merimbula%20NSW%2C%20Australia%7CRotary%20Park%2C%20Eden%20NSW%2C%20Australia
A12: 46354 | B12: 11 | C12: Eden→ Traralgon | D12: Dag 11 – Eden→ Traralgon Zwemmen en relaxten | E12: 416 | F12: 5 | H12: https://www.google.com/maps/dir/?api=1&origin=731%20Princes%20Hwy%2C%20Boydtown%20NSW%202551%2C%20Australia&destination=5353%20Princes%20Highway%2C%20Traralgon%20VIC%203844%2C%20Australia&travelmode=driving&waypoints=Lakes%20Entrance%20Main%20Beach%2C%20Lakes%20Entrance%20VIC%2C%20Australia
A13: 46355 | B13: 12 | C13: Traralgon → Wilsons Promontory | D13: Dag 12 – Traralgon → Wilsons Promontory - Rit naar Wilsons Promontory NP - Middagwandeling naar Squeaky Beach - Hike naar Mt. Oberon Lookout (kindvriendelijk: halverwege stoppen) | E13: 150 | F13: 2 | H13: https://www.google.com/maps/dir/?api=1&origin=5353%20Princes%20Highway%2C%20Traralgon%20VIC%203844%2C%20Australia&destination=Tidal%20River%20Visitor%20Centre%2C%201%20Ring%20Road%2C%20Tidal%20River%20VIC%203960%2C%20Australia&travelmode=driving&waypoints=Squeaky%20Beach%20Carpark%2C%20Wilsons%20Promontory%20VIC%2C%20Australia%7CTelegraph%20Saddle%20Carpark%2C%20Wilsons%20Promontory%20VIC%2C%20Australia | I13: https://www.komoot.com/nl-nl/tour/2615866530 https://www.komoot.com/nl-nl/tour/2615872347 https://www.komoot.com/nl-nl/tour/2615907336
A14: 46356 | B14: 13 | C14: Wilsons Promontory | D14: Dag 13 – Wilsons Promontory - Hike naar Lilly pilly gully 5,5 km 1,5 u (makkelijk) - Wildlife-spotten (kangoeroes, wombats, emoes) - Optioneel: Tidal River wandeling | H14: https://www.google.com/maps/dir/?api=1&origin=Tidal%20River%20Visitor%20Centre%2C%201%20Ring%20Road%2C%20Tidal%20River%20VIC%203960%2C%20Australia&destination=Tidal%20River%20Visitor%20Centre%2C%201%20Ring%20Road%2C%20Tidal%20River%20VIC%203960%2C%20Australia&travelmode=driving&waypoints=Lilly%20Pilly%20Gully%20Carpark%2C%20Wilsons%20Promontory%20VIC%2C%20Australia%7CProm%20Wildlife%20Walk%2C%20Wilsons%20Promontory%20VIC%2C%20Australia%7CTidal%20River%20Footbridge%2C%20Wilsons%20Promontory%20VIC%2C%20Australia | I14: https://www.komoot.com/nl-nl/tour/2768887281 https://www.komoot.com/nl-nl/tour/2615896897 https://www.komoot.com/nl-nl/tour/2768875031
A15: 46357 | B15: 14 | C15: Wilsons Promontory → Yarra Ranges | D15: Dag 14 – Wilsons Promontory → Yarra Ranges - Rit richting Yarra Ranges NP - Middagwandeling door regenwoud met hoge eucalyptusbomen - Warburton river tubing (zelf tubes kopen?) | E15: 250 | F15: 3.3 | H15: https://www.google.com/maps/dir/?api=1&origin=Tidal%20River%20Visitor%20Centre%2C%201%20Ring%20Road%2C%20Tidal%20River%20VIC%203960%2C%20Australia&destination=30%20Woods%20Point%20Rd%2C%20Warburton%20VIC%203799%2C%20Australia&travelmode=driving&waypoints=Rainforest%20Gallery%2C%20Mount%20Donna%20Buang%2C%20VIC%2C%20Australia%7CWarburton%20Water%20World%2C%20Warburton%20VIC%2C%20Australia
A16: 46358 | B16: 15 | C16: Yarra Ranges | D16: Dag 15 – Yarra Ranges - Middagwandeling door regenwoud met hoge eucalyptusbomen - Warburton river tubing (zelf tubes kopen?) | H16: https://www.google.com/maps/dir/?api=1&origin=30%20Woods%20Point%20Rd%2C%20Warburton%20VIC%203799%2C%20Australia&destination=30%20Woods%20Point%20Rd%2C%20Warburton%20VIC%203799%2C%20Australia&travelmode=driving&waypoints=Warburton%20Redwood%20Forest%2C%20Cement%20Creek%20Rd%2C%20East%20Warburton%20VIC%2C%20Australia%7CRainforest%20Gallery%2C%20Mount%20Donna%20Buang%2C%20VIC%2C%20Australia%7CWarburton%20Water%20World%2C%20Warburton%20VIC%2C%20Australia
A17: 46359 | B17: 16 | C17: Yarra Ranges → Lorne | D17: Dag 16 – Yarra Ranges → Lorne - fotostop Black Spur Drive - Waterval bij Lorne bijkijken - afsluiten aan het strand | E17: 240 | F17: 3.2 | H17: https://www.google.com/maps/dir/?api=1&origin=30%20Woods%20Point%20Rd%2C%20Warburton%20VIC%203799%2C%20Australia&destination=Lorne%20VIC%203232%2C%20Australia&travelmode=driving&waypoints=Black%20Spur%20Drive%2C%20Narbethong%20VIC%2C%20Australia%7CBells%20Beach%2C%20VIC%2C%20Australia%7CErskine%20Falls%2C%20Lorne%20VIC%2C%20Australia%7CLorne%20Beach%2C%20Lorne%20VIC%2C%20Australia
A18: 46360 | B18: 17 | C18: Lorne → Bimbi Park | D18: Dag 17 – Lorne → Bimbi park - Nog wandeling of zwemmen in de ochtend - Rit over de Great Ocean Road - Aankomst in Bimbi Park (koala’s spotten) | E18: 75 | F18: 1.2 | H18: https://www.google.com/maps/dir/?api=1&origin=Lorne%20VIC%203232%2C%20Australia&destination=Bimbi%20Park%2C%2090%20Manna%20Gum%20Drive%2C%20Cape%20Otway%20VIC%203233%2C%20Australia&travelmode=driving&waypoints=Teddy's%20Lookout%2C%20Lorne%20VIC%2C%20Australia%7CKennet%20River%20Nature%20Walk%2C%20Kennett%20River%20VIC%2C%20Australia%7CApollo%20Bay%2C%20VIC%2C%20Australia | I18: https://www.komoot.com/nl-nl/tour/2615914738
A19: 46361 | B19: 18 | C19: Bimbi Park | D19: Dag 18 – Bimbi Park - Wandelen in Great Otway National Park - Stops bij Bells Beach en Twelve Apostles - Bezoek Cape Otway Lightstation - Middag strandwandeling of relaxen | H19: https://www.google.com/maps/dir/?api=1&origin=Bimbi%20Park%2C%2090%20Manna%20Gum%20Drive%2C%20Cape%20Otway%20VIC%203233%2C%20Australia&destination=Bimbi%20Park%2C%2090%20Manna%20Gum%20Drive%2C%20Cape%20Otway%20VIC%203233%2C%20Australia&travelmode=driving&waypoints=Maits%20Rest%20Rainforest%20Walk%2C%20Cape%20Otway%20VIC%2C%20Australia%7CTwelve%20Apostles%2C%20Port%20Campbell%20National%20Park%20VIC%2C%20Australia%7CCape%20Otway%20Lightstation%2C%20Cape%20Otway%20VIC%2C%20Australia | I19: https://www.komoot.com/nl-nl/tour/2615919843
A20: 46362 | B20: 19 | C20: Bimbi Park → Mount Macedon | D20: Dag 19 – Bimbi Park → Mount Macedon - Rit richting Mount Macedon (via Geelong & Melbourne) - Stop bij Hanging Rock | E20: 250 | F20: 3.3 | H20: https://www.google.com/maps/dir/?api=1&origin=Bimbi%20Park%2C%2090%20Manna%20Gum%20Drive%2C%20Cape%20Otway%20VIC%203233%2C%20Australia&destination=47%20Taylors%20Rd%2C%20Mount%20Macedon%20VIC%203441%2C%20Australia&travelmode=driving&waypoints=Geelong%20Waterfront%2C%20Geelong%20VIC%2C%20Australia%7CHanging%20Rock%20Reserve%2C%20Woodend%20VIC%2C%20Australia
A21: 46363 | B21: 20 | C21: Mount Macedon | D21: Dag 20 – Mount Macedon - Wandelen door Macedon Ranges Regional Park - Bezoek Memorial Cross - Middag: natuur & rust | H21: https://www.google.com/maps/dir/?api=1&origin=47%20Taylors%20Rd%2C%20Mount%20Macedon%20VIC%203441%2C%20Australia&destination=47%20Taylors%20Rd%2C%20Mount%20Macedon%20VIC%203441%2C%20Australia&travelmode=driving&waypoints=Camels%20Hump%2C%20Mount%20Macedon%20VIC%2C%20Australia%7CMount%20Macedon%20Memorial%20Cross%2C%20Mount%20Macedon%20VIC%2C%20Australia%7CMacedon%20Regional%20Park%2C%20Mount%20Macedon%20VIC%2C%20Australia
A22: 46364 | B22: 21 | C22: Mount Macedon | D22: Dag 21 – Mount Macedon - Dagtocht naar wijnregio Woodend & Hanging Rock - Picknick en lokale proeverijen | H22: https://www.google.com/maps/dir/?api=1&origin=47%20Taylors%20Rd%2C%20Mount%20Macedon%20VIC%203441%2C%20Australia&destination=47%20Taylors%20Rd%2C%20Mount%20Macedon%20VIC%203441%2C%20Australia&travelmode=driving&waypoints=Woodend%20VIC%2C%20Australia%7CHanging%20Rock%20Winery%2C%20Newham%20VIC%2C%20Australia%7CHanging%20Rock%20Reserve%2C%20Woodend%20VIC%2C%20Australia
A23: 46365 | B23: 22 | C23: Mount Macedon | D23: Dag 22 – Mount Macedon - Bezoek tuinen en parken in Macedon | H23: https://www.google.com/maps/dir/?api=1&origin=47%20Taylors%20Rd%2C%20Mount%20Macedon%20VIC%203441%2C%20Australia&destination=47%20Taylors%20Rd%2C%20Mount%20Macedon%20VIC%203441%2C%20Australia&travelmode=driving&waypoints=Forest%20Glade%20Gardens%2C%20Mount%20Macedon%20VIC%2C%20Australia%7CCentennial%20Park%2C%20Macedon%20VIC%2C%20Australia%7CStanley%20Park%2C%20Mount%20Macedon%20VIC%2C%20Australia
A24: 46366 | B24: 23 | C24: Mount Macedon → Melbourne | D24: Dag 23 – Mount Macedon → Melbourne - Rit naar Melbourne - Wandeling door Fitzroy Gardens - Bezoek Federation Square / optionele lunch in centrum | E24: 60 | F24: 1 | H24: https://www.google.com/maps/dir/?api=1&origin=47%20Taylors%20Rd%2C%20Mount%20Macedon%20VIC%203441%2C%20Australia&destination=639%20Lonsdale%20St%2C%20Melbourne%20VIC%203000%2C%20Australia&travelmode=driving&waypoints=Fitzroy%20Gardens%2C%20East%20Melbourne%20VIC%2C%20Australia%7CFederation%20Square%2C%20Melbourne%20VIC%2C%20Australia
A25: 46367 | B25: 24 | C25: Melbourne | D25: Dag 24 – Melbourne - Verken de stad per City Circle Tram (gratis hop-on-hop-off) - Bezoek de laneways & street art (o.a. Hosier Lane, AC/DC Lane) - Dwaal door de Queen Victoria Market (eten, lokale sfeer) | G25: https://www.komoot.com/nl-nl/tour/3192928549?share_token=aXxsZ4xh4f2cbHJ5mcjwqgwY9RyNIfZJCbUx8xh56YyKQ6AGd2&ref=wtd&t_s=referral&t_cid=route_share&t_ref_username=5138285305045 | H25: https://www.google.com/maps/dir/?api=1&origin=639%20Lonsdale%20St%2C%20Melbourne%20VIC%203000%2C%20Australia&destination=639%20Lonsdale%20St%2C%20Melbourne%20VIC%203000%2C%20Australia&travelmode=walking&waypoints=Queen%20Victoria%20Market%2C%20Melbourne%20VIC%2C%20Australia%7CHosier%20Lane%2C%20Melbourne%20VIC%2C%20Australia%7CAC%2FDC%20Lane%2C%20Melbourne%20VIC%2C%20Australia%7CFlinders%20Street%20Station%2C%20Melbourne%20VIC%2C%20Australia | I25: https://www.komoot.com/nl-nl/tour/3192928549
A26: 46368 | B26: 25 | C26: Melbourne | D26: Dag 25 – Melbourne - Bezoek ACMI (Australian Centre for the Moving Image) - Middag: tram of taxi naar St Kilda - Wandel door Luna Park en langs de pier - Avond: pinguïns bij St Kilda Pier spotten bij zonsondergang | G26: https://holidayhaven.com.au/bendalong/ | H26: https://www.google.com/maps/dir/?api=1&origin=639%20Lonsdale%20St%2C%20Melbourne%20VIC%203000%2C%20Australia&destination=639%20Lonsdale%20St%2C%20Melbourne%20VIC%203000%2C%20Australia&travelmode=driving&waypoints=ACMI%2C%20Federation%20Square%2C%20Melbourne%20VIC%2C%20Australia%7CLuna%20Park%20Melbourne%2C%20Lower%20Esplanade%2C%20St%20Kilda%20VIC%2C%20Australia%7CSt%20Kilda%20Pier%20Penguin%20Viewing%20Platform%2C%20St%20Kilda%20VIC%2C%20Australia
A27: 46369 | B27: 26 | C27: Melbourne - Christchurch (ochten vlucht/middag aankomst

Sheet Dagplanning - Nieuw Zeeland
A1: Datum | B1: Dag | C1: Route | D1: Beschrijving | E1: Afstand | F1: Reistijd | G1: informatie | H1: Google Maps-route | I1: Komoot wandeling
A2: 46369 | B2: 1 | C2: Christchurch | D2: Dag 1 – Christchurch - Aankomst in middag, eerst naar hotel - avond wandeling in de stad | H2: https://www.google.com/maps/dir/?api=1&origin=176%20Manchester%20Street%2C%20Apartment%20107%2C%20Christchurch%208011%2C%20New%20Zealand&destination=176%20Manchester%20Street%2C%20Apartment%20107%2C%20Christchurch%208011%2C%20New%20Zealand&travelmode=walking&waypoints=Riverside%20Market%2C%20Christchurch%2C%20New%20Zealand%7CBridge%20of%20Remembrance%2C%20Christchurch%2C%20New%20Zealand%7CNew%20Regent%20Street%2C%20Christchurch%2C%20New%20Zealand
A3: 46370 | B3: 2 | C3: Christchurch | D3: Dag 2 – Christchurch - Bezoek Botanic Gardens en de Avon River - Ontdek het centrum met street art en vernieuwde architectuur - Ontdek Canterbury Museum of Quake City Museum | H3: https://www.google.com/maps/dir/?api=1&origin=176%20Manchester%20Street%2C%20Apartment%20107%2C%20Christchurch%208011%2C%20New%20Zealand&destination=176%20Manchester%20Street%2C%20Apartment%20107%2C%20Christchurch%208011%2C%20New%20Zealand&travelmode=driving&waypoints=Christchurch%20Botanic%20Gardens%2C%20Christchurch%2C%20New%20Zealand%7CAvon%20River%20Precinct%2C%20Christchurch%2C%20New%20Zealand%7CQuake%20City%2C%20299%20Durham%20Street%20North%2C%20Christchurch%2C%20New%20Zealand%7CChristchurch%20Street%20Art%20Trail%2C%20Christchurch%2C%20New%20Zealand
A4: 46371 | B4: 3 | C4: Christchurch | D4: Dag 3 – Christchurch - Dagtocht naar Akaroa (Frans dorpje & optionele dolfijncruise) - Alternatief: rit met de Christchurch Gondola - Avondwandeling door de stad of relaxdag | H4: https://www.google.com/maps/dir/?api=1&origin=176%20Manchester%20Street%2C%20Apartment%20107%2C%20Christchurch%208011%2C%20New%20Zealand&destination=176%20Manchester%20Street%2C%20Apartment%20107%2C%20Christchurch%208011%2C%20New%20Zealand&travelmode=driving&waypoints=Akaroa%20Lighthouse%2C%20Akaroa%2C%20New%20Zealand%7CAkaroa%20Main%20Wharf%2C%20Akaroa%2C%20New%20Zealand%7CAkaroa%2C%20New%20Zealand
A5: 46372 | B5: 4 | C5: Lake Tekapo | D5: Dag 4 – Lake Tekapo - Rit naar Lake Tekapo (ca. 3 uur) - Bezoek Church of the Good Shepherd - ’s Avonds sterrenkijken bij Mt John Observatory - Tekapo Springs (bij tijd over €50 family | E5: 225 km | F5: 3u | H5: https://www.google.com/maps/dir/?api=1&origin=176%20Manchester%20Street%2C%20Apartment%20107%2C%20Christchurch%208011%2C%20New%20Zealand&destination=Irishman%20Creek%20Station%2C%20State%20Highway%208%2C%20Lake%20Tekapo%207999%2C%20New%20Zealand&travelmode=driving&waypoints=Church%20of%20the%20Good%20Shepherd%2C%20Lake%20Tekapo%2C%20New%20Zealand%7CTekapo%20Springs%2C%20Lake%20Tekapo%2C%20New%20Zealand%7CMt%20John%20Observatory%2C%20Lake%20Tekapo%2C%20New%20Zealand | I5: https://www.komoot.com/nl-nl/tour/2617940841
A6: 46373 | B6: 5 | C6: Mount Cook | D6: Dag 5 – Mount Cook - Rit naar Mount Cook Village (ca. 1 uur) - Wandeling Hooker Valley Track - Overnachting met uitzicht op Aoraki/Mount Cook | E6: 105 km | F6: 1u30 | G6: Kea Point 2.8 km return of Hooker Valley 10 km return | H6: https://www.google.com/maps/dir/?api=1&origin=Irishman%20Creek%20Station%2C%20State%20Highway%208%2C%20Lake%20Tekapo%207999%2C%20New%20Zealand&destination=Mt%20Cook%20Lodge%2C%20Aoraki%20Mount%20Cook%20Village%2C%20New%20Zealand&travelmode=driving&waypoints=Peters%20Lookout%2C%20Lake%20Pukaki%2C%20New%20Zealand%7CWhite%20Horse%20Hill%20Car%20Park%2C%20Aoraki%20Mount%20Cook%20National%20Park%2C%20New%20Zealand%7CHooker%20Valley%20Track%2C%20Aoraki%20Mount%20Cook%20National%20Park%2C%20New%20Zealand | I6: https://www.komoot.com/nl-nl/tour/2617818404 https://www.komoot.com/nl-nl/tour/3110103381 https://www.komoot.com/nl-nl/tour/2617823779 https://www.komoot.com/nl-nl/tour/2617834182 https://www.komoot.com/nl-nl/tour/2617829803 https://www.komoot.com/nl-nl/tour/2617778324
A7: 46374 | B7: 6 | C7: Dunedin | D7: Dag 6 – Moeraki - Stop bij de Omaru | E7: 320 km | F7: 4u30 | G7: via Twizel Oamaru en Moeraki | H7: https://www.google.com/maps/dir/?api=1&origin=Mt%20Cook%20Lodge%2C%20Aoraki%20Mount%20Cook%20Village%2C%20New%20Zealand&destination=114%20Wansbeck%20Street%2C%20Oamaru%209401%2C%20New%20Zealand&travelmode=driving&waypoints=Oamaru%20Victorian%20Precinct%2C%20Oamaru%2C%20New%20Zealand%7CMoeraki%20Boulders%20Beach%2C%20Moeraki%2C%20New%20Zealand
A8: 46375 | B8: 7 | C8: Te Anau | D8: Dag 7 – Te Anau - Rit naar Te Anau (ca. 4 uur) - Optioneel: Catlins-route langs ruige kust - Avondwandeling aan Lake Te Anau | E8: 400 km | F8: 5u30 | H8: https://www.google.com/maps/dir/?api=1&origin=114%20Wansbeck%20Street%2C%20Oamaru%209401%2C%20New%20Zealand&destination=77%20Te%20Anau-Manapouri%20Highway%2C%20Te%20Anau%209640%2C%20New%20Zealand&travelmode=driving&waypoints=Dunedin%20Railway%20Station%2C%20Dunedin%2C%20New%20Zealand%7CLake%20Te%20Anau%2C%20Te%20Anau%2C%20New%20Zealand | I8: https://www.komoot.com/nl-nl/tour/2783334098 https://www.komoot.com/nl-nl/tour/2783334502 https://www.komoot.com/nl-nl/tour/2783336809 https://www.komoot.com/nl-nl/tour/2783340849
A9: 46376 | B9: 8 | C9: Te Anau | D9: Dag 8 – Te Anau (Fiordland) - Dagtocht Milford Sound (cruise met fjorden & watervallen) - Op terugweg van Milford wandeling naar Key Summit | E9: 120 km 240 km retour | F9: 1u40 + cruise | G9: Mirror Lakes, Eglinton, or Hollyford Valleys, Key Summit | H9: https://www.google.com/maps/dir/?api=1&origin=77%20Te%20Anau-Manapouri%20Highway%2C%20Te%20Anau%209640%2C%20New%20Zealand&destination=77%20Te%20Anau-Manapouri%20Highway%2C%20Te%20Anau%209640%2C%20New%20Zealand&travelmode=driving&waypoints=Milford%20Sound%20Visitor%20Terminal%2C%20Milford%20Sound%2C%20New%20Zealand%7CThe%20Divide%20Shelter%2C%20Milford%20Road%2C%20Fiordland%20National%20Park%2C%20New%20Zealand%7CMirror%20Lakes%2C%20Milford%20Road%2C%20New%20Zealand | I9: https://www.komoot.com/nl-nl/tour/2783218665 https://www.komoot.com/nl-nl/tour/2616257680 https://www.komoot.com/nl-nl/tour/2616261577
A10: 46377 | B10: 9 | C10: Queenstown | D10: Dag 9 – Queenstown - Rit naar Queenstown - Stop bij Kingston / Lake Wakatipu - Avond in levendig centrum | E10: 175 km | F10: 2u30 | H10: https://www.google.com/maps/dir/?api=1&origin=77%20Te%20Anau-Manapouri%20Highway%2C%20Te%20Anau%209640%2C%20New%20Zealand&destination=4%20Cemetery%20Road%2C%20Queenstown%209300%2C%20New%20Zealand&travelmode=driving&waypoints=Kingston%2C%20New%20Zealand%7CDevils%20Staircase%20Lookout%20Point%2C%20Lake%20Wakatipu%2C%20New%20Zealand%7CQueenstown%20Bay%20Beach%2C%20Queenstown%2C%20New%20Zealand
A11: 46378 | B11: 10 | C11: Queenstown | D11: Dag 10 – Queenstown - Kabelbaan Skyline Gondola - Activiteiten: jetboat, wijnproeverij, hike - Avondwandeling langs het meer | G11: Queenstown / Glenorchy / Arrowtown | H11: https://www.google.com/maps/dir/?api=1&origin=4%20Cemetery%20Road%2C%20Queenstown%209300%2C%20New%20Zealand&destination=4%20Cemetery%20Road%2C%20Queenstown%209300%2C%20New%20Zealand&travelmode=driving&waypoints=Skyline%20Queenstown%2C%20Queenstown%2C%20New%20Zealand%7CShotover%20Jet%2C%20Arthurs%20Point%2C%20New%20Zealand%7CGibbston%20Valley%20Winery%2C%20Gibbston%2C%20New%20Zealand%7CQueenstown%20Bay%20Beach%2C%20Queenstown%2C%20New%20Zealand | I11: https://www.komoot.com/nl-nl/tour/2617889552 https://www.komoot.com/nl-nl/tour/2616234917 https://www.komoot.com/nl-nl/tour/2617885861 https://www.komoot.com/nl-nl/tour/2617880186 https://www.komoot.com/nl-nl/tour/2617883150
A12: 46379 | B12: 11 | C12: Wanaka | D12: Dag 11 – Wanaka - Rit via Crown Range Road (prachtige uitzichten) - Bezoek Wanaka Tree en meerwandeling - Wandeling Roy's peak of Diamond Lake | E12: 70 km | F12: 1u30 | G12: viewpoints The Blue Pools, Fantail Falls, or Lake Hawea | H12: https://www.google.com/maps/dir/?api=1&origin=4%20Cemetery%20Road%2C%20Queenstown%209300%2C%20New%20Zealand&destination=19A%20Kidds%20Way%2C%20Albert%20Town%209305%2C%20New%20Zealand&travelmode=driving&waypoints=Crown%20Range%20Summit%2C%20Crown%20Range%20Road%2C%20New%20Zealand%7CThat%20Wanaka%20Tree%2C%20Wanaka%2C%20New%20Zealand%7CDiamond%20Lake%20Conservation%20Area%2C%20Wanaka%2C%20New%20Zealand
A13: 46380 | B13: 12 | C13: Wanaka | D13: Dag 12 – Wanaka - Wandeling Roy's peak of Diamond Lake - Vrije middag bij het meer | H13: https://www.google.com/maps/dir/?api=1&origin=19A%20Kidds%20Way%2C%20Albert%20Town%209305%2C%20New%20Zealand&destination=19A%20Kidds%20Way%2C%20Albert%20Town%209305%2C%20New%20Zealand&travelmode=driving&waypoints=Diamond%20Lake%20Conservation%20Area%2C%20Wanaka%2C%20New%20Zealand%7CLake%20Wanaka%2C%20Wanaka%2C%20New%20Zealand%7CWanaka%20Lakefront%2C%20Wanaka%2C%20New%20Zealand | I13: https://www.komoot.com/nl-nl/tour/2616240586 https://www.komoot.com/nl-nl/tour/2617873194 https://www.komoot.com/nl-nl/tour/2616244397
A14: 46381 | B14: 13 | C14: Franz Josef | D14: Dag 13 – Franz Josef - Rit via Haast Pass (ca. 5-6 uur als, stops bij watervallen) - Avondwandeling in Franz Josef | E14: 285 km | F14: 4u30 | H14: https://www.google.com/maps/dir/?api=1&origin=19A%20Kidds%20Way%2C%20Albert%20Town%209305%2C%20New%20Zealand&destination=46%20Cron%20Street%2C%20Franz%20Josef%207886%2C%20New%20Zealand&travelmode=driving&waypoints=Blue%20Pools%20Track%2C%20Haast%20Pass%20Highway%2C%20New%20Zealand%7CFantail%20Falls%2C%20Haast%20Pass%2C%20New%20Zealand%7CThunder%20Creek%20Falls%2C%20Haast%20Pass%20Highway%2C%20New%20Zealand | I14: https://www.komoot.com/nl-nl/tour/2617913044
A15: 46382 | B15: 14 | C15: Franz Josef | D15: Dag 14 – Franz Josef - Wandeling naar Glacier Viewpoint - Relax in de Glacier Hot Pools | H15: https://www.google.com/maps/dir/?api=1&origin=46%20Cron%20Street%2C%20Franz%20Josef%207886%2C%20New%20Zealand&destination=46%20Cron%20Street%2C%20Franz%20Josef%207886%2C%20New%20Zealand&travelmode=driving&waypoints=Franz%20Josef%20Glacier%20Walk%2C%20Franz%20Josef%2C%20New%20Zealand%7CWaiho%20Hot%20Tubs%2C%2064B%20Cron%20Street%2C%20Franz%20Josef%2C%20New%20Zealand | I15: https://www.komoot.com/nl-nl/tour/2616272589 https://www.komoot.com/nl-nl/tour/2617641037 https://www.komoot.com/nl-nl/tour/2617841774 https://www.komoot.com/nl-nl/tour/2617636994 https://www.komoot.com/nl-nl/tour/2617918883 https://www.komoot.com/nl-nl/tour/2617616890 https://www.komoot.com/nl-nl/tour/2617639131
A16: 46383 | B16: 15 | C16: Punakaiki | D16: Dag 15 – Punakaiki - Rit naar Punakaiki - Bezoek Pancake Rocks & Blowholes - kayaken over rivier of Pororari track 7km 2 u - Overnachting bij de kust | E16: 225 km | F16: 3u30 | G16: https://riverkayaking.co.nz/ | H16: https://www.google.com/maps/dir/?api=1&origin=46%20Cron%20Street%2C%20Franz%20Josef%207886%2C%20New%20Zealand&destination=Mabel%20Street%2C%20Punakaiki%207873%2C%20New%20Zealand&travelmode=driving&waypoints=Hokitika%20Beach%2C%20Hokitika%2C%20New%20Zealand%7CPancake%20Rocks%20and%20Blowholes%2C%20Punakaiki%2C%20New%20Zealand%7CPororari%20River%20Track%2C%20Punakaiki%2C%20New%20Zealand | I16: https://www.komoot.com/nl-nl/tour/2617932341 https://www.komoot.com/nl-nl/tour/2617930576
A17: 46384 | B17: 16 | C17: Abel Tasman | D17: Dag 16 – Abel Tasman NP - Rit naar Abel Tasman (ca. 5 uur) - Avondwandeling of relaxen bij de kust | E17: 290 km | F17: 4u30 | H17: https://www.google.com/maps/dir/?api=1&origin=Mabel%20Street%2C%20Punakaiki%207873%2C%20New%20Zealand&destination=14%20Harvey%20Road%2C%20Marahau%207197%2C%20New%20Zealand&travelmode=driving&waypoints=Nelson%2C%20New%20Zealand%7CKaiteriteri%20Beach%2C%20Kaiteriteri%2C%20New%20Zealand%7CMarahau%20Beach%2C%20Marahau%2C%20New%20Zealand | I17: https://www.komoot.com/nl-nl/tour/2617924397 https://www.komoot.com/nl-nl/tour/2616268015
A18: 46385 | B18: 17 | C18: Abel Tasman | D18: Dag 17 – Abel Tasman NP - Hike dag 1 | H18: https://www.google.com/maps/dir/?api=1&origin=14%20Harvey%20Road%2C%20Marahau%207197%2C%20New%20Zealand&destination=14%20Harvey%20Road%2C%20Marahau%207197%2C%20New%20Zealand&travelmode=walking&waypoints=Abel%20Tasman%20Coast%20Track%20Marahau%20Entrance%2C%20Marahau%2C%20New%20Zealand%7CAbel%20Tasman%20AquaTaxi%2C%20Marahau%2C%20New%20Zealand | I18: https://www.komoot.com/nl-nl/tour/2711227413
A19: 46386 | B19: 18 | C19: Abel Tasman | D19: Dag 18 – Abel Tasman NP - Hike dag 2 | H19: https://www.google.com/maps/dir/?api=1&origin=14%20Harvey%20Road%2C%20Marahau%207197%2C%20New%20Zealand&destination=14%20Harvey%20Road%2C%20Marahau%207197%2C%20New%20Zealand&travelmode=walking&waypoints=Abel%20Tasman%20AquaTaxi%2C%20Marahau%2C%20New%20Zealand%7CAbel%20Tasman%20Coast%20Track%20Marahau%20Entrance%2C%20Marahau%2C%20New%20Zealand
A20: 46387 | B20: 19 | C20: Pohara | D20: Dag 19 – Pohara Beach - Te Waikoropupu Springs (kan daar ook forelvissen in buurt) - Labyrinth Rocks - Paines Ford (zwemmen in rivier) - Pohara Beach | E20: 60 km | F20: 1u | H20: https://www.google.com/maps/dir/?api=1&origin=14%20Harvey%20Road%2C%20Marahau%207197%2C%20New%20Zealand&destination=40%20Ruataniwha%20Drive%2C%20Collingwood%207073%2C%20New%20Zealand&travelmode=driving&waypoints=Paines%20Ford%20Scenic%20Reserve%2C%20Takaka%2C%20New%20Zealand%7CLabyrinth%20Rocks%2C%20Takaka%2C%20New%20Zealand%7CPohara%20Beach%2C%20Pohara%2C%20New%20Zealand%7CTe%20Waikoropupu%20Springs%2C%20Takaka%2C%20New%20Zealand
A21: 46388 | B21: 20 | C21: Pohara | D21: Dag 20 – Pohara Beach - Golden by Kayaks tot 12:30 | G21: https://www.goldenbaykayaks.co.nz/guided-kayak-tour-options | H21: https://www.google.com/maps/dir/?api=1&origin=40%20Ruataniwha%20Drive%2C%20Collingwood%207073%2C%20New%20Zealand&destination=40%20Ruataniwha%20Drive%2C%20Collingwood%207073%2C%20New%20Zealand&travelmode=driving&waypoints=Golden%20Bay%20Kayaks%2C%2029%20Cornwall%20Place%2C%20Tata%20Beach%2C%20New%20Zealand%7CWainui%20Bay%2C%20Tasman%2C%20New%20Zealand%7CPohara%20Beach%2C%20Pohara%2C%20New%20Zealand
A22: 46389 | B22: 21 | D22: Dag 21 – Picton - Rit naar Nelson 1u40 (3 uurtjes in stad) - rit naar Pelorus Bridge voor zwemmen en koffie - rit naar Picton voor overnachting | E22: 230 km | F22: 3u 30 | H22: https://www.google.com/maps/dir/?api=1&origin=40%20Ruataniwha%20Drive%2C%20Collingwood%207073%2C%20New%20Zealand&destination=113%20High%20Street%2C%20Picton%207220%2C%20New%20Zealand&travelmode=driving&waypoints=Nelson%2C%20New%20Zealand%7CPelorus%20Bridge%20Scenic%20Reserve%2C%20New%20Zealand%7CPicton%20Waterfront%2C%20Picton%2C%20New%20Zealand | I22: https://www.komoot.com/nl-nl/tour/2617944045
A23: 46390 | B23: 22 | C23: Wellington | D23: Dag 22 – Wellington | H23: https://www.google.com/maps/dir/?api=1&origin=113%20High%20Street%2C%20Picton%207220%2C%20New%20Zealand&destination=Wellington%20CBD%2C%20Wellington%206011%2C%20New%20Zealand&travelmode=driving&waypoints=Interislander%20Vehicle%20Check-In%2C%20Lagoon%20Road%2C%20Picton%2C%20New%20Zealand%7CInterislander%20Wellington%20Terminal%2C%20Kaiwharawhara%2C%20Wellington%2C%20New%20Zealand
A24: 46391 | B24: 23 | C24: Wellington | D24: Dag 23 – Wellington | H24: https://www.google.com/maps/dir/?api=1&origin=Wellington%20CBD%2C%20Wellington%206011%2C%20New%20Zealand&destination=Wellington%20CBD%2C%20Wellington%206011%2C%20New%20Zealand&travelmode=driving&waypoints=Museum%20of%20New%20Zealand%20Te%20Papa%20Tongarewa%2C%20Wellington%2C%20New%20Zealand%7CWellington%20Cable%20Car%2C%20Lambton%20Quay%2C%20Wellington%2C%20New%20Zealand%7CMount%20Victoria%20Lookout%2C%20Wellington%2C%20New%20Zealand%7COriental%20Bay%2C%20Wellington%2C%20New%20Zealand
A25: 46392 | B25: 24 | C25: Taranaki | D25: Dag 24 – Stratford (Mt Taranaki) | H25: https://www.google.com/maps/dir/?api=1&origin=Wellington%20CBD%2C%20Wellington%206011%2C%20New%20Zealand&destination=1801%20Mangorei%20Road%2C%20New%20Plymouth%204371%2C%20New%20Zealand&travelmode=driving&waypoints=Whanganui%20Riverfront%2C%20Whanganui%2C%20New%20Zealand%7CStratford%20Glockenspiel%2C%20Stratford%2C%20New%20Zealand
A26: 46393 | C26: Taranaki | D26: Dag 25 – Mt Taranaki - Dawson Falls Visitor Centre Goblin Forest + Wilkies Pools - North Egmont Visitor Centre + Manganui Gorge Track - Lake Mangamahoe | H26: https://www.google.com/maps/dir/?api=1&origin=1801%20Mangorei%20Road%2C%20New%20Plymouth%204371%2C%20New%20Zealand&destination=1801%20Mangorei%20Road%2C%20New%20Plymouth%204371%2C%20New%20Zealand&travelmode=driving&waypoints=Dawson%20Falls%20Visitor%20Centre%2C%20Egmont%20National%20Park%2C%20New%20Zealand%7CWilkies%20Pools%20Loop%20Track%2C%20Egmont%20National%20Park%2C%20New%20Zealand%7CNorth%20Egmont%20Visitor%20Centre%2C%20New%20Zealand%7CLake%20Mangamahoe%2C%20New%20Plymouth%2C%20New%20Zealand | I26: https://www.komoot.com/nl-nl/tour/2616132950 https://www.komoot.com/nl-nl/tour/2616135234 https://www.komoot.com/nl-nl/tour/2616103465 https://www.komoot.com/nl-nl/tour/2616116563 https://www.komoot.com/nl-nl/tour/2616140903
A27: 46394 | B27: 25 | C27: Waitomo | D27: Dag 26 – Waitomo | E27: 220 km | F27: 3u | H27: https://www.google.com/maps/dir/?api=1&origin=1801%20Mangorei%20Road%2C%20New%20Plymouth%204371%2C%20New%20Zealand&destination=12%20Waitomo%20Village%20Road%2C%20Waitomo%20Caves%203977%2C%20New%20Zealand&travelmode=driving&waypoints=Waitomo%20Glowworm%20Caves%2C%20Waitomo%2C%20New%20Zealand
A28: 46395 | B28: 26 | C28: Taupo | D28: Dag 27 – Taupo - Bezoek Huka Falls - Boottocht naar Maori Rock Carvings | H28: https://www.google.com/maps/dir/?api=1&origin=12%20Waitomo%20Village%20Road%2C%20Waitomo%20Caves%203977%2C%20New%20Zealand&destination=76%20Napier-Taupo%20Road%2C%20Taupo%203330%2C%20New%20Zealand&travelmode=driving&waypoints=Huka%20Falls%2C%20Taupo%2C%20New%20Zealand%7CTaupo%20Boat%20Harbour%2C%20Taupo%2C%20New%20Zealand%7CMaori%20Rock%20Carvings%20Cruise%2C%20Taupo%2C%20New%20Zealand
A29: 46396 | B29: 27 | C29: Taupo | D29: Dag 28 – Taupo | E29: 220 km | F29: 3u30 | H29: https://www.google.com/maps/dir/?api=1&origin=76%20Napier-Taupo%20Road%2C%20Taupo%203330%2C%20New%20Zealand&destination=76%20Napier-Taupo%20Road%2C%20Taupo%203330%2C%20New%20Zealand&travelmode=driving&waypoints=Craters%20of%20the%20Moon%2C%20Taupo%2C%20New%20Zealand%7CAratiatia%20Rapids%2C%20Taupo%2C%20New%20Zealand%7CTaupo%20Lakefront%2C%20Taupo%2C%20New%20Zealand
A30: 46397 | B30: 28 | C30: Tongariro NP | D30: Dag 29 – Taupo / Tongariro NP | H30: https://www.google.com/maps/dir/?api=1&origin=76%20Napier-Taupo%20Road%2C%20Taupo%203330%2C%20New%20Zealand&destination=76%20Napier-Taupo%20Road%2C%20Taupo%203330%2C%20New%20Zealand&travelmode=driving&waypoints=Whakapapa%20Visitor%20Centre%2C%20Tongariro%20National%20Park%2C%20New%20Zealand%7CTaranaki%20Falls%20Track%2C%20Tongariro%20National%20Park%2C%20New%20Zealand%7CMangatepopo%20Car%20Park%2C%20Tongariro%20National%20Park%2C%20New%20Zealand | I30: https://www.komoot.com/nl-nl/tour/2730441355 https://www.komoot.com/nl-nl/tour/2730497120 https://www.komoot.com/nl-nl/tour/2737103944
A31: 46398 | B31: 29 | C31: Taupo | D31: Dag 30 – Taupo | E31: 75 km | F31: 1u | H31: https://www.google.com/maps/dir/?api=1&origin=76%20Napier-Taupo%20Road%2C%20Taupo%203330%2C%20New%20Zealand&destination=76%20Napier-Taupo%20Road%2C%20Taupo%203330%2C%20New%20Zealand&travelmode=driving&waypoints=Spa%20Thermal%20Park%2C%20Taupo%2C%20New%20Zealand%7CTaupo%20Lakefront%2C%20Taupo%2C%20New%20Zealand
A32: 46399 | B32: 30 | C32: Rotorua | D32: Dag 31 – Rotorua - Rit naar Rotorua (ca. 1 uur) - Bezoek Wai-o-Tapu of Te Puia (geisers, modderpoelen) - Maori diner & show | H32: https://www.google.com/maps/dir/?api=1&origin=76%20Napier-Taupo%20Road%2C%20Taupo%203330%2C%20New%20Zealand&destination=436%20Ngongotaha%20Road%2C%20Rotorua%203015%2C%20New%20Zealand&travelmode=driving&waypoints=Wai-O-Tapu%20Thermal%20Wonderland%2C%20Rotorua%2C%20New%20Zealand%7CTe%20Puia%2C%20Hemo%20Road%2C%20Rotorua%2C%20New%20Zealand
A33: 46400 | B33: 31 | C33: Rotorua | D33: Dag 32 – Rotorua - Wandel door Redwoods Forest (suspension bridges) - Middag spa bij Polynesian Spa | E33: 75 km | F33: 1u | H33: https://www.google.com/maps/dir/?api=1&origin=436%20Ngongotaha%20Road%2C%20Rotorua%203015%2C%20New%20Zealand&destination=436%20Ngongotaha%20Road%2C%20Rotorua%203015%2C%20New%20Zealand&travelmode=driving&waypoints=Redwoods%20Treewalk%2C%20Rotorua%2C%20New%20Zealand%7CPolynesian%20Spa%2C%20Rotorua%2C%20New%20Zealand%7CRotorua%20Lakefront%2C%20Rotorua%2C%20New%20Zealand
A34: 46401 | B34: 32 | C34: Coromandel | D34: Dag 33 – Coromandel - Rit naar Coromandel (ca. 3 uur excl stops) - via Putaruru Blue Spring - Riverside Adventures Waikato (3 uur durende tour 9:30am and 1:30pm) | E34: 80 km | F34: 1u | G34: https://www.riversideadventures.co.nz/daytime-canyon-kayak-tour/ | H34: https://www.google.com/maps/dir/?api=1&origin=436%20Ngongotaha%20Road%2C%20Rotorua%203015%2C%20New%20Zealand&destination=790%20Hot%20Water%20Beach%20Road%2C%20Whitianga%203591%2C%20New%20Zealand&travelmode=driving&waypoints=Blue%20Spring%20Te%20Waihou%20Walkway%2C%20Leslie%20Road%2C%20Putaruru%2C%20New%20Zealand%7CRiverside%20Adventures%20Waikato%2C%20396%20Horahora%20Road%2C%20Piarere%2C%20New%20Zealand
A35: 46402 | B35: 33 | C35: Coromandel | D35: Dag 34 – Coromandel - Bezoek Hot Water Beach - Wandeling naar Cathedral Cove | E35: 160 km | F35: 2u40 | G35: https://www.haheiholidays.co.nz/ | H35: https://www.google.com/maps/dir/?api=1&origin=790%20Hot%20Water%20Beach%20Road%2C%20Whitianga%203591%2C%20New%20Zealand&destination=790%20Hot%20Water%20Beach%20Road%2C%20Whitianga%203591%2C%20New%20Zealand&travelmode=driving&waypoints=Hot%20Water%20Beach%2C%20Waikato%2C%20New%20Zealand%7CCathedral%20Cove%20Gateway%20Trail%2C%20150%20Lees%20Road%2C%20Hahei%2C%20New%20Zealand%7CHahei%20Beach%2C%20Hahei%2C%20New%20Zealand | I35: https://www.komoot.com/nl-nl/tour/2616122360
A36: 46403 | B36: 34 | C36: Coromandel | D36: Dag 35 – Coromandel - Hahei | H36: https://www.google.com/maps/dir/?api=1&origin=790%20Hot%20Water%20Beach%20Road%2C%20Whitianga%203591%2C%20New%20Zealand&destination=790%20Hot%20Water%20Beach%20Road%2C%20Whitianga%203591%2C%20New%20Zealand&travelmode=driving&waypoints=Hahei%20Beach%2C%20Hahei%2C%20New%20Zealand%7CCooks%20Beach%2C%20Waikato%2C%20New%20Zealand%7CShakespeare%20Cliff%20Lookout%2C%20Cooks%20Beach%2C%20New%20Zealand
A37: 46404 | B37: 35 | C37: Coromandel | D37: Dag 36 – Coromandel - Verken kustwegen - Optioneel: kajakken of dolfijnentocht | H37: https://www.google.com/maps/dir/?api=1&origin=790%20Hot%20Water%20Beach%20Road%2C%20Whitianga%203591%2C%20New%20Zealand&destination=790%20Hot%20Water%20Beach%20Road%2C%20Whitianga%203591%2C%20New%20Zealand&travelmode=driving&waypoints=Whitianga%20Wharf%2C%20Whitianga%2C%20New%20Zealand%7CKuaotunu%20Beach%2C%20Waikato%2C%20New%20Zealand%7CNew%20Chums%20Beach%20Track%2C%20Whangapoua%2C%20New%20Zealand%7CCoromandel%20Town%2C%20New%20Zealand
A38: 46405 | B38: 36 | C38: Coromandel | D38: Dag 37 – Coromandel | H38: https://www.google.com/maps/dir/?api=1&origin=790%20Hot%20Water%20Beach%20Road%2C%20Whitianga%203591%2C%20New%20Zealand&destination=790%20Hot%20Water%20Beach%20Road%2C%20Whitianga%203591%2C%20New%20Zealand&travelmode=driving&waypoints=Hot%20Water%20Beach%2C%20Waikato%2C%20New%20Zealand
A39: 46406 | B39: 37 | C39: Auckland | D39: Dag 38 – Auckland - Rit naar Auckland (ca. 4 uur) - Middag/avond in de stad | E39: 170 km | F39: 2u30 | H39: https://www.google.com/maps/dir/?api=1&origin=790%20Hot%20Water%20Beach%20Road%2C%20Whitianga%203591%2C%20New%20Zealand&destination=71%20Mayoral%20Drive%2C%20corner%20Vincent%20Street%2C%20Auckland%201010%2C%20New%20Zealand&travelmode=driving&waypoints=Thames%2C%20New%20Zealand%7CMount%20Eden%20Summit%2C%20Auckland%2C%20New%20Zealand%7CViaduct%20Harbour%2C%20Auckland%2C%20New%20Zealand
A40: 46407 | B40: 38 | C40: Auckland | D40: Dag 39 – Auckland - Middag/avond in de stad | H40: https://www.google.com/maps/dir/?api=1&origin=71%20Mayoral%20Drive%2C%20corner%20Vincent%20Street%2C%20Auckland%201010%2C%20New%20Zealand&destination=71%20Mayoral%20Drive%2C%20corner%20Vincent%20Street%2C%20Auckland%201010%2C%20New%20Zealand&travelmode=driving&waypoints=Sky%20Tower%2C%20Auckland%2C%20New%20Zealand%7CAuckland%20War%20Memorial%20Museum%2C%20Auckland%2C%20New%20Zealand%7CMount%20Eden%20Summit%2C%20Auckland%2C%20New%20Zealand%7CViaduct%20Harbour%2C%20Auckland%2C%20New%20Zealand
A41: 46408 | B41: 39 | C41: Auckland | D41: Auckland ➔ Singapore | H41: https://www.google.com/maps/dir/?api=1&origin=71%20Mayoral%20Drive%2C%20corner%20Vincent%20Street%2C%20Auckland%201010%2C%20New%20Zealand&destination=Auckland%20Airport%20International%20Terminal%2C%20Auckland%2C%20New%20Zealand&travelmode=driving

Sheet Dagplanning - Singapore
A1: Datum | B1: Dag | C1: Route | D1: Beschrijving | E1: Afstand | F1: Reistijd | G1: informatie | H1: Google Maps-route | I1: Komoot wandeling
A2: 46408 | B2: 1 | C2: Singapore | D2: Dag 1 – Aankomst | G2: https://www.rwsentosa.com/en/play/universal-studios-singapore | H2: https://www.google.com/maps/dir/?api=1&origin=Grand%20Copthorne%20Waterfront%20Singapore%2C%20392%20Havelock%20Road%2C%20Singapore%20169663&destination=Grand%20Copthorne%20Waterfront%20Singapore%2C%20392%20Havelock%20Road%2C%20Singapore%20169663&travelmode=walking&waypoints=Robertson%20Quay%2C%20Singapore%7CSingapore%20River%20Promenade%2C%20Singapore%7CClarke%20Quay%2C%20Singapore
A3: 46409 | B3: 2 | C3: Singapore | D3: Dag 2 – Marina Bay & Gardens by the Bay Ochtend - Wandeling bij Marina Bay → foto bij Merlion Park - Eventueel Singapore River boottocht (45 min) Middag - Lunch in hawker center (Lau Pa Sat of Satay by the Bay) - Gardens by the Bay: - Flower Dome + Cloud Forest - Gratis: SuperTree Grove wandeling - Kids spelen in waterzone / kleine speeltuin Avond - Supertree Grove lightshow (19:45 & 20:45) - Optioneel: Marina Bay Sands SkyPark voor uitzicht | G3: https://www.rwsentosa.com/en/play/universal-studios-singapore | H3: https://www.google.com/maps/dir/?api=1&origin=Grand%20Copthorne%20Waterfront%20Singapore%2C%20392%20Havelock%20Road%2C%20Singapore%20169663&destination=Grand%20Copthorne%20Waterfront%20Singapore%2C%20392%20Havelock%20Road%2C%20Singapore%20169663&travelmode=driving&waypoints=Singapore%20River%20Cruise%2C%20Clarke%20Quay%20Jetty%2C%20Singapore%7CMerlion%20Park%2C%20Singapore%7CLau%20Pa%20Sat%2C%2018%20Raffles%20Quay%2C%20Singapore%7CMarina%20Bay%20Sands%20SkyPark%20Observation%20Deck%2C%20Singapore%7CFlower%20Dome%2C%20Gardens%20by%20the%20Bay%2C%20Singapore%7CCloud%20Forest%2C%20Gardens%20by%20the%20Bay%2C%20Singapore%7CFar%20East%20Organization%20Children's%20Garden%2C%20Singapore%7CSupertree%20Grove%2C%20Singapore
A4: 46410 | B4: 3 | C4: Singapore | D4: Dag 3 – Wildlife & Night Safari Ochtend - Mandai 5‑parks pass: begin bij Singapore Zoo - Orang-oetans, primaten, Splash Playground - Rustmoment / snackpauze Middag - River Wonders: panda’s, bootje, kindvriendelijk - Terug naar hotel → rust Avond - Night Safari (tram door de jungle, ±19:30–22:00) - Eten bij het park of hotel | G4: https://www.mandai.com/en/discover-mandai.html | H4: https://www.google.com/maps/dir/?api=1&origin=Grand%20Copthorne%20Waterfront%20Singapore%2C%20392%20Havelock%20Road%2C%20Singapore%20169663&destination=Grand%20Copthorne%20Waterfront%20Singapore%2C%20392%20Havelock%20Road%2C%20Singapore%20169663&travelmode=driving&waypoints=Singapore%20Zoo%2C%2080%20Mandai%20Lake%20Road%2C%20Singapore%20729826%7CRiver%20Wonders%2C%2080%20Mandai%20Lake%20Road%2C%20Singapore%20729826%7CGrand%20Copthorne%20Waterfront%20Singapore%2C%20392%20Havelock%20Road%2C%20Singapore%20169663%7CNight%20Safari%2C%2080%20Mandai%20Lake%20Road%2C%20Singapore%20729826
A5: 46411 | B5: 4 | D5: Dag 4 – Sentosa & Universal Studios Ochtend - Vroeg naar Sentosa eiland - Universal Studios Singapore (hele dag) - Leuk voor kinderen 7–9 jaar - Waterrides + shows Middag - Lunch in park of Sentosa (foodcourt / fastfood) - Meer attracties Universal Studios Avond - Optioneel relax bij Palawan of Siloso Beach - Terug naar stad → diner bij hotel / Clarke Quay | H5: https://www.google.com/maps/dir/?api=1&origin=Grand%20Copthorne%20Waterfront%20Singapore%2C%20392%20Havelock%20Road%2C%20Singapore%20169663&destination=Grand%20Copthorne%20Waterfront%20Singapore%2C%20392%20Havelock%20Road%2C%20Singapore%20169663&travelmode=driving&waypoints=Universal%20Studios%20Singapore%2C%208%20Sentosa%20Gateway%2C%20Singapore%20098269%7CPalawan%20Beach%2C%20Sentosa%2C%20Singapore%7CSiloso%20Beach%2C%20Sentosa%2C%20Singapore%7CClarke%20Quay%2C%20Singapore
A6: 46412 | B6: 5 | D6: Dag 5 - Vertrek | H6: https://www.google.com/maps/dir/?api=1&origin=Grand%20Copthorne%20Waterfront%20Singapore%2C%20392%20Havelock%20Road%2C%20Singapore%20169663&destination=Singapore%20Changi%20Airport%2C%20Airport%20Boulevard%2C%20Singapore&travelmode=driving

Sheet Dagplanning - Thailand en Qatar
A1: Datum | B1: Dag | C1: Route | D1: Beschrijving | E1: Afstand | F1: Reistijd | G1: informatie | H1: Google Maps-route | I1: Komoot wandeling
A2: 46412 | B2: 1 | C2: Singapore ➔ Phuket ➔ Khao Lak | D2: Dag 1 – Aankomst & door naar Khao Lak - Aankomst Phuket (14:05) - Transfer naar Khao Lak (ca. 1 uur) - Inchecken en rustig bijkomen - Korte strandwandeling | H2: https://www.google.com/maps/dir/?api=1&origin=Grand%20Copthorne%20Waterfront%20Singapore%2C%20392%20Havelock%20Road%2C%20Singapore%20169663&destination=The%20Sands%20Khao%20Lak%20by%20Katathani%2C%2010%2F18%20Petchkasem%20Road%2C%20Moo%207%2C%20Khuk%20Khak%2C%20Takua%20Pa%2C%20Phang%20Nga%2082220%2C%20Thailand&travelmode=transit&waypoints=Singapore%20Changi%20Airport%2C%20Singapore%7CPhuket%20International%20Airport%2C%20Phuket%2C%20Thailand
A3: 46413 | B3: 2 | C3: Khao Lak | D3: Dag 2 – Strand & relax - Rustig opstarten - Strand en zwembad - Eventueel massage of relaxmoment - olifanten opvang? | H3: https://www.google.com/maps/dir/?api=1&origin=The%20Sands%20Khao%20Lak%20by%20Katathani%2C%2010%2F18%20Petchkasem%20Road%2C%20Moo%207%2C%20Khuk%20Khak%2C%20Takua%20Pa%2C%20Phang%20Nga%2082220%2C%20Thailand&destination=The%20Sands%20Khao%20Lak%20by%20Katathani%2C%2010%2F18%20Petchkasem%20Road%2C%20Moo%207%2C%20Khuk%20Khak%2C%20Takua%20Pa%2C%20Phang%20Nga%2082220%2C%20Thailand&travelmode=walking&waypoints=Nang%20Thong%20Beach%2C%20Khao%20Lak%2C%20Thailand%7CKhao%20Lak%20Center%2C%20Phang%20Nga%2C%20Thailand
A4: 46414 | B4: 3 | C4: Khao Lak | D4: Dag 3 – Natuur & lokaal - Bezoek Khao Lak–Lam Ru National Park - Junglewandeling en waterval - Middag strand - Avondmarkt Optioneel snorkeltrip Similan/Surin eilanden | H4: https://www.google.com/maps/dir/?api=1&origin=The%20Sands%20Khao%20Lak%20by%20Katathani%2C%2010%2F18%20Petchkasem%20Road%2C%20Moo%207%2C%20Khuk%20Khak%2C%20Takua%20Pa%2C%20Phang%20Nga%2082220%2C%20Thailand&destination=The%20Sands%20Khao%20Lak%20by%20Katathani%2C%2010%2F18%20Petchkasem%20Road%2C%20Moo%207%2C%20Khuk%20Khak%2C%20Takua%20Pa%2C%20Phang%20Nga%2082220%2C%20Thailand&travelmode=driving&waypoints=Khao%20Lak-Lam%20Ru%20National%20Park%20Visitor%20Center%2C%20Phang%20Nga%2C%20Thailand%7CTon%20Chong%20Fa%20Waterfall%2C%20Khuekkhak%2C%20Phang%20Nga%2C%20Thailand%7CBang%20Niang%20Market%2C%20Khao%20Lak%2C%20Thailand
A5: 46415 | B5: 4 | C5: Khao Lak | D5: Dag 4 – Naar Khao Sok - Transfer naar Khao Sok National Park (ca. 2 uur) - Incheck jungle lodge - Rivierwandeling of tubing | H5: https://www.google.com/maps/dir/?api=1&origin=The%20Sands%20Khao%20Lak%20by%20Katathani%2C%2010%2F18%20Petchkasem%20Road%2C%20Moo%207%2C%20Khuk%20Khak%2C%20Takua%20Pa%2C%20Phang%20Nga%2082220%2C%20Thailand&destination=Magical%20Mountain%20View%20Resort%2C%20292%2F1%20Moo%207%2C%20Khlong%20Sok%2C%20Phanom%2C%20Surat%20Thani%2084250%2C%20Thailand&travelmode=driving&waypoints=Khao%20Sok%20National%20Park%20Visitor%20Center%2C%20Khlong%20Sok%2C%20Thailand%7CSok%20River%2C%20Khlong%20Sok%2C%20Thailand
A6: 46416 | B6: 5 | C6: Khao Sok | D6: Dag 5 – Cheow Lan Lake - Boottocht tussen kalksteenrotsen - Kajakken en zwemmen - Overnachting drijvende bungalow | H6: https://www.google.com/maps/dir/?api=1&origin=Magical%20Mountain%20View%20Resort%2C%20292%2F1%20Moo%207%2C%20Khlong%20Sok%2C%20Phanom%2C%20Surat%20Thani%2084250%2C%20Thailand&destination=Cheow%20Lan%20Lake%2C%20Khao%20Phang%2C%20Ban%20Ta%20Khun%20District%2C%20Surat%20Thani%2C%20Thailand&travelmode=driving&waypoints=Ratchaprapha%20Dam%20Scenic%20Viewpoint%2C%20Surat%20Thani%2C%20Thailand%7CRatchaprapha%20Marina%2C%20Ban%20Ta%20Khun%2C%20Surat%20Thani%2C%20Thailand
A7: 46417 | B7: 6 | C7: Khao Sok | D7: Dag 6 – Transfer + ferry naar Koh Lanta (±3–4 uur) Inchecken in resort aan Long Beach (Phra Ae Beach) Strandmiddag, zwemmen en relaxen | H7: https://www.google.com/maps/dir/?api=1&origin=Cheow%20Lan%20Lake%2C%20Khao%20Phang%2C%20Ban%20Ta%20Khun%20District%2C%20Surat%20Thani%2C%20Thailand&destination=Sai%20Naam%20Lanta%20Residence%2C%20541%2F2%20Moo%202%2C%20Long%20Beach%2C%20Saladan%2C%20Koh%20Lanta%2C%20Krabi%2081150%2C%20Thailand&travelmode=driving&waypoints=Ratchaprapha%20Marina%2C%20Ban%20Ta%20Khun%2C%20Surat%20Thani%2C%20Thailand%7CHua%20Hin%20Pier%2C%20Khlong%20Yang%2C%20Krabi%2C%20Thailand
A8: 46418 | B8: 7 | C8: Khao Sok | D8: Dag 7 – korte boottochtje naar dichtbijgelegen eilandje of mangrove kajak (met gids) | H8: https://www.google.com/maps/dir/?api=1&origin=Sai%20Naam%20Lanta%20Residence%2C%20541%2F2%20Moo%202%2C%20Long%20Beach%2C%20Saladan%2C%20Koh%20Lanta%2C%20Krabi%2081150%2C%20Thailand&destination=Sai%20Naam%20Lanta%20Residence%2C%20541%2F2%20Moo%202%2C%20Long%20Beach%2C%20Saladan%2C%20Koh%20Lanta%2C%20Krabi%2081150%2C%20Thailand&travelmode=driving&waypoints=Thung%20Yee%20Pheng%20Mangrove%20Forest%2C%20Koh%20Lanta%2C%20Thailand%7CLong%20Beach%2C%20Koh%20Lanta%2C%20Thailand
A9: 46419 | B9: 8 | C9: Koh Lanta | D9: Dag 8 – Optioneel: korte snorkelexcursie bij nabijgelegen eilandjes | H9: https://www.google.com/maps/dir/?api=1&origin=Sai%20Naam%20Lanta%20Residence%2C%20541%2F2%20Moo%202%2C%20Long%20Beach%2C%20Saladan%2C%20Koh%20Lanta%2C%20Krabi%2081150%2C%20Thailand&destination=Sai%20Naam%20Lanta%20Residence%2C%20541%2F2%20Moo%202%2C%20Long%20Beach%2C%20Saladan%2C%20Koh%20Lanta%2C%20Krabi%2081150%2C%20Thailand&travelmode=driving&waypoints=Saladan%20Pier%2C%20Koh%20Lanta%2C%20Thailand
A10: 46420 | B10: 9 | C10: Koh Lanta | D10: Dag 9 – Naar Koh Phi Phi - Boottransfer - Inchecken - Strand en korte verkenning | H10: https://www.google.com/maps/dir/?api=1&origin=Sai%20Naam%20Lanta%20Residence%2C%20541%2F2%20Moo%202%2C%20Long%20Beach%2C%20Saladan%2C%20Koh%20Lanta%2C%20Krabi%2081150%2C%20Thailand&destination=Long%20Beach%2C%20Ko%20Phi%20Phi%20Don%2C%20Krabi%2C%20Thailand&travelmode=transit&waypoints=Saladan%20Pier%2C%20Koh%20Lanta%2C%20Thailand%7CTonsai%20Pier%2C%20Ko%20Phi%20Phi%20Don%2C%20Thailand
A11: 46421 | B11: 10 | C11: Koh Lanta | D11: Dag 10 – Ferry naar Koh Phi Phi (±1,5 uur) Stranddag - Zwemmen en snorkelen - Relaxen | H11: https://www.google.com/maps/dir/?api=1&origin=Long%20Beach%2C%20Ko%20Phi%20Phi%20Don%2C%20Krabi%2C%20Thailand&destination=Long%20Beach%2C%20Ko%20Phi%20Phi%20Don%2C%20Krabi%2C%20Thailand&travelmode=walking&waypoints=Tonsai%20Pier%2C%20Ko%20Phi%20Phi%20Don%2C%20Thailand%7CLoh%20Dalum%20Beach%2C%20Ko%20Phi%20Phi%20Don%2C%20Thailand
A12: 46422 | B12: 11 | C12: Koh Lanta | D12: Dag 11 – Stranddag -Maya Bay - Vroege boottocht - Maya Bay en Bamboo Island - Middag vrij | H12: https://www.google.com/maps/dir/?api=1&origin=Long%20Beach%2C%20Ko%20Phi%20Phi%20Don%2C%20Krabi%2C%20Thailand&destination=Long%20Beach%2C%20Ko%20Phi%20Phi%20Don%2C%20Krabi%2C%20Thailand&travelmode=walking&waypoints=Tonsai%20Pier%2C%20Ko%20Phi%20Phi%20Don%2C%20Thailand%7CMaya%20Bay%2C%20Ko%20Phi%20Phi%20Leh%2C%20Thailand%7CBamboo%20Island%2C%20Krabi%2C%20Thailand
A13: 46423 | B13: 12 | C13: Koh Lanta | D13: Dag 12 – Zwemmen bij stranden (Loh Dalum, Long Beach) | H13: https://www.google.com/maps/dir/?api=1&origin=Long%20Beach%2C%20Ko%20Phi%20Phi%20Don%2C%20Krabi%2C%20Thailand&destination=Long%20Beach%2C%20Ko%20Phi%20Phi%20Don%2C%20Krabi%2C%20Thailand&travelmode=walking&waypoints=Loh%20Moo%20Dee%20Beach%2C%20Ko%20Phi%20Phi%20Don%2C%20Thailand%7CLoh%20Dalum%20Beach%2C%20Ko%20Phi%20Phi%20Don%2C%20Thailand
... A19: 46429 | B19: 18 | C19: Phuket ➔ Doha ochtend V 09:05 - A 12.30 | D19: Dag 18 – Transfer naar luchthaven - Vlucht 09:00 | H19: https://www.google.com/maps/dir/?api=1&origin=Baan%20Karon%20Resort%2C%20213%20Patak%20Road%2C%20Karon%2C%20Phuket%2083100%2C%20Thailand&destination=Phuket%20International%20Airport%2C%20International%20Terminal%2C%20222%20Moo%206%2C%20Mai%20Khao%2C%20Thalang%2C%20Phuket%2C%20Thailand&travelmode=driving
A20: 46430 | B20: 19 | C20: Doha | D20: Dag 19 - Hele dag doha
A21: 46431 | B21: 20 | C21: Doha ➔ Arusha V 08:15 - A 16:35

Sheet Dagplanning - Tanzania
A1: Datum | B1: Dag | C1: Route | D1: Beschrijving | E1: Afstand | F1: Reistijd | G1: informatie
A2: 46431 | B2: 1 | C2: Doha ➔ Arusha V 08:15 - A 16:35 | D2: Aankomst op Kilimanjaro International Airport | G2: Ilboru Safari Lodge; 2 Standard Double Room & 1 Family Interconnected Family (One room)
A3: 46432 | B3: 2 | C3: Tarangire | D3: Tarangire National Park | G3: Tarangire Safari Lodge; 2 Standard Double Room & 1 Standard Family (One room)
A4: 46433 | B4: 3 | C4: Tarangire | D4: Tarangire National Park | G4: Manyara Best View Lodge and Spa; 2 Standard Double Room & 1 Standard Family (One room)
A5: 46434 | B5: 4 | C5: Ndutu | D5: Ndutu (van eind december t/m maart tijdens het kalverseizoen van de Grote Trek) | G5: Kon Tiki Migration Tented Camp Ndutu; 2 Standard Tent Double Room & 1 Standard Tent Family (One room)
A6: 46435 | B6: 5 | C6: Ndutu | D6: Ndutu (van eind december t/m maart tijdens het kalverseizoen van de Grote Trek) | G6: Kon Tiki Migration Tented Camp Ndutu; 2 Standard Tent Double Room & 1 Standard Tent Family (One room)
A7: 46436 | B7: 6 | C7: Serengeti | D7: Serengeti National Park (centraal west/oost) | G7: Kubu Kubu Tented Lodge by Tanganyika Wilderness Camps; 2 Standard Double Room & 1 Standard Family (One room)
A8: 46437 | B8: 7 | C8: Serengeti | D8: Serengeti National Park (centraal west/oost) | G8: Kubu Kubu Tented Lodge by Tanganyika Wilderness Camps; 2 Standard Double Room & 1 Standard Family (One room)
A9: 46438 | B9: 8 | C9: Karatu | D9: Autorit van Serengeti naar Ngorongoro voor een overnachting | G9: Ang'ata Ngorongoro Camp; 2 Standard Tent Double Room & 1 Standard Tent Family (One room)
A10: 46439 | B10: 9 | C10: Karatu | D10: Ngorongoro Conservation Area (incl. krater) | G10: Manyara Best View Lodge and Spa; 2 Standard Double Room & 1 Standard Family (One room)
A11: 46440 | B11: 10 | C11: West Kilimanjaro → Kilimanjaro Airport → AMS | D11: Internationale vlucht huiswaarts vanaf Kilimanjaro Int. Airport | G11: —
